[ {
  "name" : "Sigal_Eduardo",
  "imports" : [ "Orbe_Walter", "Besttard_Sergio", "Iglesias_Perez_Juan_Carlos" ]
}, {
  "name" : "Orbe_Walter",
  "imports" : [ ]
}, {
  "name" : "Besttard_Sergio",
  "imports" : [ ]
}, {
  "name" : "Iglesias_Perez_Juan_Carlos",
  "imports" : [ ]
}, {
  "name" : "Amicarelli_Hugo",
  "imports" : [ "Collado_Horacio", "Bolla_Enrique", "Pilar_Jorge", "Rodriguez_Velo_Jorge_Nicolas", "Van_Houtum_Robert_Jan", "Kokrorev_Victor", "Santarelli_Hector_Gabriel", "Conocchiari_Alberto_Ruben", "Roggio_Alejandro__Arq", "Giuliani__Dr_Carlos", "Fernandez_Jose", "Joaquin_Alberto", "Clerici_Estela", "Mosca_Sabrina" ]
}, {
  "name" : "Collado_Horacio",
  "imports" : [ ]
}, {
  "name" : "Bolla_Enrique",
  "imports" : [ ]
}, {
  "name" : "Pilar_Jorge",
  "imports" : [ ]
}, {
  "name" : "Rodriguez_Velo_Jorge_Nicolas",
  "imports" : [ ]
}, {
  "name" : "Van_Houtum_Robert_Jan",
  "imports" : [ ]
}, {
  "name" : "Kokrorev_Victor",
  "imports" : [ ]
}, {
  "name" : "Santarelli_Hector_Gabriel",
  "imports" : [ ]
}, {
  "name" : "Conocchiari_Alberto_Ruben",
  "imports" : [ ]
}, {
  "name" : "Roggio_Alejandro__Arq",
  "imports" : [ ]
}, {
  "name" : "Giuliani__Dr_Carlos",
  "imports" : [ ]
}, {
  "name" : "Fernandez_Jose",
  "imports" : [ ]
}, {
  "name" : "Joaquin_Alberto",
  "imports" : [ ]
}, {
  "name" : "Clerici_Estela",
  "imports" : [ ]
}, {
  "name" : "Mosca_Sabrina",
  "imports" : [ ]
}, {
  "name" : "Bontempo_Luis_Alberto_Rafael",
  "imports" : [ "Lico_Miguel_Angel", "Selzer_Subsecretario_de_Vivienda_del_Gob_de_la_Ci_Ernesto", "Citadino_Adriana", "Morin_Juan_Jose", "Quiros_Julio", "Ferraresi_Jorge_Horacio" ]
}, {
  "name" : "Lico_Miguel_Angel",
  "imports" : [ ]
}, {
  "name" : "Selzer_Subsecretario_de_Vivienda_del_Gob_de_la_Ci_Ernesto",
  "imports" : [ ]
}, {
  "name" : "Citadino_Adriana",
  "imports" : [ ]
}, {
  "name" : "Morin_Juan_Jose",
  "imports" : [ ]
}, {
  "name" : "Quiros_Julio",
  "imports" : [ ]
}, {
  "name" : "Ferraresi_Jorge_Horacio",
  "imports" : [ ]
}, {
  "name" : "Moncalvillo_Adelina",
  "imports" : [ "Botas_Jorge" ]
}, {
  "name" : "Botas_Jorge",
  "imports" : [ ]
}, {
  "name" : "Suarez_Fernando",
  "imports" : [ "Gomez_Jorge", "Slokar_Alejandro", "Bozzano_Horacio", "Groppi_Alberto", "Yoris_Froilan_Luis", "Diaz_Zabala_Ignacio", "De_Vido_Julio", "Romero_Alfredo", "Di_Tullo_Hernan", "Guazzardi_Ricardo" ]
}, {
  "name" : "Gomez_Jorge",
  "imports" : [ ]
}, {
  "name" : "Slokar_Alejandro",
  "imports" : [ ]
}, {
  "name" : "Bozzano_Horacio",
  "imports" : [ ]
}, {
  "name" : "Groppi_Alberto",
  "imports" : [ ]
}, {
  "name" : "Yoris_Froilan_Luis",
  "imports" : [ ]
}, {
  "name" : "Diaz_Zabala_Ignacio",
  "imports" : [ ]
}, {
  "name" : "De_Vido_Julio",
  "imports" : [ ]
}, {
  "name" : "Romero_Alfredo",
  "imports" : [ ]
}, {
  "name" : "Di_Tullo_Hernan",
  "imports" : [ ]
}, {
  "name" : "Guazzardi_Ricardo",
  "imports" : [ ]
}, {
  "name" : "Gonzalez_Garcia_Gines",
  "imports" : [ "Iparraguirre_Maria_Veronica", "Mussin_Marta", "Guerina_Maria", "Sylvestre_Begnis_Juan", "Van_Trotsenburg_Axel", "Figueroa_Jose_Oscar", "Menehem_Jorge", "Baeza_Cristian", "Pereira_Julio", "Carli_Norberto" ]
}, {
  "name" : "Iparraguirre_Maria_Veronica",
  "imports" : [ ]
}, {
  "name" : "Mussin_Marta",
  "imports" : [ ]
}, {
  "name" : "Guerina_Maria",
  "imports" : [ ]
}, {
  "name" : "Sylvestre_Begnis_Juan",
  "imports" : [ ]
}, {
  "name" : "Van_Trotsenburg_Axel",
  "imports" : [ ]
}, {
  "name" : "Figueroa_Jose_Oscar",
  "imports" : [ ]
}, {
  "name" : "Menehem_Jorge",
  "imports" : [ ]
}, {
  "name" : "Baeza_Cristian",
  "imports" : [ ]
}, {
  "name" : "Pereira_Julio",
  "imports" : [ ]
}, {
  "name" : "Carli_Norberto",
  "imports" : [ ]
}, {
  "name" : "Porras_Alfredo",
  "imports" : [ "Diaz_Jose_M" ]
}, {
  "name" : "Diaz_Jose_M",
  "imports" : [ ]
}, {
  "name" : "Oliveri_Guillermo_Rodolfo",
  "imports" : [ "Romano_Carlos", "Schvindt_Juan_Abelardo" ]
}, {
  "name" : "Romano_Carlos",
  "imports" : [ ]
}, {
  "name" : "Schvindt_Juan_Abelardo",
  "imports" : [ ]
}, {
  "name" : "Kirchner_Nestor",
  "imports" : [ "Confederacion_General_del_Trabajo_CGT", "Pte_y_Dtor_Ejec_de_General_Electrice_D_Jeffrey_Immelt", "Delegacion_del_Senado_de_los_Estados_Unidos_de_Norteamerica", "Vazquez_Tabare", "Maza_Angel_Eduardo", "Duhalde_Eduardo", "Repsol-Ypf_Sr_Antonio_Brufau", "Presidente_del_Gobierno_de_Espana_Sr_Jose_Luis_Rodriguez_Zapatero", "Argibay_Molina_Carmen" ]
}, {
  "name" : "Confederacion_General_del_Trabajo_CGT",
  "imports" : [ ]
}, {
  "name" : "Pte_y_Dtor_Ejec_de_General_Electrice_D_Jeffrey_Immelt",
  "imports" : [ ]
}, {
  "name" : "Delegacion_del_Senado_de_los_Estados_Unidos_de_Norteamerica",
  "imports" : [ ]
}, {
  "name" : "Vazquez_Tabare",
  "imports" : [ ]
}, {
  "name" : "Maza_Angel_Eduardo",
  "imports" : [ ]
}, {
  "name" : "Duhalde_Eduardo",
  "imports" : [ ]
}, {
  "name" : "Repsol-Ypf_Sr_Antonio_Brufau",
  "imports" : [ ]
}, {
  "name" : "Presidente_del_Gobierno_de_Espana_Sr_Jose_Luis_Rodriguez_Zapatero",
  "imports" : [ ]
}, {
  "name" : "Argibay_Molina_Carmen",
  "imports" : [ ]
}, {
  "name" : "Siegenthaler_Juan",
  "imports" : [ "Ley_Victor" ]
}, {
  "name" : "Ley_Victor",
  "imports" : [ ]
}, {
  "name" : "Bechini_Leonardo",
  "imports" : [ "Lopez_Lecube_Gloria", "Echave_Rolando", "Giorgiuti_Franco", "Cohen_Ricardo", "Kremer_Luisa", "Palmisano_Roberto", "Ferragut_Nara", "Ciliberti_Luis", "Piccone_Nestor", "Korol_Adrian", "Falco_Maria" ]
}, {
  "name" : "Lopez_Lecube_Gloria",
  "imports" : [ ]
}, {
  "name" : "Echave_Rolando",
  "imports" : [ ]
}, {
  "name" : "Giorgiuti_Franco",
  "imports" : [ ]
}, {
  "name" : "Cohen_Ricardo",
  "imports" : [ ]
}, {
  "name" : "Kremer_Luisa",
  "imports" : [ ]
}, {
  "name" : "Palmisano_Roberto",
  "imports" : [ ]
}, {
  "name" : "Ferragut_Nara",
  "imports" : [ ]
}, {
  "name" : "Ciliberti_Luis",
  "imports" : [ ]
}, {
  "name" : "Piccone_Nestor",
  "imports" : [ ]
}, {
  "name" : "Korol_Adrian",
  "imports" : [ ]
}, {
  "name" : "Falco_Maria",
  "imports" : [ ]
}, {
  "name" : "Oyhanarte_Marta",
  "imports" : [ "Caligaris_Susana" ]
}, {
  "name" : "Caligaris_Susana",
  "imports" : [ ]
}, {
  "name" : "Orefice_Horacio_A",
  "imports" : [ "Llano_Edgardo", "Borgonovo_Esteban" ]
}, {
  "name" : "Llano_Edgardo",
  "imports" : [ ]
}, {
  "name" : "Borgonovo_Esteban",
  "imports" : [ ]
}, {
  "name" : "Fernandez_Horacio",
  "imports" : [ "Riso_Eduardo" ]
}, {
  "name" : "Riso_Eduardo",
  "imports" : [ ]
}, {
  "name" : "Hernandez_Daniel",
  "imports" : [ "Abad_Luis", "Bueno_Ana_Eugenia", "Cuello_Beatriz_Evelia", "Dartiguelongue_Carlos", "Laterza_Blas", "Svarzman_Gustavo", "Ezama_Juan_Jose", "Gandara_Gustavo", "Smith_Alfredo", "Lacaria_Jorge_Omar", "Almandoz_Maria_Rosa", "Ranu_Romildo_Francisco", "Levin_Luis", "Giacchino_de_Ribet_Maria_Isabel" ]
}, {
  "name" : "Abad_Luis",
  "imports" : [ ]
}, {
  "name" : "Bueno_Ana_Eugenia",
  "imports" : [ ]
}, {
  "name" : "Cuello_Beatriz_Evelia",
  "imports" : [ ]
}, {
  "name" : "Dartiguelongue_Carlos",
  "imports" : [ ]
}, {
  "name" : "Laterza_Blas",
  "imports" : [ ]
}, {
  "name" : "Svarzman_Gustavo",
  "imports" : [ ]
}, {
  "name" : "Ezama_Juan_Jose",
  "imports" : [ ]
}, {
  "name" : "Gandara_Gustavo",
  "imports" : [ ]
}, {
  "name" : "Smith_Alfredo",
  "imports" : [ ]
}, {
  "name" : "Lacaria_Jorge_Omar",
  "imports" : [ ]
}, {
  "name" : "Almandoz_Maria_Rosa",
  "imports" : [ ]
}, {
  "name" : "Ranu_Romildo_Francisco",
  "imports" : [ ]
}, {
  "name" : "Levin_Luis",
  "imports" : [ ]
}, {
  "name" : "Giacchino_de_Ribet_Maria_Isabel",
  "imports" : [ ]
}, {
  "name" : "Zanarini_Eugenio_Daniel",
  "imports" : [ "Barenboim_Leonardo", "Fucinato_Ruben", "Gomez_Rodolfo", "Bravo_Aldo", "Corciglia_Joaquin", "Cursio_-", "Escoda_Juan_Carlos", "Chianalino_Andres", "Simonotti_Fernando", "Nacano_Silvia" ]
}, {
  "name" : "Barenboim_Leonardo",
  "imports" : [ ]
}, {
  "name" : "Fucinato_Ruben",
  "imports" : [ ]
}, {
  "name" : "Gomez_Rodolfo",
  "imports" : [ ]
}, {
  "name" : "Bravo_Aldo",
  "imports" : [ ]
}, {
  "name" : "Corciglia_Joaquin",
  "imports" : [ ]
}, {
  "name" : "Cursio_-",
  "imports" : [ ]
}, {
  "name" : "Escoda_Juan_Carlos",
  "imports" : [ ]
}, {
  "name" : "Chianalino_Andres",
  "imports" : [ ]
}, {
  "name" : "Simonotti_Fernando",
  "imports" : [ ]
}, {
  "name" : "Nacano_Silvia",
  "imports" : [ ]
}, {
  "name" : "Madies_Claudia_Viviana",
  "imports" : [ "Spagnuolo_Rey_Ernesto", "Materi_Anibal" ]
}, {
  "name" : "Spagnuolo_Rey_Ernesto",
  "imports" : [ ]
}, {
  "name" : "Materi_Anibal",
  "imports" : [ ]
}, {
  "name" : "Couyoupetrou_Luis",
  "imports" : [ "Salerno_Gustavo", "Calegari_Jorge", "Di_Paolo_Mario", "Atsbury_Raul", "Lavigne_Enrique" ]
}, {
  "name" : "Salerno_Gustavo",
  "imports" : [ ]
}, {
  "name" : "Calegari_Jorge",
  "imports" : [ ]
}, {
  "name" : "Di_Paolo_Mario",
  "imports" : [ ]
}, {
  "name" : "Atsbury_Raul",
  "imports" : [ ]
}, {
  "name" : "Lavigne_Enrique",
  "imports" : [ ]
}, {
  "name" : "Ross_Juan_Jose",
  "imports" : [ "Brufman_Alberto", "Constanzo_Escobar_Pablo_Sebastian" ]
}, {
  "name" : "Brufman_Alberto",
  "imports" : [ ]
}, {
  "name" : "Constanzo_Escobar_Pablo_Sebastian",
  "imports" : [ ]
}, {
  "name" : "Granero_Jose_Ramon",
  "imports" : [ "Wainstein_Celia", "Di_Cola_Eduardo", "Elema_Reneko" ]
}, {
  "name" : "Wainstein_Celia",
  "imports" : [ ]
}, {
  "name" : "Di_Cola_Eduardo",
  "imports" : [ ]
}, {
  "name" : "Elema_Reneko",
  "imports" : [ ]
}, {
  "name" : "Bielsa_Rafael_Antonio",
  "imports" : [ "Amorin_Celso", "Forti_Alfredo_Waldo", "Alexandre_Boniface", "Sha_Hat_Nabil", "Fatuoh_Rawhi", "Katsav_Moshe", "Shalom_Silvan", "Rodriguez_Zapatero_Jose_Luis", "Muselier_Renaud" ]
}, {
  "name" : "Amorin_Celso",
  "imports" : [ ]
}, {
  "name" : "Forti_Alfredo_Waldo",
  "imports" : [ ]
}, {
  "name" : "Alexandre_Boniface",
  "imports" : [ ]
}, {
  "name" : "Sha_Hat_Nabil",
  "imports" : [ ]
}, {
  "name" : "Fatuoh_Rawhi",
  "imports" : [ ]
}, {
  "name" : "Katsav_Moshe",
  "imports" : [ ]
}, {
  "name" : "Shalom_Silvan",
  "imports" : [ ]
}, {
  "name" : "Rodriguez_Zapatero_Jose_Luis",
  "imports" : [ ]
}, {
  "name" : "Muselier_Renaud",
  "imports" : [ ]
}, {
  "name" : "Rosatti_Horacio_Daniel",
  "imports" : [ "Rodriguez_Robledo_Oscar", "Anderson_Douglas_W" ]
}, {
  "name" : "Rodriguez_Robledo_Oscar",
  "imports" : [ ]
}, {
  "name" : "Anderson_Douglas_W",
  "imports" : [ ]
}, {
  "name" : "Sileoni_Alberto",
  "imports" : [ "Muzio_Marta", "Osorio_Fernando", "Bibiloni_Homero_Maximo", "Rojas_Rivera_Edwin" ]
}, {
  "name" : "Muzio_Marta",
  "imports" : [ ]
}, {
  "name" : "Osorio_Fernando",
  "imports" : [ ]
}, {
  "name" : "Bibiloni_Homero_Maximo",
  "imports" : [ ]
}, {
  "name" : "Rojas_Rivera_Edwin",
  "imports" : [ ]
}, {
  "name" : "Ochoa_Romero_Pedro",
  "imports" : [ "Papicio_Jorge" ]
}, {
  "name" : "Papicio_Jorge",
  "imports" : [ ]
}, {
  "name" : "Torres_Ruben_Humberto",
  "imports" : [ "Peretta_Marcelo_Daniel", "Chames_Marcelo", "Amarilla_Patricia", "Pandolfi_Luis_Juan", "Camera_Mario_Ignacio", "Delbene_Roberto", "Pinco_Maria", "Cisneros_Alicia_Soraya", "Molina_Rafael" ]
}, {
  "name" : "Peretta_Marcelo_Daniel",
  "imports" : [ ]
}, {
  "name" : "Chames_Marcelo",
  "imports" : [ ]
}, {
  "name" : "Amarilla_Patricia",
  "imports" : [ ]
}, {
  "name" : "Pandolfi_Luis_Juan",
  "imports" : [ ]
}, {
  "name" : "Camera_Mario_Ignacio",
  "imports" : [ ]
}, {
  "name" : "Delbene_Roberto",
  "imports" : [ ]
}, {
  "name" : "Pinco_Maria",
  "imports" : [ ]
}, {
  "name" : "Cisneros_Alicia_Soraya",
  "imports" : [ ]
}, {
  "name" : "Molina_Rafael",
  "imports" : [ ]
}, {
  "name" : "Lucero_Marcos",
  "imports" : [ "Lucero_Marcos_Obdulio" ]
}, {
  "name" : "Lucero_Marcos_Obdulio",
  "imports" : [ ]
}, {
  "name" : "Sardella_Rafael",
  "imports" : [ "Halm_Juan_Jose", "Morandini_Emmanuel" ]
}, {
  "name" : "Halm_Juan_Jose",
  "imports" : [ ]
}, {
  "name" : "Morandini_Emmanuel",
  "imports" : [ ]
}, {
  "name" : "Baum_Susana",
  "imports" : [ "Rioseco_Ramon", "Reigosa_Liliana_Monica" ]
}, {
  "name" : "Rioseco_Ramon",
  "imports" : [ ]
}, {
  "name" : "Reigosa_Liliana_Monica",
  "imports" : [ ]
}, {
  "name" : "Fuks_Gabriel_Marcelo",
  "imports" : [ "Nieto_Enrique_Gerardo" ]
}, {
  "name" : "Nieto_Enrique_Gerardo",
  "imports" : [ ]
}, {
  "name" : "Rial_Noemi",
  "imports" : [ "Cejas_Luis_Carlos", "Soria_Jorge_Dioniisio", "Pedraza_Jose", "Plaini_Omar", "Ruiz_Juan_Carlos", "Gimenez_Luis", "Rubio_Jorge", "Soliz_Osvaldo", "Diaz_Nielsen_Ernesto", "Gallo_Marcelo", "Pereira_Enrique", "Salinas_German", "Bianchi_Horacio_Mario", "Cholvis_Jorge", "Souto_Graciela" ]
}, {
  "name" : "Cejas_Luis_Carlos",
  "imports" : [ ]
}, {
  "name" : "Soria_Jorge_Dioniisio",
  "imports" : [ ]
}, {
  "name" : "Pedraza_Jose",
  "imports" : [ ]
}, {
  "name" : "Plaini_Omar",
  "imports" : [ ]
}, {
  "name" : "Ruiz_Juan_Carlos",
  "imports" : [ ]
}, {
  "name" : "Gimenez_Luis",
  "imports" : [ ]
}, {
  "name" : "Rubio_Jorge",
  "imports" : [ ]
}, {
  "name" : "Soliz_Osvaldo",
  "imports" : [ ]
}, {
  "name" : "Diaz_Nielsen_Ernesto",
  "imports" : [ ]
}, {
  "name" : "Gallo_Marcelo",
  "imports" : [ ]
}, {
  "name" : "Pereira_Enrique",
  "imports" : [ ]
}, {
  "name" : "Salinas_German",
  "imports" : [ ]
}, {
  "name" : "Bianchi_Horacio_Mario",
  "imports" : [ ]
}, {
  "name" : "Cholvis_Jorge",
  "imports" : [ ]
}, {
  "name" : "Souto_Graciela",
  "imports" : [ ]
}, {
  "name" : "Namuncura_Ceferino",
  "imports" : [ "Boccoli_Felipe", "Bilski_Jorge_Alberto" ]
}, {
  "name" : "Boccoli_Felipe",
  "imports" : [ ]
}, {
  "name" : "Bilski_Jorge_Alberto",
  "imports" : [ ]
}, {
  "name" : "Filmus_Daniel_Fernando",
  "imports" : [ "Levin_Hugo", "Suar_Adrian", "Baranao_Lino", "Graham_Marisa", "Rivera_Pizarro_Jorge", "Van_Gelderen_Alfredo", "Oporto_Mario", "Bettini_Carlos" ]
}, {
  "name" : "Levin_Hugo",
  "imports" : [ ]
}, {
  "name" : "Suar_Adrian",
  "imports" : [ ]
}, {
  "name" : "Baranao_Lino",
  "imports" : [ ]
}, {
  "name" : "Graham_Marisa",
  "imports" : [ ]
}, {
  "name" : "Rivera_Pizarro_Jorge",
  "imports" : [ ]
}, {
  "name" : "Van_Gelderen_Alfredo",
  "imports" : [ ]
}, {
  "name" : "Oporto_Mario",
  "imports" : [ ]
}, {
  "name" : "Bettini_Carlos",
  "imports" : [ ]
}, {
  "name" : "Lico_Oscar",
  "imports" : [ "Serman_Demetrio", "Tomasini_Daniel" ]
}, {
  "name" : "Serman_Demetrio",
  "imports" : [ ]
}, {
  "name" : "Tomasini_Daniel",
  "imports" : [ ]
}, {
  "name" : "Nun_Jose",
  "imports" : [ "Smoljan_Oscar", "Lattuada_Mario", "Fleming_Juan_E", "Levin_Hugo" ]
}, {
  "name" : "Smoljan_Oscar",
  "imports" : [ ]
}, {
  "name" : "Lattuada_Mario",
  "imports" : [ ]
}, {
  "name" : "Fleming_Juan_E",
  "imports" : [ ]
}, {
  "name" : "Prina_Eduardo_Daniel",
  "imports" : [ "Iraizoz_Juan_F", "Tiberio_Julio_Cesar" ]
}, {
  "name" : "Iraizoz_Juan_F",
  "imports" : [ ]
}, {
  "name" : "Tiberio_Julio_Cesar",
  "imports" : [ ]
}, {
  "name" : "Vessvessian_Marcela_Paola",
  "imports" : [ "Fernandez_Maria_Isabel" ]
}, {
  "name" : "Fernandez_Maria_Isabel",
  "imports" : [ ]
}, {
  "name" : "Lic_Di_Tella_Torcuato_Salvador",
  "imports" : [ "Conde_Rosa" ]
}, {
  "name" : "Conde_Rosa",
  "imports" : [ ]
}, {
  "name" : "Donikian_Oscsar",
  "imports" : [ "Seidel_Patricio" ]
}, {
  "name" : "Seidel_Patricio",
  "imports" : [ ]
}, {
  "name" : "Vizzotti_Carlos_Alberto",
  "imports" : [ "Vizzotti_Carlos" ]
}, {
  "name" : "Vizzotti_Carlos",
  "imports" : [ ]
}, {
  "name" : "Roncero_Jessica",
  "imports" : [ "Ordonez_Diego", "Trotta_Raul_Antonio", "Lopez_Lecube_Gloria", "Diaz_Agustina_Barbara", "Pelaez_Carlos_Daniel" ]
}, {
  "name" : "Ordonez_Diego",
  "imports" : [ ]
}, {
  "name" : "Trotta_Raul_Antonio",
  "imports" : [ ]
}, {
  "name" : "Diaz_Agustina_Barbara",
  "imports" : [ ]
}, {
  "name" : "Pelaez_Carlos_Daniel",
  "imports" : [ ]
}, {
  "name" : "Albistur_Alberto_Alejandro",
  "imports" : [ "Diaz_Guerrero_Edgardo" ]
}, {
  "name" : "Diaz_Guerrero_Edgardo",
  "imports" : [ ]
}, {
  "name" : "Pizarro_Roberto",
  "imports" : [ "Lego_Eduardo_Diego" ]
}, {
  "name" : "Lego_Eduardo_Diego",
  "imports" : [ ]
}, {
  "name" : "Moreno_Mario_Guillermo",
  "imports" : [ "Soldati_Santiago", "Lorenzatti_Eduardo", "Krimer_Marcelo", "Rodriguez_German", "Kazunori_Kosaka", "Cortes_Gabriel", "Lapena_Juan_Carlos", "Wilson_Carlos", "Novoa_Miguel_Angel", "Abarca_Omar_Angel" ]
}, {
  "name" : "Soldati_Santiago",
  "imports" : [ ]
}, {
  "name" : "Lorenzatti_Eduardo",
  "imports" : [ ]
}, {
  "name" : "Krimer_Marcelo",
  "imports" : [ ]
}, {
  "name" : "Rodriguez_German",
  "imports" : [ ]
}, {
  "name" : "Kazunori_Kosaka",
  "imports" : [ ]
}, {
  "name" : "Cortes_Gabriel",
  "imports" : [ ]
}, {
  "name" : "Lapena_Juan_Carlos",
  "imports" : [ ]
}, {
  "name" : "Wilson_Carlos",
  "imports" : [ ]
}, {
  "name" : "Novoa_Miguel_Angel",
  "imports" : [ ]
}, {
  "name" : "Abarca_Omar_Angel",
  "imports" : [ ]
}, {
  "name" : "Villella_Marcos_Leonel",
  "imports" : [ "Busquets_Jorge", "Travascio_Adrian", "Nazar_Gabriel", "Piacentino_Ana", "De_Pedro_Eduardo", "Brouwer_de_Koning_Christian", "Pazos_Jorge", "Belio_Gerardo", "Colombo_Leopoldo", "Boto_Alvarez_Leonardo", "Lobos_Guillermo" ]
}, {
  "name" : "Busquets_Jorge",
  "imports" : [ ]
}, {
  "name" : "Travascio_Adrian",
  "imports" : [ ]
}, {
  "name" : "Nazar_Gabriel",
  "imports" : [ ]
}, {
  "name" : "Piacentino_Ana",
  "imports" : [ ]
}, {
  "name" : "De_Pedro_Eduardo",
  "imports" : [ ]
}, {
  "name" : "Brouwer_de_Koning_Christian",
  "imports" : [ ]
}, {
  "name" : "Pazos_Jorge",
  "imports" : [ ]
}, {
  "name" : "Belio_Gerardo",
  "imports" : [ ]
}, {
  "name" : "Colombo_Leopoldo",
  "imports" : [ ]
}, {
  "name" : "Boto_Alvarez_Leonardo",
  "imports" : [ ]
}, {
  "name" : "Lobos_Guillermo",
  "imports" : [ ]
}, {
  "name" : "De_Vido_Julio_M",
  "imports" : [ "Alperovich_Jose", "Picheto_Miguel_Angel", "Alderete_Jose", "Madaro_Fulvio", "Cameron_Daniel", "Gutierrez_Ernesto", "Roggio_Aldo", "Vazquez_Amadeo", "Lopez_Jose", "Puerta_Ramon", "Uberti_Claudio", "Presidencia_De_la_Nacion", "Lingeri_Jose_Luis", "Espinosa_Exequiel", "Obeid_Jorge_Alberto", "Namuncura_Ceferino", "Celaya_Ruben" ]
}, {
  "name" : "Alperovich_Jose",
  "imports" : [ ]
}, {
  "name" : "Picheto_Miguel_Angel",
  "imports" : [ ]
}, {
  "name" : "Alderete_Jose",
  "imports" : [ ]
}, {
  "name" : "Madaro_Fulvio",
  "imports" : [ ]
}, {
  "name" : "Cameron_Daniel",
  "imports" : [ ]
}, {
  "name" : "Gutierrez_Ernesto",
  "imports" : [ ]
}, {
  "name" : "Roggio_Aldo",
  "imports" : [ ]
}, {
  "name" : "Vazquez_Amadeo",
  "imports" : [ ]
}, {
  "name" : "Lopez_Jose",
  "imports" : [ ]
}, {
  "name" : "Puerta_Ramon",
  "imports" : [ ]
}, {
  "name" : "Uberti_Claudio",
  "imports" : [ ]
}, {
  "name" : "Presidencia_De_la_Nacion",
  "imports" : [ ]
}, {
  "name" : "Lingeri_Jose_Luis",
  "imports" : [ ]
}, {
  "name" : "Espinosa_Exequiel",
  "imports" : [ ]
}, {
  "name" : "Obeid_Jorge_Alberto",
  "imports" : [ ]
}, {
  "name" : "Celaya_Ruben",
  "imports" : [ ]
}, {
  "name" : "Fleitas_Ortiz_de_Rozas_Abel",
  "imports" : [ "Garcia-Gonzalez_Jorge" ]
}, {
  "name" : "Garcia-Gonzalez_Jorge",
  "imports" : [ ]
}, {
  "name" : "Sartor_Hugo",
  "imports" : [ "Caniza_Alicia" ]
}, {
  "name" : "Caniza_Alicia",
  "imports" : [ ]
}, {
  "name" : "Donato_Sergio_Mauricio",
  "imports" : [ "Perez_Ricardo_L" ]
}, {
  "name" : "Perez_Ricardo_L",
  "imports" : [ ]
}, {
  "name" : "Granada_Rolando",
  "imports" : [ "Brunetti_Patricia_R" ]
}, {
  "name" : "Brunetti_Patricia_R",
  "imports" : [ ]
}, {
  "name" : "Deibe_Adolfo_Enrique",
  "imports" : [ "Engel_Carlos", "Perez_Sandra", "Florin_Christensen_Sergio", "Funes_de_Rioja_Daniel" ]
}, {
  "name" : "Engel_Carlos",
  "imports" : [ ]
}, {
  "name" : "Perez_Sandra",
  "imports" : [ ]
}, {
  "name" : "Florin_Christensen_Sergio",
  "imports" : [ ]
}, {
  "name" : "Funes_de_Rioja_Daniel",
  "imports" : [ ]
}, {
  "name" : "Elordi_Susana",
  "imports" : [ "Allievi_Gustavo" ]
}, {
  "name" : "Allievi_Gustavo",
  "imports" : [ ]
}, {
  "name" : "Bender_Gloria_Raquel",
  "imports" : [ "Waisbord_Leandro", "Frias_Miguel", "Arrieta_de_Blaquier_Nelly", "Chomski_Alejandro", "Silverfaden_Daniel" ]
}, {
  "name" : "Waisbord_Leandro",
  "imports" : [ ]
}, {
  "name" : "Frias_Miguel",
  "imports" : [ ]
}, {
  "name" : "Arrieta_de_Blaquier_Nelly",
  "imports" : [ ]
}, {
  "name" : "Chomski_Alejandro",
  "imports" : [ ]
}, {
  "name" : "Silverfaden_Daniel",
  "imports" : [ ]
}, {
  "name" : "Conte_Grand_Alfredo_Horacio",
  "imports" : [ "Giobergia_Humberto" ]
}, {
  "name" : "Giobergia_Humberto",
  "imports" : [ ]
}, {
  "name" : "Diez_Luis_Angel",
  "imports" : [ "Braun_Estrgamou_Guillermo", "Cingolani_Enrique_Julio", "Benitez_Pablo", "Martire_Horacio", "Echegaray_Ricardo", "Bustos_Villar_Eduardo", "Abad_Alberto", "Ameneiros_Juan_Carlos" ]
}, {
  "name" : "Braun_Estrgamou_Guillermo",
  "imports" : [ ]
}, {
  "name" : "Cingolani_Enrique_Julio",
  "imports" : [ ]
}, {
  "name" : "Benitez_Pablo",
  "imports" : [ ]
}, {
  "name" : "Martire_Horacio",
  "imports" : [ ]
}, {
  "name" : "Echegaray_Ricardo",
  "imports" : [ ]
}, {
  "name" : "Bustos_Villar_Eduardo",
  "imports" : [ ]
}, {
  "name" : "Abad_Alberto",
  "imports" : [ ]
}, {
  "name" : "Ameneiros_Juan_Carlos",
  "imports" : [ ]
}, {
  "name" : "Dorrego_Sergio",
  "imports" : [ "Ugalde_Carlos" ]
}, {
  "name" : "Ugalde_Carlos",
  "imports" : [ ]
}, {
  "name" : "Garcia_Moritan_Roberto",
  "imports" : [ "Viaje_en_Mision_Oficial_-" ]
}, {
  "name" : "Viaje_en_Mision_Oficial_-",
  "imports" : [ ]
}, {
  "name" : "Bocchio_de_Santos_Mirta",
  "imports" : [ "Steele_Mark" ]
}, {
  "name" : "Steele_Mark",
  "imports" : [ ]
}, {
  "name" : "Sereno_Juan_Carlos",
  "imports" : [ "Ordonez_Lopez_Emilio", "Sisa_Maria_Sara", "Pastoriza_Carlos", "Delicia_Carlos", "Carnevale_Piedrabuena_Gustavo_Mario", "Gomez_Luis", "Zenklusen_Nestor" ]
}, {
  "name" : "Ordonez_Lopez_Emilio",
  "imports" : [ ]
}, {
  "name" : "Sisa_Maria_Sara",
  "imports" : [ ]
}, {
  "name" : "Pastoriza_Carlos",
  "imports" : [ ]
}, {
  "name" : "Delicia_Carlos",
  "imports" : [ ]
}, {
  "name" : "Carnevale_Piedrabuena_Gustavo_Mario",
  "imports" : [ ]
}, {
  "name" : "Gomez_Luis",
  "imports" : [ ]
}, {
  "name" : "Zenklusen_Nestor",
  "imports" : [ ]
}, {
  "name" : "Ciaravino_Norberto_Jose",
  "imports" : [ "Tomada_Carlos" ]
}, {
  "name" : "Tomada_Carlos",
  "imports" : [ ]
}, {
  "name" : "Herrero_Anzorena_Julio",
  "imports" : [ "Bacigalupo_Martin" ]
}, {
  "name" : "Bacigalupo_Martin",
  "imports" : [ ]
}, {
  "name" : "Baratta_Roberto",
  "imports" : [ "Peralta_Daniel_Roman", "Lievers_Baldivieso_Arturo", "Castro_Gonzalo", "Siampini_Alberto", "Baratta_Roberto", "Cdor_Franco_Ernesto_Osvaldo" ]
}, {
  "name" : "Peralta_Daniel_Roman",
  "imports" : [ ]
}, {
  "name" : "Lievers_Baldivieso_Arturo",
  "imports" : [ ]
}, {
  "name" : "Castro_Gonzalo",
  "imports" : [ ]
}, {
  "name" : "Siampini_Alberto",
  "imports" : [ ]
}, {
  "name" : "Cdor_Franco_Ernesto_Osvaldo",
  "imports" : [ ]
}, {
  "name" : "Martin_Daniel_Eduardo",
  "imports" : [ "Semmolini_Omar", "Martin_Ricardo_Antonio" ]
}, {
  "name" : "Semmolini_Omar",
  "imports" : [ ]
}, {
  "name" : "Martin_Ricardo_Antonio",
  "imports" : [ ]
}, {
  "name" : "Cedola_Ofelia_Mabel",
  "imports" : [ "Quintar_Ernesto" ]
}, {
  "name" : "Quintar_Ernesto",
  "imports" : [ ]
}, {
  "name" : "Gadano_Julian",
  "imports" : [ "Cardozo_Fernando", "Gomez_Carlos", "Naciovich_Cecilia", "Pazos_Cecilia", "Lezcano_Lucas", "Esposito_Ruben", "Verdugo_Laura_Adriana", "Urcullo_Gaston", "Ginsburg_Cecilia", "Roitman_Oscar", "Da_Luz_Carmen", "Toledo_Sergio", "Miceli_Pablo" ]
}, {
  "name" : "Cardozo_Fernando",
  "imports" : [ ]
}, {
  "name" : "Gomez_Carlos",
  "imports" : [ ]
}, {
  "name" : "Naciovich_Cecilia",
  "imports" : [ ]
}, {
  "name" : "Pazos_Cecilia",
  "imports" : [ ]
}, {
  "name" : "Lezcano_Lucas",
  "imports" : [ ]
}, {
  "name" : "Esposito_Ruben",
  "imports" : [ ]
}, {
  "name" : "Verdugo_Laura_Adriana",
  "imports" : [ ]
}, {
  "name" : "Urcullo_Gaston",
  "imports" : [ ]
}, {
  "name" : "Ginsburg_Cecilia",
  "imports" : [ ]
}, {
  "name" : "Roitman_Oscar",
  "imports" : [ ]
}, {
  "name" : "Da_Luz_Carmen",
  "imports" : [ ]
}, {
  "name" : "Toledo_Sergio",
  "imports" : [ ]
}, {
  "name" : "Miceli_Pablo",
  "imports" : [ ]
}, {
  "name" : "Aguilera_Daniel_Pablo",
  "imports" : [ "Castracane_Domingo", "Arrachea_Santiago", "Formica_Eriberto", "Gandini_Patricia" ]
}, {
  "name" : "Castracane_Domingo",
  "imports" : [ ]
}, {
  "name" : "Arrachea_Santiago",
  "imports" : [ ]
}, {
  "name" : "Formica_Eriberto",
  "imports" : [ ]
}, {
  "name" : "Gandini_Patricia",
  "imports" : [ ]
}, {
  "name" : "Folgar_Cristian",
  "imports" : [ "Felici_Jorge_O" ]
}, {
  "name" : "Felici_Jorge_O",
  "imports" : [ ]
}, {
  "name" : "Periotti_Nelson",
  "imports" : [ "Metazza_Mario", "Ordonez_Jorge", "Rosales_Nestor", "Uribarren_Edgardo", "Grbavac_Anmtonio", "Katz_Pedro", "Jofre_Jorge_Alberto" ]
}, {
  "name" : "Metazza_Mario",
  "imports" : [ ]
}, {
  "name" : "Ordonez_Jorge",
  "imports" : [ ]
}, {
  "name" : "Rosales_Nestor",
  "imports" : [ ]
}, {
  "name" : "Uribarren_Edgardo",
  "imports" : [ ]
}, {
  "name" : "Grbavac_Anmtonio",
  "imports" : [ ]
}, {
  "name" : "Katz_Pedro",
  "imports" : [ ]
}, {
  "name" : "Jofre_Jorge_Alberto",
  "imports" : [ ]
}, {
  "name" : "Savino_Atilio",
  "imports" : [ "Pages_Jose_Antonio", "Salas_Xxxxx", "O_Neil_Maureen", "Krombach_Xxxx", "Smith_Sandra", "Peralta_Luis_Orlando", "Mussin_Marta", "Guerina_Maria", "Caballero_Pablo_Luis" ]
}, {
  "name" : "Pages_Jose_Antonio",
  "imports" : [ ]
}, {
  "name" : "Salas_Xxxxx",
  "imports" : [ ]
}, {
  "name" : "O_Neil_Maureen",
  "imports" : [ ]
}, {
  "name" : "Krombach_Xxxx",
  "imports" : [ ]
}, {
  "name" : "Smith_Sandra",
  "imports" : [ ]
}, {
  "name" : "Peralta_Luis_Orlando",
  "imports" : [ ]
}, {
  "name" : "Caballero_Pablo_Luis",
  "imports" : [ ]
}, {
  "name" : "Cantarelli_Luis_Maria",
  "imports" : [ "Barturen_Carmelo_Angulo" ]
}, {
  "name" : "Barturen_Carmelo_Angulo",
  "imports" : [ ]
}, {
  "name" : "Rodriguez_Maria_Jose",
  "imports" : [ "Goerner_Rodolfo_Gustavo", "Rodriguez_Agustine", "Bibiloni_Homero_Maximo", "Altmark_Daniel", "Clavijo_Guillermo", "Dr_Goerner_Rodolfo_Gustavo" ]
}, {
  "name" : "Goerner_Rodolfo_Gustavo",
  "imports" : [ ]
}, {
  "name" : "Rodriguez_Agustine",
  "imports" : [ ]
}, {
  "name" : "Altmark_Daniel",
  "imports" : [ ]
}, {
  "name" : "Clavijo_Guillermo",
  "imports" : [ ]
}, {
  "name" : "Dr_Goerner_Rodolfo_Gustavo",
  "imports" : [ ]
}, {
  "name" : "Morduchowicz_Alejandro_Javier",
  "imports" : [ "Blanco_Norberto" ]
}, {
  "name" : "Blanco_Norberto",
  "imports" : [ ]
}, {
  "name" : "Soratti_Carlos_Alberto",
  "imports" : [ "Rivera_Juan_Carlos" ]
}, {
  "name" : "Rivera_Juan_Carlos",
  "imports" : [ ]
}, {
  "name" : "Oporto_Graciela_Elena",
  "imports" : [ "Rulli_Jorge_Eduardo" ]
}, {
  "name" : "Rulli_Jorge_Eduardo",
  "imports" : [ ]
}, {
  "name" : "Pellizza_Valeria",
  "imports" : [ "Pesci_Ruben", "Fernandez_Bussi_Jorge" ]
}, {
  "name" : "Pesci_Ruben",
  "imports" : [ ]
}, {
  "name" : "Fernandez_Bussi_Jorge",
  "imports" : [ ]
}, {
  "name" : "Navarro_Mariana",
  "imports" : [ "Santa_Marcelo" ]
}, {
  "name" : "Santa_Marcelo",
  "imports" : [ ]
}, {
  "name" : "Meyer_Carlos_Enrique",
  "imports" : [ "Palacios_Marco", "Marangoni_Alejandro", "Busquets_Jorge", "Estevez_Eduardo", "Tortonese_Diego", "Ferrucci_Jose_Maria", "Schmidt_Claudia", "Arteta_Arregui_Amaia", "Panadero_Manuel", "Villasante_Gonzalez_Angel", "Robak_Marcelo_Daniel", "Llorens_Isabel", "Sevilla_Rodriguez_Antonio", "Martinez_Fraile_Raimon", "Hillock_John" ]
}, {
  "name" : "Palacios_Marco",
  "imports" : [ ]
}, {
  "name" : "Marangoni_Alejandro",
  "imports" : [ ]
}, {
  "name" : "Estevez_Eduardo",
  "imports" : [ ]
}, {
  "name" : "Tortonese_Diego",
  "imports" : [ ]
}, {
  "name" : "Ferrucci_Jose_Maria",
  "imports" : [ ]
}, {
  "name" : "Schmidt_Claudia",
  "imports" : [ ]
}, {
  "name" : "Arteta_Arregui_Amaia",
  "imports" : [ ]
}, {
  "name" : "Panadero_Manuel",
  "imports" : [ ]
}, {
  "name" : "Villasante_Gonzalez_Angel",
  "imports" : [ ]
}, {
  "name" : "Robak_Marcelo_Daniel",
  "imports" : [ ]
}, {
  "name" : "Llorens_Isabel",
  "imports" : [ ]
}, {
  "name" : "Sevilla_Rodriguez_Antonio",
  "imports" : [ ]
}, {
  "name" : "Martinez_Fraile_Raimon",
  "imports" : [ ]
}, {
  "name" : "Hillock_John",
  "imports" : [ ]
}, {
  "name" : "Jaime_Raul_Ricardo",
  "imports" : [ "Sicaro_Eduardo", "Pino_Carlos", "Verra_Alberto", "Diez_Luis_Angel", "Cirigliano_Claudio", "Romero_Benjamin_Gabriel", "Cimo_Hector", "Vazquez_Juan_Carlos", "Crespo_Alberto", "Verdeguer_Mario", "Vazquez_Manuel", "Schmidt_Juan_Carlos", "Otero_Nestor", "Ochoa_Romero_Pedro", "Acuna_Joaquin" ]
}, {
  "name" : "Sicaro_Eduardo",
  "imports" : [ ]
}, {
  "name" : "Pino_Carlos",
  "imports" : [ ]
}, {
  "name" : "Verra_Alberto",
  "imports" : [ ]
}, {
  "name" : "Cirigliano_Claudio",
  "imports" : [ ]
}, {
  "name" : "Romero_Benjamin_Gabriel",
  "imports" : [ ]
}, {
  "name" : "Cimo_Hector",
  "imports" : [ ]
}, {
  "name" : "Vazquez_Juan_Carlos",
  "imports" : [ ]
}, {
  "name" : "Crespo_Alberto",
  "imports" : [ ]
}, {
  "name" : "Verdeguer_Mario",
  "imports" : [ ]
}, {
  "name" : "Vazquez_Manuel",
  "imports" : [ ]
}, {
  "name" : "Schmidt_Juan_Carlos",
  "imports" : [ ]
}, {
  "name" : "Otero_Nestor",
  "imports" : [ ]
}, {
  "name" : "Acuna_Joaquin",
  "imports" : [ ]
}, {
  "name" : "Del_Bono_Tulio_Abel",
  "imports" : [ "Bauer_Conrado", "Buzzi_Martin", "Puig_de_Stubrin_Lilia", "Levato_Orlando_Hugo" ]
}, {
  "name" : "Bauer_Conrado",
  "imports" : [ ]
}, {
  "name" : "Buzzi_Martin",
  "imports" : [ ]
}, {
  "name" : "Puig_de_Stubrin_Lilia",
  "imports" : [ ]
}, {
  "name" : "Levato_Orlando_Hugo",
  "imports" : [ ]
}, {
  "name" : "Pampuro_Jose_Juan_Bautista",
  "imports" : [ "Rohde_Carlos_Alberto", "Ramos_Juan_Carlos", "Bendini_Roberto_Fernando", "Veira_Nora", "Barturen_Carmelo_Angulo" ]
}, {
  "name" : "Rohde_Carlos_Alberto",
  "imports" : [ ]
}, {
  "name" : "Ramos_Juan_Carlos",
  "imports" : [ ]
}, {
  "name" : "Bendini_Roberto_Fernando",
  "imports" : [ ]
}, {
  "name" : "Veira_Nora",
  "imports" : [ ]
}, {
  "name" : "Bortolozzi_Edgardo_Atilio",
  "imports" : [ "Savini_Miguel", "Porcaro_Roberto", "Kirschenbaun_Juan", "Rodriguez_Velo_Jorge_Nicolas", "San_Miguel_Damian", "Balatti_Marcelo", "Guarch_Jose_Luis", "Joaquin_Alberto", "Morzan_Hugo" ]
}, {
  "name" : "Savini_Miguel",
  "imports" : [ ]
}, {
  "name" : "Porcaro_Roberto",
  "imports" : [ ]
}, {
  "name" : "Kirschenbaun_Juan",
  "imports" : [ ]
}, {
  "name" : "San_Miguel_Damian",
  "imports" : [ ]
}, {
  "name" : "Balatti_Marcelo",
  "imports" : [ ]
}, {
  "name" : "Guarch_Jose_Luis",
  "imports" : [ ]
}, {
  "name" : "Morzan_Hugo",
  "imports" : [ ]
}, {
  "name" : "Lenzberg_Alejandro_Cesar",
  "imports" : [ "Anguita_Eduardo", "Ezcurra_Federico", "Bueno_Valentin" ]
}, {
  "name" : "Anguita_Eduardo",
  "imports" : [ ]
}, {
  "name" : "Ezcurra_Federico",
  "imports" : [ ]
}, {
  "name" : "Bueno_Valentin",
  "imports" : [ ]
}, {
  "name" : "Ivancich_Norberto",
  "imports" : [ "Gonzalez_Leopoldo", "Mosquera_Ruben" ]
}, {
  "name" : "Gonzalez_Leopoldo",
  "imports" : [ ]
}, {
  "name" : "Mosquera_Ruben",
  "imports" : [ ]
}, {
  "name" : "Albistur_Enrique_Raul",
  "imports" : [ "Moldovan_Mario", "Madariaga_Abel", "Piccone_Nestor" ]
}, {
  "name" : "Moldovan_Mario",
  "imports" : [ ]
}, {
  "name" : "Madariaga_Abel",
  "imports" : [ ]
}, {
  "name" : "Garreta_Jaime",
  "imports" : [ "Baizan_Mario", "Montenegro_Ruben", "Azaretto_Roberto_Angel", "Rossi_Mario" ]
}, {
  "name" : "Baizan_Mario",
  "imports" : [ ]
}, {
  "name" : "Montenegro_Ruben",
  "imports" : [ ]
}, {
  "name" : "Azaretto_Roberto_Angel",
  "imports" : [ ]
}, {
  "name" : "Rossi_Mario",
  "imports" : [ ]
}, {
  "name" : "Kunkel_Carlos_Miguel",
  "imports" : [ "Callegaro_Martin", "Hergott_Oscar_Alberto", "Acevedo_Marcelo", "Moreda_Hernan_Rosendo", "Montaiuti_Martin", "Mendoza_Oscar" ]
}, {
  "name" : "Callegaro_Martin",
  "imports" : [ ]
}, {
  "name" : "Hergott_Oscar_Alberto",
  "imports" : [ ]
}, {
  "name" : "Acevedo_Marcelo",
  "imports" : [ ]
}, {
  "name" : "Moreda_Hernan_Rosendo",
  "imports" : [ ]
}, {
  "name" : "Montaiuti_Martin",
  "imports" : [ ]
}, {
  "name" : "Mendoza_Oscar",
  "imports" : [ ]
}, {
  "name" : "Arq_Salas_Lisandro",
  "imports" : [ "Ugalde_Carlos" ]
}, {
  "name" : "Novick_Marta_Susana",
  "imports" : [ "Senen_Gonzalez_Cecilia", "Ciaravino_Norberto", "Rojo_Sofia", "Cimoli_Mario", "Heras_Ana_Ines", "Rodriguez_Carlos_Alberto" ]
}, {
  "name" : "Senen_Gonzalez_Cecilia",
  "imports" : [ ]
}, {
  "name" : "Ciaravino_Norberto",
  "imports" : [ ]
}, {
  "name" : "Rojo_Sofia",
  "imports" : [ ]
}, {
  "name" : "Cimoli_Mario",
  "imports" : [ ]
}, {
  "name" : "Heras_Ana_Ines",
  "imports" : [ ]
}, {
  "name" : "Rodriguez_Carlos_Alberto",
  "imports" : [ ]
}, {
  "name" : "Raigorodsky_Nicolas",
  "imports" : [ "Nino_Ezequiel", "Garcia-Gonzalez_Jorge", "Di_Cola_Eduardo" ]
}, {
  "name" : "Nino_Ezequiel",
  "imports" : [ ]
}, {
  "name" : "Fernandez_Novoa_Sergio",
  "imports" : [ "Lopez_Jacinto" ]
}, {
  "name" : "Lopez_Jacinto",
  "imports" : [ ]
}, {
  "name" : "Segui_Luz",
  "imports" : [ "Marcos_Puscovich", "Pineda_Daniel" ]
}, {
  "name" : "Marcos_Puscovich",
  "imports" : [ ]
}, {
  "name" : "Pineda_Daniel",
  "imports" : [ ]
}, {
  "name" : "Tomada_Carlos_Alfonso",
  "imports" : [ "Gallo_Marcelo", "Savini_Miguel", "Achingo_Beatriz", "Palladino_Gabriela", "Urig_Claudia_Andrea", "Quiroz_Damian", "Reguera_Pablo", "Silva_Claudio_Cesar", "Jorullenca_Susana", "Miguel_Armando", "Tarrisse_Omar_Alfredo", "D_<U+00B4>Elia_Maria", "Manuel_Norma_Noemi", "Dorta_Alejandro", "Benz_Inceborg_Tannhauser", "Narvaja_Pablo", "Yanez_Rodolfo_Martin", "D<U+00B4>Angelo_Luis", "Chiesa_Miriam_Daniela", "Sindicato_de_Vendedores_de_Diarios__Revistas_y_Afi_Del_Interior", "Izetta_Elina" ]
}, {
  "name" : "Achingo_Beatriz",
  "imports" : [ ]
}, {
  "name" : "Palladino_Gabriela",
  "imports" : [ ]
}, {
  "name" : "Urig_Claudia_Andrea",
  "imports" : [ ]
}, {
  "name" : "Quiroz_Damian",
  "imports" : [ ]
}, {
  "name" : "Reguera_Pablo",
  "imports" : [ ]
}, {
  "name" : "Silva_Claudio_Cesar",
  "imports" : [ ]
}, {
  "name" : "Jorullenca_Susana",
  "imports" : [ ]
}, {
  "name" : "Miguel_Armando",
  "imports" : [ ]
}, {
  "name" : "Tarrisse_Omar_Alfredo",
  "imports" : [ ]
}, {
  "name" : "D_<U+00B4>Elia_Maria",
  "imports" : [ ]
}, {
  "name" : "Manuel_Norma_Noemi",
  "imports" : [ ]
}, {
  "name" : "Dorta_Alejandro",
  "imports" : [ ]
}, {
  "name" : "Benz_Inceborg_Tannhauser",
  "imports" : [ ]
}, {
  "name" : "Narvaja_Pablo",
  "imports" : [ ]
}, {
  "name" : "Yanez_Rodolfo_Martin",
  "imports" : [ ]
}, {
  "name" : "D<U+00B4>Angelo_Luis",
  "imports" : [ ]
}, {
  "name" : "Chiesa_Miriam_Daniela",
  "imports" : [ ]
}, {
  "name" : "Sindicato_de_Vendedores_de_Diarios__Revistas_y_Afi_Del_Interior",
  "imports" : [ ]
}, {
  "name" : "Izetta_Elina",
  "imports" : [ ]
}, {
  "name" : "Parrilli_Oscar",
  "imports" : [ "Bordon_Luis", "Angulo_Carmelo", "Brillo_Jose_Ricardo", "Sivanto_Eva", "Blanco_Pablo_Martin", "Dentesano_Ivone", "Gomez_de_Benitez_Nilda", "Carro_Jorge_Horacio", "Baraibar_Julio", "Gonzalez_Torrico_Katia_E", "Sandoval_Oscar", "Garcia_Costa_Victor_Oscar", "Viegas_Mendes_Jorge_Rufino", "Wainfeld_Mario" ]
}, {
  "name" : "Bordon_Luis",
  "imports" : [ ]
}, {
  "name" : "Angulo_Carmelo",
  "imports" : [ ]
}, {
  "name" : "Brillo_Jose_Ricardo",
  "imports" : [ ]
}, {
  "name" : "Sivanto_Eva",
  "imports" : [ ]
}, {
  "name" : "Blanco_Pablo_Martin",
  "imports" : [ ]
}, {
  "name" : "Dentesano_Ivone",
  "imports" : [ ]
}, {
  "name" : "Gomez_de_Benitez_Nilda",
  "imports" : [ ]
}, {
  "name" : "Carro_Jorge_Horacio",
  "imports" : [ ]
}, {
  "name" : "Baraibar_Julio",
  "imports" : [ ]
}, {
  "name" : "Gonzalez_Torrico_Katia_E",
  "imports" : [ ]
}, {
  "name" : "Sandoval_Oscar",
  "imports" : [ ]
}, {
  "name" : "Garcia_Costa_Victor_Oscar",
  "imports" : [ ]
}, {
  "name" : "Viegas_Mendes_Jorge_Rufino",
  "imports" : [ ]
}, {
  "name" : "Wainfeld_Mario",
  "imports" : [ ]
}, {
  "name" : "Mariotto_Juan_G",
  "imports" : [ "Vivori_Claudio", "Gimenez_Luis", "Picone_Nestor", "Carranza_Carlos", "Alvarez_Rodriguez_Cristina", "Flematti_Cecilio", "Lazzaro_Luis", "Mazzitelli_Luis", "Lupo_Tom", "Mercado_Silvia", "Donatucci_Ariel", "Soria_Jorge_Dioniisio", "Contissa_Nestor", "Rivero_Julio", "Pelicari_Mariana", "Moratto_Ricardo", "Boveda_Fernando", "Vargas_Estela", "D_Onofrio_Manuel", "Vitelli_Yolanda", "Peloso_Rogelio", "Barral_Patricia", "Rezzano_Ivana", "Lopez_Dolores", "Campolongo_Carlos" ]
}, {
  "name" : "Vivori_Claudio",
  "imports" : [ ]
}, {
  "name" : "Picone_Nestor",
  "imports" : [ ]
}, {
  "name" : "Carranza_Carlos",
  "imports" : [ ]
}, {
  "name" : "Alvarez_Rodriguez_Cristina",
  "imports" : [ ]
}, {
  "name" : "Flematti_Cecilio",
  "imports" : [ ]
}, {
  "name" : "Lazzaro_Luis",
  "imports" : [ ]
}, {
  "name" : "Mazzitelli_Luis",
  "imports" : [ ]
}, {
  "name" : "Lupo_Tom",
  "imports" : [ ]
}, {
  "name" : "Mercado_Silvia",
  "imports" : [ ]
}, {
  "name" : "Donatucci_Ariel",
  "imports" : [ ]
}, {
  "name" : "Contissa_Nestor",
  "imports" : [ ]
}, {
  "name" : "Rivero_Julio",
  "imports" : [ ]
}, {
  "name" : "Pelicari_Mariana",
  "imports" : [ ]
}, {
  "name" : "Moratto_Ricardo",
  "imports" : [ ]
}, {
  "name" : "Boveda_Fernando",
  "imports" : [ ]
}, {
  "name" : "Vargas_Estela",
  "imports" : [ ]
}, {
  "name" : "D_Onofrio_Manuel",
  "imports" : [ ]
}, {
  "name" : "Vitelli_Yolanda",
  "imports" : [ ]
}, {
  "name" : "Peloso_Rogelio",
  "imports" : [ ]
}, {
  "name" : "Barral_Patricia",
  "imports" : [ ]
}, {
  "name" : "Rezzano_Ivana",
  "imports" : [ ]
}, {
  "name" : "Lopez_Dolores",
  "imports" : [ ]
}, {
  "name" : "Campolongo_Carlos",
  "imports" : [ ]
}, {
  "name" : "Contissa_Nestor",
  "imports" : [ "Cammisa_Agustin" ]
}, {
  "name" : "Cammisa_Agustin",
  "imports" : [ ]
} ]