[ {
  "name" : "Colombo_Maria_Lucila",
  "imports" : [ "Mena_Marta", "Loisi_Osvaldo" ]
}, {
  "name" : "Mena_Marta",
  "imports" : [ ]
}, {
  "name" : "Loisi_Osvaldo",
  "imports" : [ ]
}, {
  "name" : "Arias_Duval_Martin_Augusto",
  "imports" : [ "Hutado_Sergio", "Winnik_Gabriela", "Racconto_Cristian__Arq", "Abarca_Walter", "Arias_Duval_Martin_Augusto", "Morales_Gaston", "Garcia_Gimenez_Alvaro", "Medica_Sergio", "Barbosa_Moreira_Marcio", "Dunlop_Michael", "Linares_Juan", "Arrieta_Ruben", "Postiglioni_Salvador__Dr", "Karmirshalyan_Vladimir", "Biacchi_Juan_Carlos" ]
}, {
  "name" : "Hutado_Sergio",
  "imports" : [ ]
}, {
  "name" : "Winnik_Gabriela",
  "imports" : [ ]
}, {
  "name" : "Racconto_Cristian__Arq",
  "imports" : [ ]
}, {
  "name" : "Abarca_Walter",
  "imports" : [ ]
}, {
  "name" : "Morales_Gaston",
  "imports" : [ ]
}, {
  "name" : "Garcia_Gimenez_Alvaro",
  "imports" : [ ]
}, {
  "name" : "Medica_Sergio",
  "imports" : [ ]
}, {
  "name" : "Barbosa_Moreira_Marcio",
  "imports" : [ ]
}, {
  "name" : "Dunlop_Michael",
  "imports" : [ ]
}, {
  "name" : "Linares_Juan",
  "imports" : [ ]
}, {
  "name" : "Arrieta_Ruben",
  "imports" : [ ]
}, {
  "name" : "Postiglioni_Salvador__Dr",
  "imports" : [ ]
}, {
  "name" : "Karmirshalyan_Vladimir",
  "imports" : [ ]
}, {
  "name" : "Biacchi_Juan_Carlos",
  "imports" : [ ]
}, {
  "name" : "Boudou_Amado",
  "imports" : [ "Pulti_Gustavo", "Mantega_Guido", "Descalzo_Alberto_Daniel", "Fabrega_Juan_Carlos", "Schiaretti_Juan", "Insfran_Gildo", "Zamora_Dr_Gerardo", "Elfar_Soha", "Beder_Herrera_Luis", "Cordeiro_Enio", "Jaque_Celso", "Gioja_Jose_Luis", "Alperovich_Jose", "Bonafini_Hebe", "Alba_Pedro" ]
}, {
  "name" : "Pulti_Gustavo",
  "imports" : [ ]
}, {
  "name" : "Mantega_Guido",
  "imports" : [ ]
}, {
  "name" : "Descalzo_Alberto_Daniel",
  "imports" : [ ]
}, {
  "name" : "Fabrega_Juan_Carlos",
  "imports" : [ ]
}, {
  "name" : "Schiaretti_Juan",
  "imports" : [ ]
}, {
  "name" : "Insfran_Gildo",
  "imports" : [ ]
}, {
  "name" : "Zamora_Dr_Gerardo",
  "imports" : [ ]
}, {
  "name" : "Elfar_Soha",
  "imports" : [ ]
}, {
  "name" : "Beder_Herrera_Luis",
  "imports" : [ ]
}, {
  "name" : "Cordeiro_Enio",
  "imports" : [ ]
}, {
  "name" : "Jaque_Celso",
  "imports" : [ ]
}, {
  "name" : "Gioja_Jose_Luis",
  "imports" : [ ]
}, {
  "name" : "Alperovich_Jose",
  "imports" : [ ]
}, {
  "name" : "Bonafini_Hebe",
  "imports" : [ ]
}, {
  "name" : "Alba_Pedro",
  "imports" : [ ]
}, {
  "name" : "Janices_Pedro_Daniel",
  "imports" : [ "Cali_Nicolas" ]
}, {
  "name" : "Cali_Nicolas",
  "imports" : [ ]
}, {
  "name" : "Thill_Eduardo_A",
  "imports" : [ "Piotti_Lopez_Hernan_Carlos", "Paglialunga_Alfredo", "Mollon_Fernando", "Chehebar_Alberto" ]
}, {
  "name" : "Piotti_Lopez_Hernan_Carlos",
  "imports" : [ ]
}, {
  "name" : "Paglialunga_Alfredo",
  "imports" : [ ]
}, {
  "name" : "Mollon_Fernando",
  "imports" : [ ]
}, {
  "name" : "Chehebar_Alberto",
  "imports" : [ ]
}, {
  "name" : "Gonzalez_Gaviola_Juan_Horacio",
  "imports" : [ "Cutuli_Jorge_Alfredo" ]
}, {
  "name" : "Cutuli_Jorge_Alfredo",
  "imports" : [ ]
}, {
  "name" : "Arce_Oscar_Adolfo",
  "imports" : [ "Falinari_Horacio", "Burzaco_Eugenio", "Martinez_Viademonte_Hugo", "Dominguez_Federico_Guillermo_Jose", "Gray_Fernando" ]
}, {
  "name" : "Falinari_Horacio",
  "imports" : [ ]
}, {
  "name" : "Burzaco_Eugenio",
  "imports" : [ ]
}, {
  "name" : "Martinez_Viademonte_Hugo",
  "imports" : [ ]
}, {
  "name" : "Dominguez_Federico_Guillermo_Jose",
  "imports" : [ ]
}, {
  "name" : "Gray_Fernando",
  "imports" : [ ]
}, {
  "name" : "Oliveri_Guillermo_Rodolfo",
  "imports" : [ "Scialaba_Raul", "Burman_Mario" ]
}, {
  "name" : "Scialaba_Raul",
  "imports" : [ ]
}, {
  "name" : "Burman_Mario",
  "imports" : [ ]
}, {
  "name" : "Perceval_Maria_Cristina",
  "imports" : [ "Bertranou_Julian", "Cotillo_Fernando", "Faur_Eleonor", "Herrero_Alvaro" ]
}, {
  "name" : "Bertranou_Julian",
  "imports" : [ ]
}, {
  "name" : "Cotillo_Fernando",
  "imports" : [ ]
}, {
  "name" : "Faur_Eleonor",
  "imports" : [ ]
}, {
  "name" : "Herrero_Alvaro",
  "imports" : [ ]
}, {
  "name" : "Abrile_de_Vollmer_Maria_Ines",
  "imports" : [ "Rivas_Axel", "Bombarolo_Felix" ]
}, {
  "name" : "Rivas_Axel",
  "imports" : [ ]
}, {
  "name" : "Bombarolo_Felix",
  "imports" : [ ]
}, {
  "name" : "Duhalde_Eduardo_Luis",
  "imports" : [ "Ferraresi_Jorge_Horacio" ]
}, {
  "name" : "Ferraresi_Jorge_Horacio",
  "imports" : [ ]
}, {
  "name" : "Cosentino_Adrian_Esteban",
  "imports" : [ "Chalia_Sonia", "Jaspersen_Frederick_Z", "Ryser_Federic", "Asaka_Takashi", "Peralta_Ramos_Santiago", "Vargas_Sebastian" ]
}, {
  "name" : "Chalia_Sonia",
  "imports" : [ ]
}, {
  "name" : "Jaspersen_Frederick_Z",
  "imports" : [ ]
}, {
  "name" : "Ryser_Federic",
  "imports" : [ ]
}, {
  "name" : "Asaka_Takashi",
  "imports" : [ ]
}, {
  "name" : "Peralta_Ramos_Santiago",
  "imports" : [ ]
}, {
  "name" : "Vargas_Sebastian",
  "imports" : [ ]
}, {
  "name" : "Guardia_Mendonca_Humberto",
  "imports" : [ "Canada_Jorge", "Bouzat_Gabriel" ]
}, {
  "name" : "Canada_Jorge",
  "imports" : [ ]
}, {
  "name" : "Bouzat_Gabriel",
  "imports" : [ ]
}, {
  "name" : "Granero_Jose_Ramon",
  "imports" : [ "Peralta_Fabian_Francisco", "Kohanoff_Rafael", "Vignolo_Jose_Luis" ]
}, {
  "name" : "Peralta_Fabian_Francisco",
  "imports" : [ ]
}, {
  "name" : "Kohanoff_Rafael",
  "imports" : [ ]
}, {
  "name" : "Vignolo_Jose_Luis",
  "imports" : [ ]
}, {
  "name" : "Baranao_Jose_Lino_Salvador",
  "imports" : [ "Reginato_Gianni", "Raiter_Gustavo", "Vainstok_Otilia", "Santiago_Martin_Lic" ]
}, {
  "name" : "Reginato_Gianni",
  "imports" : [ ]
}, {
  "name" : "Raiter_Gustavo",
  "imports" : [ ]
}, {
  "name" : "Vainstok_Otilia",
  "imports" : [ ]
}, {
  "name" : "Santiago_Martin_Lic",
  "imports" : [ ]
}, {
  "name" : "Sileoni_Alberto",
  "imports" : [ "Ferrari_Elisa", "Calchaqui_Mariel", "Gazit_Daniel" ]
}, {
  "name" : "Ferrari_Elisa",
  "imports" : [ ]
}, {
  "name" : "Calchaqui_Mariel",
  "imports" : [ ]
}, {
  "name" : "Gazit_Daniel",
  "imports" : [ ]
}, {
  "name" : "Kolm_Maria_Cristina",
  "imports" : [ "Moreno_Jos<U+00E8>_Arturo", "Barcelo_Sandra_E" ]
}, {
  "name" : "Moreno_Jos<U+00E8>_Arturo",
  "imports" : [ ]
}, {
  "name" : "Barcelo_Sandra_E",
  "imports" : [ ]
}, {
  "name" : "Simeonoff_Jorge_Gustavo",
  "imports" : [ "Seillant_Horacio_A" ]
}, {
  "name" : "Seillant_Horacio_A",
  "imports" : [ ]
}, {
  "name" : "Dibbern_Alberto_Ricardo",
  "imports" : [ "Cansanello_Oreste_Carlos" ]
}, {
  "name" : "Cansanello_Oreste_Carlos",
  "imports" : [ ]
}, {
  "name" : "Vessvessian_Marcela_Paola",
  "imports" : [ "Marck_Jason", "Solanas_Ra<U+00F9>l_Diputado_Nacional", "Curuchet_Ricardo", "Franco_Franco" ]
}, {
  "name" : "Marck_Jason",
  "imports" : [ ]
}, {
  "name" : "Solanas_Ra<U+00F9>l_Diputado_Nacional",
  "imports" : [ ]
}, {
  "name" : "Curuchet_Ricardo",
  "imports" : [ ]
}, {
  "name" : "Franco_Franco",
  "imports" : [ ]
}, {
  "name" : "Eluani_Andres",
  "imports" : [ "Nadra_Horacio" ]
}, {
  "name" : "Nadra_Horacio",
  "imports" : [ ]
}, {
  "name" : "Fernandez_de_Kirchner_Cristina",
  "imports" : [ "Boudou_Amado", "Manzur_Juan_Luis", "Brufau_Antoni", "Meyer_Carlos", "Taiana_Jorge", "Fernandez_Alberto", "Cardozo_Jorge", "Faraoni_Miguel", "Dominguez_Julian", "Carlotto_Estela" ]
}, {
  "name" : "Manzur_Juan_Luis",
  "imports" : [ ]
}, {
  "name" : "Brufau_Antoni",
  "imports" : [ ]
}, {
  "name" : "Meyer_Carlos",
  "imports" : [ ]
}, {
  "name" : "Taiana_Jorge",
  "imports" : [ ]
}, {
  "name" : "Fernandez_Alberto",
  "imports" : [ ]
}, {
  "name" : "Cardozo_Jorge",
  "imports" : [ ]
}, {
  "name" : "Faraoni_Miguel",
  "imports" : [ ]
}, {
  "name" : "Dominguez_Julian",
  "imports" : [ ]
}, {
  "name" : "Carlotto_Estela",
  "imports" : [ ]
}, {
  "name" : "De_Vido_Julio_M",
  "imports" : [ "Puricelli_Arturo", "Jorge_Oscar_Mario", "Presidencia_De_la_Nacion" ]
}, {
  "name" : "Puricelli_Arturo",
  "imports" : [ ]
}, {
  "name" : "Jorge_Oscar_Mario",
  "imports" : [ ]
}, {
  "name" : "Presidencia_De_la_Nacion",
  "imports" : [ ]
}, {
  "name" : "Randazzo_Anibal_Florencio",
  "imports" : [ "Feliu_Marcelo", "Capitanich_Jorge", "Arlia_Alejandro_G", "Sapag_Luz", "Pulti_Gustavo", "Celso_Jaque_X", "Jorge_Oscar_Mario", "Uribarri_Sergio_Daniel", "Urtubey_Juan_Manuel" ]
}, {
  "name" : "Feliu_Marcelo",
  "imports" : [ ]
}, {
  "name" : "Capitanich_Jorge",
  "imports" : [ ]
}, {
  "name" : "Arlia_Alejandro_G",
  "imports" : [ ]
}, {
  "name" : "Sapag_Luz",
  "imports" : [ ]
}, {
  "name" : "Celso_Jaque_X",
  "imports" : [ ]
}, {
  "name" : "Uribarri_Sergio_Daniel",
  "imports" : [ ]
}, {
  "name" : "Urtubey_Juan_Manuel",
  "imports" : [ ]
}, {
  "name" : "Garre_Nilda",
  "imports" : [ "Martinez_Vilma", "Santiago_Martin_Lic", "Acuna_Luis_E", "Eskenazi_Sebastian_Sr", "Insfran_Gildo", "Cordeiro_Enio" ]
}, {
  "name" : "Martinez_Vilma",
  "imports" : [ ]
}, {
  "name" : "Acuna_Luis_E",
  "imports" : [ ]
}, {
  "name" : "Eskenazi_Sebastian_Sr",
  "imports" : [ ]
}, {
  "name" : "Lorenzino_Hernan_Gaspar",
  "imports" : [ "Finkman_Javier", "Melin_Luis_Eduardo", "Blanco_Marcelo", "La_Tella_Guido", "Stancanelli_Nestor", "Taccetti_Victorio", "Silvani_Matias", "Alba_Pedro", "Marini_Federico", "Werning_Vladimir", "Cordeiro_Enio" ]
}, {
  "name" : "Finkman_Javier",
  "imports" : [ ]
}, {
  "name" : "Melin_Luis_Eduardo",
  "imports" : [ ]
}, {
  "name" : "Blanco_Marcelo",
  "imports" : [ ]
}, {
  "name" : "La_Tella_Guido",
  "imports" : [ ]
}, {
  "name" : "Stancanelli_Nestor",
  "imports" : [ ]
}, {
  "name" : "Taccetti_Victorio",
  "imports" : [ ]
}, {
  "name" : "Silvani_Matias",
  "imports" : [ ]
}, {
  "name" : "Marini_Federico",
  "imports" : [ ]
}, {
  "name" : "Werning_Vladimir",
  "imports" : [ ]
}, {
  "name" : "Pronsato_Antonio_Luis",
  "imports" : [ "Cordero_Andres" ]
}, {
  "name" : "Cordero_Andres",
  "imports" : [ ]
}, {
  "name" : "Abal_Medina_Juan_Manuel",
  "imports" : [ "Ruta_Carlos", "Rigo_Raul" ]
}, {
  "name" : "Ruta_Carlos",
  "imports" : [ ]
}, {
  "name" : "Rigo_Raul",
  "imports" : [ ]
}, {
  "name" : "Ruete_Rodrigo_Maria",
  "imports" : [ "Bossio_Diego_Luis" ]
}, {
  "name" : "Bossio_Diego_Luis",
  "imports" : [ ]
}, {
  "name" : "Bender_Gloria_Raquel",
  "imports" : [ "Jusid_Margarita" ]
}, {
  "name" : "Jusid_Margarita",
  "imports" : [ ]
}, {
  "name" : "Bossio_Diego_Luis",
  "imports" : [ "Fernandez_de_Kirchner_Cristina" ]
}, {
  "name" : "Martinez_Ricardo",
  "imports" : [ "D`Agostino_Omar", "Querald<U+00F2>_Miguel_<U+00C1>ngel", "Perez_Philip", "Butti_Maria_Eugenia", "Fernandez_Carlos", "Camino_Eduardo", "Maza_Sandra" ]
}, {
  "name" : "D`Agostino_Omar",
  "imports" : [ ]
}, {
  "name" : "Querald<U+00F2>_Miguel_<U+00C1>ngel",
  "imports" : [ ]
}, {
  "name" : "Perez_Philip",
  "imports" : [ ]
}, {
  "name" : "Butti_Maria_Eugenia",
  "imports" : [ ]
}, {
  "name" : "Fernandez_Carlos",
  "imports" : [ ]
}, {
  "name" : "Camino_Eduardo",
  "imports" : [ ]
}, {
  "name" : "Maza_Sandra",
  "imports" : [ ]
}, {
  "name" : "Ruiz_Alvaro_Daniel",
  "imports" : [ "Segovia_Rodolfo" ]
}, {
  "name" : "Segovia_Rodolfo",
  "imports" : [ ]
}, {
  "name" : "Estabillo_Jose_Arturo",
  "imports" : [ "Galarza_Juan_Carlos", "Brizuela_del_Moral_Eduardo", "Strada_Ing_Tomas_Jose_Strada", "Alvarez_Rodriguez_Cristina", "Graglia_Mario_Gustavo", "Cufre_Marcelo_Gustavo", "Zamora_Dr_Gerardo", "Alperovich_Jose", "Testa_Hugo_Atilio", "Jaque_Celso", "Amaya_Domingo_Luis" ]
}, {
  "name" : "Galarza_Juan_Carlos",
  "imports" : [ ]
}, {
  "name" : "Brizuela_del_Moral_Eduardo",
  "imports" : [ ]
}, {
  "name" : "Strada_Ing_Tomas_Jose_Strada",
  "imports" : [ ]
}, {
  "name" : "Alvarez_Rodriguez_Cristina",
  "imports" : [ ]
}, {
  "name" : "Graglia_Mario_Gustavo",
  "imports" : [ ]
}, {
  "name" : "Cufre_Marcelo_Gustavo",
  "imports" : [ ]
}, {
  "name" : "Testa_Hugo_Atilio",
  "imports" : [ ]
}, {
  "name" : "Amaya_Domingo_Luis",
  "imports" : [ ]
}, {
  "name" : "Beuret_Luis_Alberto",
  "imports" : [ "Ibanez_Guillermo", "Baratchart_Rogelio", "Bravo_Oscar_Horacio", "Vendrell_Gabriel", "Gatti_Juan_Marcelo", "Turri_Horacio" ]
}, {
  "name" : "Ibanez_Guillermo",
  "imports" : [ ]
}, {
  "name" : "Baratchart_Rogelio",
  "imports" : [ ]
}, {
  "name" : "Bravo_Oscar_Horacio",
  "imports" : [ ]
}, {
  "name" : "Vendrell_Gabriel",
  "imports" : [ ]
}, {
  "name" : "Gatti_Juan_Marcelo",
  "imports" : [ ]
}, {
  "name" : "Turri_Horacio",
  "imports" : [ ]
}, {
  "name" : "Righi_Roberto_Jorge",
  "imports" : [ "De_Rosa_Leandro_Marcelo" ]
}, {
  "name" : "De_Rosa_Leandro_Marcelo",
  "imports" : [ ]
}, {
  "name" : "Baratta_Roberto",
  "imports" : [ "Mindlin_Marcelo", "Otheguy_Hector" ]
}, {
  "name" : "Mindlin_Marcelo",
  "imports" : [ ]
}, {
  "name" : "Otheguy_Hector",
  "imports" : [ ]
}, {
  "name" : "Gras_Bucetto_Mariana",
  "imports" : [ "Gitart_Sebastian", "Barraza_Simon_Ignacio" ]
}, {
  "name" : "Gitart_Sebastian",
  "imports" : [ ]
}, {
  "name" : "Barraza_Simon_Ignacio",
  "imports" : [ ]
}, {
  "name" : "Brizzi_Carlos_Marcelo",
  "imports" : [ "Vera_Luis", "Fuster_Carlos_Anibal", "Fernandez_Patricia", "Alonso_Cristian_Adrian", "D_Alfonso_Gladys", "Altschuler_Jeronimo", "Quiroga_Mauro" ]
}, {
  "name" : "Vera_Luis",
  "imports" : [ ]
}, {
  "name" : "Fuster_Carlos_Anibal",
  "imports" : [ ]
}, {
  "name" : "Fernandez_Patricia",
  "imports" : [ ]
}, {
  "name" : "Alonso_Cristian_Adrian",
  "imports" : [ ]
}, {
  "name" : "D_Alfonso_Gladys",
  "imports" : [ ]
}, {
  "name" : "Altschuler_Jeronimo",
  "imports" : [ ]
}, {
  "name" : "Quiroga_Mauro",
  "imports" : [ ]
}, {
  "name" : "Gentili_Gustavo_Marcelo",
  "imports" : [ "Conocchiari_Alberto_Ruben", "Cansanello_Oreste_Carlos", "Hernandez_Maria_Ines", "Arrieta_Gustavo" ]
}, {
  "name" : "Conocchiari_Alberto_Ruben",
  "imports" : [ ]
}, {
  "name" : "Hernandez_Maria_Ines",
  "imports" : [ ]
}, {
  "name" : "Arrieta_Gustavo",
  "imports" : [ ]
}, {
  "name" : "Martini_Oscar_Alberto",
  "imports" : [ "Irigaray_Silvia" ]
}, {
  "name" : "Irigaray_Silvia",
  "imports" : [ ]
}, {
  "name" : "Martin_Daniel",
  "imports" : [ "Molina_Claudio" ]
}, {
  "name" : "Molina_Claudio",
  "imports" : [ ]
}, {
  "name" : "Periotti_Nelson",
  "imports" : [ "Pulti_Gustavo", "Clerici_Estela", "Zaballa_Hernan_Miguel", "Morales_Luis", "Castillo_Marin_Nazareno", "Closs_Maurice_Fabian", "Contreras_Adrian" ]
}, {
  "name" : "Clerici_Estela",
  "imports" : [ ]
}, {
  "name" : "Zaballa_Hernan_Miguel",
  "imports" : [ ]
}, {
  "name" : "Morales_Luis",
  "imports" : [ ]
}, {
  "name" : "Castillo_Marin_Nazareno",
  "imports" : [ ]
}, {
  "name" : "Closs_Maurice_Fabian",
  "imports" : [ ]
}, {
  "name" : "Contreras_Adrian",
  "imports" : [ ]
}, {
  "name" : "Godoy_Jorge_Omar",
  "imports" : [ "Arecco_Carlos_Alberto", "Sibilla_Gustavo", "Guacone_Pablo" ]
}, {
  "name" : "Arecco_Carlos_Alberto",
  "imports" : [ ]
}, {
  "name" : "Sibilla_Gustavo",
  "imports" : [ ]
}, {
  "name" : "Guacone_Pablo",
  "imports" : [ ]
}, {
  "name" : "Landaburu_Juan_Laureano_Fabian",
  "imports" : [ "Valles_Juan_Carlos" ]
}, {
  "name" : "Valles_Juan_Carlos",
  "imports" : [ ]
}, {
  "name" : "Fontdevila_Pablo_Antonio",
  "imports" : [ "Pomies_Patricia", "Elias_Daniel", "Fernandez_de_Kirchner_Cristina" ]
}, {
  "name" : "Pomies_Patricia",
  "imports" : [ ]
}, {
  "name" : "Elias_Daniel",
  "imports" : [ ]
}, {
  "name" : "Cormick_Hugo",
  "imports" : [ "Cormick_Hugo_Tomas" ]
}, {
  "name" : "Cormick_Hugo_Tomas",
  "imports" : [ ]
}, {
  "name" : "Vanoli_Long_Biocca_Alejandro",
  "imports" : [ "Mindlin_Marcelo", "Sbattella_Jose" ]
}, {
  "name" : "Sbattella_Jose",
  "imports" : [ ]
}, {
  "name" : "Dalairac_Hugo_Anibal",
  "imports" : [ "Saglione_Gonzalo", "Lavot_Cecilia_Maria", "Pichetto_Juan_Manuel", "Capra_Guillermo", "Accastello_Eduardo_Luis" ]
}, {
  "name" : "Saglione_Gonzalo",
  "imports" : [ ]
}, {
  "name" : "Lavot_Cecilia_Maria",
  "imports" : [ ]
}, {
  "name" : "Pichetto_Juan_Manuel",
  "imports" : [ ]
}, {
  "name" : "Capra_Guillermo",
  "imports" : [ ]
}, {
  "name" : "Accastello_Eduardo_Luis",
  "imports" : [ ]
}, {
  "name" : "Sicaro_Antonio_Eduardo",
  "imports" : [ "Gorgal_Diego", "Iglesias_Walter" ]
}, {
  "name" : "Gorgal_Diego",
  "imports" : [ ]
}, {
  "name" : "Iglesias_Walter",
  "imports" : [ ]
}, {
  "name" : "Bibiloni_Homero_Maximo",
  "imports" : [ "Vecslir_Oscar_Hugo", "Esber_Horacio", "Moler_Emilce", "Brunswig_Herman_Miguel", "Garcia_Luis", "Boero_Norma", "Bresciano_Alberto", "Hogan_Patricio", "Rujana_Mario_Ruben", "Merega_Silvia", "Bay_Hugo_Eduardo", "Bianchi_Eduardo_Dante", "Lopez_Fabian", "Dominguez_Julian", "Mariotto_Gabriel", "Ponzio_Raul", "Basterra_Luis", "Pereyra_Julio_Cesar", "Molina_Jose_Luis", "Orduna_Hernan", "Granovsky_Martin", "Bahilo_Juan_Jose", "Fernandez_de_Kirchner_Cristina", "Mondino_Eduardo", "Gaincerain_Jose_Lucas", "Dress_Gross_Franz", "Savino_Atilio" ]
}, {
  "name" : "Vecslir_Oscar_Hugo",
  "imports" : [ ]
}, {
  "name" : "Esber_Horacio",
  "imports" : [ ]
}, {
  "name" : "Moler_Emilce",
  "imports" : [ ]
}, {
  "name" : "Brunswig_Herman_Miguel",
  "imports" : [ ]
}, {
  "name" : "Garcia_Luis",
  "imports" : [ ]
}, {
  "name" : "Boero_Norma",
  "imports" : [ ]
}, {
  "name" : "Bresciano_Alberto",
  "imports" : [ ]
}, {
  "name" : "Hogan_Patricio",
  "imports" : [ ]
}, {
  "name" : "Rujana_Mario_Ruben",
  "imports" : [ ]
}, {
  "name" : "Merega_Silvia",
  "imports" : [ ]
}, {
  "name" : "Bay_Hugo_Eduardo",
  "imports" : [ ]
}, {
  "name" : "Bianchi_Eduardo_Dante",
  "imports" : [ ]
}, {
  "name" : "Lopez_Fabian",
  "imports" : [ ]
}, {
  "name" : "Mariotto_Gabriel",
  "imports" : [ ]
}, {
  "name" : "Ponzio_Raul",
  "imports" : [ ]
}, {
  "name" : "Basterra_Luis",
  "imports" : [ ]
}, {
  "name" : "Pereyra_Julio_Cesar",
  "imports" : [ ]
}, {
  "name" : "Molina_Jose_Luis",
  "imports" : [ ]
}, {
  "name" : "Orduna_Hernan",
  "imports" : [ ]
}, {
  "name" : "Granovsky_Martin",
  "imports" : [ ]
}, {
  "name" : "Bahilo_Juan_Jose",
  "imports" : [ ]
}, {
  "name" : "Mondino_Eduardo",
  "imports" : [ ]
}, {
  "name" : "Gaincerain_Jose_Lucas",
  "imports" : [ ]
}, {
  "name" : "Dress_Gross_Franz",
  "imports" : [ ]
}, {
  "name" : "Savino_Atilio",
  "imports" : [ ]
}, {
  "name" : "Fernandez_Anibal_Domingo",
  "imports" : [ "Zabala_Silvina", "Zannini_Carlos", "Reposo_Daniel", "Coradazzi_Fernando", "Da_Rocha_Joaquin", "Scoccimarro_Alfredo", "Manzur_Juan_Luis", "Rodriguez_Ricardo", "<U+00D1>amandu_Alejandro", "Bauer_Tristan", "Boudou_Amado", "Gaincerain_Jose_Lucas", "Tn_-", "Guastavino_Pedro", "Plo_Maria_Jesus", "Fernandez_de_Kirchner_Cristina", "Arias_Duval_Martin_Augusto", "Herrera_Griselda", "Matus_Fabian", "Alak_Julio_Cesar", "Fernandez_Nicolas", "Sica_Dante", "Molluso_Luciano", "Rodriguez_Alejandrdo", "Gallardo_Miguel_Angel", "Ross_Juan", "Paladino_Pablo", "Cunarro_Monica", "Romero_Berry_Azul", "Curia_Eugenio", "Lebed_Mariana", "Rizzi_Fernando", "Tomada_Carlos", "Fabrega_Juan_Carlos", "Fernandez_Novoa_Sergio", "Calabrese_Alberto", "Echegaray_Ricardo", "Abarca_Walter", "Insaurralde_Martin", "Frasquet_Gustavo", "Mariotto_Gabriel", "Alarcon_Maria_del_Carmen", "Fellner_Eduardo_Alfredo", "Dominguez_Julian", "Guarnacci_Graciela", "Vittori_Gustavo", "Renna_Carlos", "Descalzo_Eduardo", "Santiago_Martin_Lic", "David_Pedro", "Calchaqui_Mariel", "Copal_-", "Cordeiro_Enio", "Vasquez_Ocampo_Jose_Maria", "Conferencia_de_Prensa_-", "Rodriguez_Ricardo_Eusebio", "Domenech_Roberto_Jesus", "Beder_Herrera_Luis_Dr", "Fernandez_Garrido_Diego", "Gatti_Eduardo", "Grondona_Julio", "Palacio_Ricardo", "Pichetto_Miguel_<U+00C1>ngel", "Gorostiza_Ricardo", "Schulz_Juan_Carlos", "Castagneto_Carlos", "Mazzon_Juan_Carlos", "Liuzzi_Carlos", "Larraz_Nicanor", "Arslanian_Leon_Carlos", "Giraud_Victor", "Asvazadourian_Jean-Pierre", "Berrozpe_Eduardo", "Morgado_Claudio", "Thill_Eduardo", "Lopez_Carlos", "Diaz_Dario", "Urribarri_Sergio", "Abramowski_Carla", "Ferrara_Pedro", "Rodriguez_Canedo_Fernando", "Molina_Juan_Carlos", "Cingolani_Enrique_Julio", "Ottavis_Jose", "Abramowsky_Carla", "Ross__Dr_Juan" ]
}, {
  "name" : "Zabala_Silvina",
  "imports" : [ ]
}, {
  "name" : "Zannini_Carlos",
  "imports" : [ ]
}, {
  "name" : "Reposo_Daniel",
  "imports" : [ ]
}, {
  "name" : "Coradazzi_Fernando",
  "imports" : [ ]
}, {
  "name" : "Da_Rocha_Joaquin",
  "imports" : [ ]
}, {
  "name" : "Scoccimarro_Alfredo",
  "imports" : [ ]
}, {
  "name" : "Rodriguez_Ricardo",
  "imports" : [ ]
}, {
  "name" : "<U+00D1>amandu_Alejandro",
  "imports" : [ ]
}, {
  "name" : "Bauer_Tristan",
  "imports" : [ ]
}, {
  "name" : "Tn_-",
  "imports" : [ ]
}, {
  "name" : "Guastavino_Pedro",
  "imports" : [ ]
}, {
  "name" : "Plo_Maria_Jesus",
  "imports" : [ ]
}, {
  "name" : "Herrera_Griselda",
  "imports" : [ ]
}, {
  "name" : "Matus_Fabian",
  "imports" : [ ]
}, {
  "name" : "Alak_Julio_Cesar",
  "imports" : [ ]
}, {
  "name" : "Fernandez_Nicolas",
  "imports" : [ ]
}, {
  "name" : "Sica_Dante",
  "imports" : [ ]
}, {
  "name" : "Molluso_Luciano",
  "imports" : [ ]
}, {
  "name" : "Rodriguez_Alejandrdo",
  "imports" : [ ]
}, {
  "name" : "Gallardo_Miguel_Angel",
  "imports" : [ ]
}, {
  "name" : "Ross_Juan",
  "imports" : [ ]
}, {
  "name" : "Paladino_Pablo",
  "imports" : [ ]
}, {
  "name" : "Cunarro_Monica",
  "imports" : [ ]
}, {
  "name" : "Romero_Berry_Azul",
  "imports" : [ ]
}, {
  "name" : "Curia_Eugenio",
  "imports" : [ ]
}, {
  "name" : "Lebed_Mariana",
  "imports" : [ ]
}, {
  "name" : "Rizzi_Fernando",
  "imports" : [ ]
}, {
  "name" : "Tomada_Carlos",
  "imports" : [ ]
}, {
  "name" : "Fernandez_Novoa_Sergio",
  "imports" : [ ]
}, {
  "name" : "Calabrese_Alberto",
  "imports" : [ ]
}, {
  "name" : "Echegaray_Ricardo",
  "imports" : [ ]
}, {
  "name" : "Insaurralde_Martin",
  "imports" : [ ]
}, {
  "name" : "Frasquet_Gustavo",
  "imports" : [ ]
}, {
  "name" : "Alarcon_Maria_del_Carmen",
  "imports" : [ ]
}, {
  "name" : "Fellner_Eduardo_Alfredo",
  "imports" : [ ]
}, {
  "name" : "Guarnacci_Graciela",
  "imports" : [ ]
}, {
  "name" : "Vittori_Gustavo",
  "imports" : [ ]
}, {
  "name" : "Renna_Carlos",
  "imports" : [ ]
}, {
  "name" : "Descalzo_Eduardo",
  "imports" : [ ]
}, {
  "name" : "David_Pedro",
  "imports" : [ ]
}, {
  "name" : "Copal_-",
  "imports" : [ ]
}, {
  "name" : "Vasquez_Ocampo_Jose_Maria",
  "imports" : [ ]
}, {
  "name" : "Conferencia_de_Prensa_-",
  "imports" : [ ]
}, {
  "name" : "Rodriguez_Ricardo_Eusebio",
  "imports" : [ ]
}, {
  "name" : "Domenech_Roberto_Jesus",
  "imports" : [ ]
}, {
  "name" : "Beder_Herrera_Luis_Dr",
  "imports" : [ ]
}, {
  "name" : "Fernandez_Garrido_Diego",
  "imports" : [ ]
}, {
  "name" : "Gatti_Eduardo",
  "imports" : [ ]
}, {
  "name" : "Grondona_Julio",
  "imports" : [ ]
}, {
  "name" : "Palacio_Ricardo",
  "imports" : [ ]
}, {
  "name" : "Pichetto_Miguel_<U+00C1>ngel",
  "imports" : [ ]
}, {
  "name" : "Gorostiza_Ricardo",
  "imports" : [ ]
}, {
  "name" : "Schulz_Juan_Carlos",
  "imports" : [ ]
}, {
  "name" : "Castagneto_Carlos",
  "imports" : [ ]
}, {
  "name" : "Mazzon_Juan_Carlos",
  "imports" : [ ]
}, {
  "name" : "Liuzzi_Carlos",
  "imports" : [ ]
}, {
  "name" : "Larraz_Nicanor",
  "imports" : [ ]
}, {
  "name" : "Arslanian_Leon_Carlos",
  "imports" : [ ]
}, {
  "name" : "Giraud_Victor",
  "imports" : [ ]
}, {
  "name" : "Asvazadourian_Jean-Pierre",
  "imports" : [ ]
}, {
  "name" : "Berrozpe_Eduardo",
  "imports" : [ ]
}, {
  "name" : "Morgado_Claudio",
  "imports" : [ ]
}, {
  "name" : "Thill_Eduardo",
  "imports" : [ ]
}, {
  "name" : "Lopez_Carlos",
  "imports" : [ ]
}, {
  "name" : "Diaz_Dario",
  "imports" : [ ]
}, {
  "name" : "Urribarri_Sergio",
  "imports" : [ ]
}, {
  "name" : "Abramowski_Carla",
  "imports" : [ ]
}, {
  "name" : "Ferrara_Pedro",
  "imports" : [ ]
}, {
  "name" : "Rodriguez_Canedo_Fernando",
  "imports" : [ ]
}, {
  "name" : "Molina_Juan_Carlos",
  "imports" : [ ]
}, {
  "name" : "Cingolani_Enrique_Julio",
  "imports" : [ ]
}, {
  "name" : "Ottavis_Jose",
  "imports" : [ ]
}, {
  "name" : "Abramowsky_Carla",
  "imports" : [ ]
}, {
  "name" : "Ross__Dr_Juan",
  "imports" : [ ]
}, {
  "name" : "Vallecca_Nestor_Jorge",
  "imports" : [ "Arias_Duval_Martin", "Bidart_Nestor_Horacio", "Addor_Neto_Alexandre", "Tullio_Alejandro" ]
}, {
  "name" : "Arias_Duval_Martin",
  "imports" : [ ]
}, {
  "name" : "Bidart_Nestor_Horacio",
  "imports" : [ ]
}, {
  "name" : "Addor_Neto_Alexandre",
  "imports" : [ ]
}, {
  "name" : "Tullio_Alejandro",
  "imports" : [ ]
}, {
  "name" : "Meyer_Carlos_Enrique",
  "imports" : [ "Hernaiz_Ignacio", "Gandini_Patricia", "Salim_Juan", "Ghezzi_Oscar", "Yauhar_Norberto", "Irurtia_Gonzalo", "Lamota_Luciana", "Acosta_Gabriel", "Barassi_Luis_Maria" ]
}, {
  "name" : "Hernaiz_Ignacio",
  "imports" : [ ]
}, {
  "name" : "Gandini_Patricia",
  "imports" : [ ]
}, {
  "name" : "Salim_Juan",
  "imports" : [ ]
}, {
  "name" : "Ghezzi_Oscar",
  "imports" : [ ]
}, {
  "name" : "Yauhar_Norberto",
  "imports" : [ ]
}, {
  "name" : "Irurtia_Gonzalo",
  "imports" : [ ]
}, {
  "name" : "Lamota_Luciana",
  "imports" : [ ]
}, {
  "name" : "Acosta_Gabriel",
  "imports" : [ ]
}, {
  "name" : "Barassi_Luis_Maria",
  "imports" : [ ]
}, {
  "name" : "Pedelaborde_Isabel_Elena",
  "imports" : [ "Tessore_Eduardo", "Turinetto_Jorge", "Mirkin_Beatriz" ]
}, {
  "name" : "Tessore_Eduardo",
  "imports" : [ ]
}, {
  "name" : "Turinetto_Jorge",
  "imports" : [ ]
}, {
  "name" : "Mirkin_Beatriz",
  "imports" : [ ]
}, {
  "name" : "Cingolani_Enrique_Julio",
  "imports" : [ "Bonzon_Juan_Carlos", "Donate_Miguel_Angel" ]
}, {
  "name" : "Bonzon_Juan_Carlos",
  "imports" : [ ]
}, {
  "name" : "Donate_Miguel_Angel",
  "imports" : [ ]
}, {
  "name" : "Arq_Salas_Lisandro",
  "imports" : [ "Iglesias_Daniel" ]
}, {
  "name" : "Iglesias_Daniel",
  "imports" : [ ]
}, {
  "name" : "Manzur_Juan_Luis",
  "imports" : [ "Mussi_Juan_Jose", "Di_Sabatino_Daniel", "West_Ocampo_Carlos", "Vaquero_Francisco", "Bellagio_Ricardo_Ernesto", "Leguizamon_Maria_Laura", "Granero_Jose_Ramon", "Urbani_Victor", "Mascoto_Aleandro", "Dominguez_Julian", "Martinez_Luis_Cesar", "Gonzalez_Jorge", "Grieco_Maria_Haydee", "Mazu_Horacio_Matias", "Gray_Fernando", "Schiavi_Juan_Pablo" ]
}, {
  "name" : "Mussi_Juan_Jose",
  "imports" : [ ]
}, {
  "name" : "Di_Sabatino_Daniel",
  "imports" : [ ]
}, {
  "name" : "West_Ocampo_Carlos",
  "imports" : [ ]
}, {
  "name" : "Vaquero_Francisco",
  "imports" : [ ]
}, {
  "name" : "Bellagio_Ricardo_Ernesto",
  "imports" : [ ]
}, {
  "name" : "Leguizamon_Maria_Laura",
  "imports" : [ ]
}, {
  "name" : "Urbani_Victor",
  "imports" : [ ]
}, {
  "name" : "Mascoto_Aleandro",
  "imports" : [ ]
}, {
  "name" : "Martinez_Luis_Cesar",
  "imports" : [ ]
}, {
  "name" : "Gonzalez_Jorge",
  "imports" : [ ]
}, {
  "name" : "Grieco_Maria_Haydee",
  "imports" : [ ]
}, {
  "name" : "Mazu_Horacio_Matias",
  "imports" : [ ]
}, {
  "name" : "Schiavi_Juan_Pablo",
  "imports" : [ ]
}, {
  "name" : "Zabala_Silvina_Elena",
  "imports" : [ "Taccetti_Victorio", "Guastavino_Pedro" ]
}, {
  "name" : "Rotolo_Benito_Italo",
  "imports" : [ "Gomez_Oscar_Marciano" ]
}, {
  "name" : "Gomez_Oscar_Marciano",
  "imports" : [ ]
}, {
  "name" : "Giorgi_Debora_Adriana",
  "imports" : [ "Roza_Ricardo", "Zamora_Dr_Gerardo", "Lascurain_Juan_Carlos", "Hogan_Patricio", "Rapallini_Martin", "Fernandez_Roberto_C", "Martinez_Vilma", "Petersen_Bjarne" ]
}, {
  "name" : "Roza_Ricardo",
  "imports" : [ ]
}, {
  "name" : "Lascurain_Juan_Carlos",
  "imports" : [ ]
}, {
  "name" : "Rapallini_Martin",
  "imports" : [ ]
}, {
  "name" : "Fernandez_Roberto_C",
  "imports" : [ ]
}, {
  "name" : "Petersen_Bjarne",
  "imports" : [ ]
}, {
  "name" : "Cobos_Julio_Cesar",
  "imports" : [ "Artaza_Eugenio", "Llano_Ramos_Blas_Antonio" ]
}, {
  "name" : "Artaza_Eugenio",
  "imports" : [ ]
}, {
  "name" : "Llano_Ramos_Blas_Antonio",
  "imports" : [ ]
}, {
  "name" : "Ghetti_Roberto_Conrado",
  "imports" : [ "Arriola_Walter_Alfredo" ]
}, {
  "name" : "Arriola_Walter_Alfredo",
  "imports" : [ ]
}, {
  "name" : "Barbosa_Moreira_Marcio",
  "imports" : [ "Kniess_G<U+00FC>nter" ]
}, {
  "name" : "Kniess_G<U+00FC>nter",
  "imports" : [ ]
}, {
  "name" : "Tomada_Carlos_Alfonso",
  "imports" : [ "Chavez_Jorge", "Giaigischia_Jose_Ernesto", "Yasky_Hugo", "Salas_Oscar", "Theodor_Silvia_Elizabeth", "Palazzo_Sergio_Omar", "Inverivizzi_Edelma", "Sian_Ernesto" ]
}, {
  "name" : "Chavez_Jorge",
  "imports" : [ ]
}, {
  "name" : "Giaigischia_Jose_Ernesto",
  "imports" : [ ]
}, {
  "name" : "Yasky_Hugo",
  "imports" : [ ]
}, {
  "name" : "Salas_Oscar",
  "imports" : [ ]
}, {
  "name" : "Theodor_Silvia_Elizabeth",
  "imports" : [ ]
}, {
  "name" : "Palazzo_Sergio_Omar",
  "imports" : [ ]
}, {
  "name" : "Inverivizzi_Edelma",
  "imports" : [ ]
}, {
  "name" : "Sian_Ernesto",
  "imports" : [ ]
}, {
  "name" : "Parrilli_Oscar",
  "imports" : [ "Del_Rio_Francisco", "Pineyro_Iniguez_Carlos", "Macedo_Horacio", "Ivoskus_Ricardo", "De_la_Mata_Fernandez_Judith", "Curuchet_Ricardo", "Balza_Martin_Antonio" ]
}, {
  "name" : "Del_Rio_Francisco",
  "imports" : [ ]
}, {
  "name" : "Pineyro_Iniguez_Carlos",
  "imports" : [ ]
}, {
  "name" : "Macedo_Horacio",
  "imports" : [ ]
}, {
  "name" : "Ivoskus_Ricardo",
  "imports" : [ ]
}, {
  "name" : "De_la_Mata_Fernandez_Judith",
  "imports" : [ ]
}, {
  "name" : "Balza_Martin_Antonio",
  "imports" : [ ]
}, {
  "name" : "Ceccatto_Hermeregildo_Alejandro_Ramon",
  "imports" : [ "Sanchez_Guillermo", "Mastriani_Mario" ]
}, {
  "name" : "Sanchez_Guillermo",
  "imports" : [ ]
}, {
  "name" : "Mastriani_Mario",
  "imports" : [ ]
}, {
  "name" : "Gras_Buscetto_Mariana",
  "imports" : [ "Flesman_Luciano" ]
}, {
  "name" : "Flesman_Luciano",
  "imports" : [ ]
}, {
  "name" : "Lopez_Gustavo_Fernando",
  "imports" : [ "Chavez_Silvia", "Demaio_Iliana" ]
}, {
  "name" : "Chavez_Silvia",
  "imports" : [ ]
}, {
  "name" : "Demaio_Iliana",
  "imports" : [ ]
} ]