[ {
  "name" : "Sauret_Hector",
  "imports" : [ "Gussoni_Humberto_Angel" ]
}, {
  "name" : "Gussoni_Humberto_Angel",
  "imports" : [ ]
}, {
  "name" : "Amicarelli_Hugo",
  "imports" : [ "Wagner_Eduardo", "Margaria_Luis" ]
}, {
  "name" : "Wagner_Eduardo",
  "imports" : [ ]
}, {
  "name" : "Margaria_Luis",
  "imports" : [ ]
}, {
  "name" : "Fernandez_Rita_Andrea",
  "imports" : [ "Sanchez_Cristian" ]
}, {
  "name" : "Sanchez_Cristian",
  "imports" : [ ]
}, {
  "name" : "Chevalier_Jorge_Alberto",
  "imports" : [ "Corino_Carlos_Enrique", "Fernandez_Maguer_Ernesto", "Valladares_Gabriel_Pablo" ]
}, {
  "name" : "Corino_Carlos_Enrique",
  "imports" : [ ]
}, {
  "name" : "Fernandez_Maguer_Ernesto",
  "imports" : [ ]
}, {
  "name" : "Valladares_Gabriel_Pablo",
  "imports" : [ ]
}, {
  "name" : "Perrone_Graciela_Teresa",
  "imports" : [ "Cyranek_Gunther", "Villar_Gabriela", "Rodriguez_Rolando", "Vazquez_Marcos", "Salvatori_Roberto" ]
}, {
  "name" : "Cyranek_Gunther",
  "imports" : [ ]
}, {
  "name" : "Villar_Gabriela",
  "imports" : [ ]
}, {
  "name" : "Rodriguez_Rolando",
  "imports" : [ ]
}, {
  "name" : "Vazquez_Marcos",
  "imports" : [ ]
}, {
  "name" : "Salvatori_Roberto",
  "imports" : [ ]
}, {
  "name" : "Moncalvillo_Adelina",
  "imports" : [ "Alconada_Carlos", "Miro_Rodrigo", "Acciardi_Carlos", "Curis_Mabel", "Lorenzo_Cristina", "Muniz_Carlos", "Lupo_Tom", "Silva_Miguel_Angel", "Iniguez_Silvia", "Fuentes_Rey_Guillermo", "Mona_Mon", "Lopez_Guillermo", "Sosa_Matilde", "Farias_Gomez_Chango", "Perez_Antonio" ]
}, {
  "name" : "Alconada_Carlos",
  "imports" : [ ]
}, {
  "name" : "Miro_Rodrigo",
  "imports" : [ ]
}, {
  "name" : "Acciardi_Carlos",
  "imports" : [ ]
}, {
  "name" : "Curis_Mabel",
  "imports" : [ ]
}, {
  "name" : "Lorenzo_Cristina",
  "imports" : [ ]
}, {
  "name" : "Muniz_Carlos",
  "imports" : [ ]
}, {
  "name" : "Lupo_Tom",
  "imports" : [ ]
}, {
  "name" : "Silva_Miguel_Angel",
  "imports" : [ ]
}, {
  "name" : "Iniguez_Silvia",
  "imports" : [ ]
}, {
  "name" : "Fuentes_Rey_Guillermo",
  "imports" : [ ]
}, {
  "name" : "Mona_Mon",
  "imports" : [ ]
}, {
  "name" : "Lopez_Guillermo",
  "imports" : [ ]
}, {
  "name" : "Sosa_Matilde",
  "imports" : [ ]
}, {
  "name" : "Farias_Gomez_Chango",
  "imports" : [ ]
}, {
  "name" : "Perez_Antonio",
  "imports" : [ ]
}, {
  "name" : "Stahlschmidt_Alfredo_Augusto",
  "imports" : [ "Scarpati_Olga_Eugenia", "Episcopo_Eduardo", "Garcia_Luis_Maria", "Marti_Alejandro", "Casoli_Carlos_Alberto" ]
}, {
  "name" : "Scarpati_Olga_Eugenia",
  "imports" : [ ]
}, {
  "name" : "Episcopo_Eduardo",
  "imports" : [ ]
}, {
  "name" : "Garcia_Luis_Maria",
  "imports" : [ ]
}, {
  "name" : "Marti_Alejandro",
  "imports" : [ ]
}, {
  "name" : "Casoli_Carlos_Alberto",
  "imports" : [ ]
}, {
  "name" : "Herms_Rodolfo_Hernan",
  "imports" : [ "Perez_Vovard_Nestor", "Bianco_Eduardo", "Marrapodi_Alicia", "Bauzo_Juan_Alberto", "Stahlschmidt_Alfredo", "Montagna_Antonio", "Escobar_Tomas", "Fraguglia_Juan" ]
}, {
  "name" : "Perez_Vovard_Nestor",
  "imports" : [ ]
}, {
  "name" : "Bianco_Eduardo",
  "imports" : [ ]
}, {
  "name" : "Marrapodi_Alicia",
  "imports" : [ ]
}, {
  "name" : "Bauzo_Juan_Alberto",
  "imports" : [ ]
}, {
  "name" : "Stahlschmidt_Alfredo",
  "imports" : [ ]
}, {
  "name" : "Montagna_Antonio",
  "imports" : [ ]
}, {
  "name" : "Escobar_Tomas",
  "imports" : [ ]
}, {
  "name" : "Fraguglia_Juan",
  "imports" : [ ]
}, {
  "name" : "Vallone_Miguel_Gabriel",
  "imports" : [ "Hualde_Marisa", "Taboada_Ernesto" ]
}, {
  "name" : "Hualde_Marisa",
  "imports" : [ ]
}, {
  "name" : "Taboada_Ernesto",
  "imports" : [ ]
}, {
  "name" : "Oliveri_Guillermo_Rodolfo",
  "imports" : [ "Escudero_Hernan", "Kissag_Mouradian_Kissag", "Arias_Uriburu_Gabriela", "Ringler_Mario", "Masferrer_Kan_Elio" ]
}, {
  "name" : "Escudero_Hernan",
  "imports" : [ ]
}, {
  "name" : "Kissag_Mouradian_Kissag",
  "imports" : [ ]
}, {
  "name" : "Arias_Uriburu_Gabriela",
  "imports" : [ ]
}, {
  "name" : "Ringler_Mario",
  "imports" : [ ]
}, {
  "name" : "Masferrer_Kan_Elio",
  "imports" : [ ]
}, {
  "name" : "Kirchner_Nestor",
  "imports" : [ "Kennedy_Kerry", "De_Vido_Julio", "Matsuura_Koichiro", "Das_Neves_Mario", "Jaime_Ricardo", "Guiscardo_Marcelo" ]
}, {
  "name" : "Kennedy_Kerry",
  "imports" : [ ]
}, {
  "name" : "De_Vido_Julio",
  "imports" : [ ]
}, {
  "name" : "Matsuura_Koichiro",
  "imports" : [ ]
}, {
  "name" : "Das_Neves_Mario",
  "imports" : [ ]
}, {
  "name" : "Jaime_Ricardo",
  "imports" : [ ]
}, {
  "name" : "Guiscardo_Marcelo",
  "imports" : [ ]
}, {
  "name" : "Martinelli_Diego",
  "imports" : [ "Amenabar_Adrian", "Rodriguez_Jose_Luis", "Helueni_Carlos_A", "Rotondo_Gerardo", "Santangelo_Arturo" ]
}, {
  "name" : "Amenabar_Adrian",
  "imports" : [ ]
}, {
  "name" : "Rodriguez_Jose_Luis",
  "imports" : [ ]
}, {
  "name" : "Helueni_Carlos_A",
  "imports" : [ ]
}, {
  "name" : "Rotondo_Gerardo",
  "imports" : [ ]
}, {
  "name" : "Santangelo_Arturo",
  "imports" : [ ]
}, {
  "name" : "Siegenthaler_Juan",
  "imports" : [ "Ley_Victor", "Sanchez_Cristian" ]
}, {
  "name" : "Ley_Victor",
  "imports" : [ ]
}, {
  "name" : "Schiaffino_Eduardo_Augusto",
  "imports" : [ "Deluchi_Marta", "Lurbe_Mario", "Ottegui_-", "Comite_Aereo_Franco_Argentino_-" ]
}, {
  "name" : "Deluchi_Marta",
  "imports" : [ ]
}, {
  "name" : "Lurbe_Mario",
  "imports" : [ ]
}, {
  "name" : "Ottegui_-",
  "imports" : [ ]
}, {
  "name" : "Comite_Aereo_Franco_Argentino_-",
  "imports" : [ ]
}, {
  "name" : "Abrile_de_Vollmer_Maria_Ines",
  "imports" : [ "Avila_Jose_Luis", "Rossi_Anibal", "Martinitto_Osvaldo", "Ruiz_Santiago" ]
}, {
  "name" : "Avila_Jose_Luis",
  "imports" : [ ]
}, {
  "name" : "Rossi_Anibal",
  "imports" : [ ]
}, {
  "name" : "Martinitto_Osvaldo",
  "imports" : [ ]
}, {
  "name" : "Ruiz_Santiago",
  "imports" : [ ]
}, {
  "name" : "Hernandez_Daniel",
  "imports" : [ "Saavedra_Laura", "Lebedevski_Ricardo", "Torres_Leandro", "Dartiguelongue_Carlos", "Baldini_Gabriela", "Molla_Hector", "Bacalini_Gerardo", "Guglielmetti_Pedro", "Ranu_Romildo_Francisco", "Laterza_Blas" ]
}, {
  "name" : "Saavedra_Laura",
  "imports" : [ ]
}, {
  "name" : "Lebedevski_Ricardo",
  "imports" : [ ]
}, {
  "name" : "Torres_Leandro",
  "imports" : [ ]
}, {
  "name" : "Dartiguelongue_Carlos",
  "imports" : [ ]
}, {
  "name" : "Baldini_Gabriela",
  "imports" : [ ]
}, {
  "name" : "Molla_Hector",
  "imports" : [ ]
}, {
  "name" : "Bacalini_Gerardo",
  "imports" : [ ]
}, {
  "name" : "Guglielmetti_Pedro",
  "imports" : [ ]
}, {
  "name" : "Ranu_Romildo_Francisco",
  "imports" : [ ]
}, {
  "name" : "Laterza_Blas",
  "imports" : [ ]
}, {
  "name" : "Zanarini_Eugenio_Daniel",
  "imports" : [ "Corciglia_Joaquin", "Mendez_Karina" ]
}, {
  "name" : "Corciglia_Joaquin",
  "imports" : [ ]
}, {
  "name" : "Mendez_Karina",
  "imports" : [ ]
}, {
  "name" : "Pacios_Carlos_Alberto",
  "imports" : [ "Gianni_Carlos", "Toutoundjian_Beatriz", "Marconi_Marcos", "Dolmen_Gustavo_Adolfo", "Allera_Marcos", "Nicora_Juan", "Rojo_Mirta", "Tenaglia_Omar" ]
}, {
  "name" : "Gianni_Carlos",
  "imports" : [ ]
}, {
  "name" : "Toutoundjian_Beatriz",
  "imports" : [ ]
}, {
  "name" : "Marconi_Marcos",
  "imports" : [ ]
}, {
  "name" : "Dolmen_Gustavo_Adolfo",
  "imports" : [ ]
}, {
  "name" : "Allera_Marcos",
  "imports" : [ ]
}, {
  "name" : "Nicora_Juan",
  "imports" : [ ]
}, {
  "name" : "Rojo_Mirta",
  "imports" : [ ]
}, {
  "name" : "Tenaglia_Omar",
  "imports" : [ ]
}, {
  "name" : "Bontempo_Juan_Antonio",
  "imports" : [ "Mattarollo_Rosaura", "Hermida_Norberto", "Cesaroni_Claudia", "Saboularo_Alberto", "Loza_Vilma_Francisca", "Herrera_Hugo", "Laigre_-", "Feldman_Alejandra" ]
}, {
  "name" : "Mattarollo_Rosaura",
  "imports" : [ ]
}, {
  "name" : "Hermida_Norberto",
  "imports" : [ ]
}, {
  "name" : "Cesaroni_Claudia",
  "imports" : [ ]
}, {
  "name" : "Saboularo_Alberto",
  "imports" : [ ]
}, {
  "name" : "Loza_Vilma_Francisca",
  "imports" : [ ]
}, {
  "name" : "Herrera_Hugo",
  "imports" : [ ]
}, {
  "name" : "Laigre_-",
  "imports" : [ ]
}, {
  "name" : "Feldman_Alejandra",
  "imports" : [ ]
}, {
  "name" : "Couyoupetrou_Luis",
  "imports" : [ "Darrichon_Carlos", "Rodriguez_Alfredo", "Conte_Jorge", "Jurado_Jorge", "Ricciutti_Raul", "Simone_Horacio", "Romero_Ddamian", "Parmigiani_Guillermo", "De_Luca_Eduardo_Guillermo", "Bertone_Roxana", "Briozzo_Alberto", "Lupo_Joaquin" ]
}, {
  "name" : "Darrichon_Carlos",
  "imports" : [ ]
}, {
  "name" : "Rodriguez_Alfredo",
  "imports" : [ ]
}, {
  "name" : "Conte_Jorge",
  "imports" : [ ]
}, {
  "name" : "Jurado_Jorge",
  "imports" : [ ]
}, {
  "name" : "Ricciutti_Raul",
  "imports" : [ ]
}, {
  "name" : "Simone_Horacio",
  "imports" : [ ]
}, {
  "name" : "Romero_Ddamian",
  "imports" : [ ]
}, {
  "name" : "Parmigiani_Guillermo",
  "imports" : [ ]
}, {
  "name" : "De_Luca_Eduardo_Guillermo",
  "imports" : [ ]
}, {
  "name" : "Bertone_Roxana",
  "imports" : [ ]
}, {
  "name" : "Briozzo_Alberto",
  "imports" : [ ]
}, {
  "name" : "Lupo_Joaquin",
  "imports" : [ ]
}, {
  "name" : "Brennan_Roberto",
  "imports" : [ "Montestno_Franco", "Caldararo_Andrea", "Imazio_Sergio" ]
}, {
  "name" : "Montestno_Franco",
  "imports" : [ ]
}, {
  "name" : "Caldararo_Andrea",
  "imports" : [ ]
}, {
  "name" : "Imazio_Sergio",
  "imports" : [ ]
}, {
  "name" : "Granitto_Marcelo_Oscar",
  "imports" : [ "Kilinsky_Dov", "Ledesma_Nicolas" ]
}, {
  "name" : "Kilinsky_Dov",
  "imports" : [ ]
}, {
  "name" : "Ledesma_Nicolas",
  "imports" : [ ]
}, {
  "name" : "Granero_Jose_Ramon",
  "imports" : [ "Ricci_Juana", "Segovia_Juan", "Espinosa_Rodolfo", "Irigoyen-Coll_Cristina" ]
}, {
  "name" : "Ricci_Juana",
  "imports" : [ ]
}, {
  "name" : "Segovia_Juan",
  "imports" : [ ]
}, {
  "name" : "Espinosa_Rodolfo",
  "imports" : [ ]
}, {
  "name" : "Irigoyen-Coll_Cristina",
  "imports" : [ ]
}, {
  "name" : "Rosatti_Horacio_Daniel",
  "imports" : [ "Telerman_Jorge", "Romero_Juan_Carlos", "Grillo_Sergio", "De_Santos_Carlos", "Branda_Ricardo_Alberto", "Despouy_Leandro", "Petracchi_Enrique", "Kahul_Abraham", "Conte_Grand_Gerardo", "Rabinstein_Alberto", "Michael_Bess", "Calcagno_Eric", "Ducote_Nicolas" ]
}, {
  "name" : "Telerman_Jorge",
  "imports" : [ ]
}, {
  "name" : "Romero_Juan_Carlos",
  "imports" : [ ]
}, {
  "name" : "Grillo_Sergio",
  "imports" : [ ]
}, {
  "name" : "De_Santos_Carlos",
  "imports" : [ ]
}, {
  "name" : "Branda_Ricardo_Alberto",
  "imports" : [ ]
}, {
  "name" : "Despouy_Leandro",
  "imports" : [ ]
}, {
  "name" : "Petracchi_Enrique",
  "imports" : [ ]
}, {
  "name" : "Kahul_Abraham",
  "imports" : [ ]
}, {
  "name" : "Conte_Grand_Gerardo",
  "imports" : [ ]
}, {
  "name" : "Rabinstein_Alberto",
  "imports" : [ ]
}, {
  "name" : "Michael_Bess",
  "imports" : [ ]
}, {
  "name" : "Calcagno_Eric",
  "imports" : [ ]
}, {
  "name" : "Ducote_Nicolas",
  "imports" : [ ]
}, {
  "name" : "Sileoni_Alberto",
  "imports" : [ "Cafiero_Ana", "Parandekar_Suhas", "Ostrower_Ruben", "Rodriguez_Jorge", "Sabate_Felix", "Bouchoux_Horacio", "Feldman_Fabian", "Cartagenova_Veronica", "Macchia_Elvio", "Fernandez_Oscar", "Orlowski_de_Amadeo_Beatriz", "Perez_de_Bianchi_Stella", "Barros_Gabriel" ]
}, {
  "name" : "Cafiero_Ana",
  "imports" : [ ]
}, {
  "name" : "Parandekar_Suhas",
  "imports" : [ ]
}, {
  "name" : "Ostrower_Ruben",
  "imports" : [ ]
}, {
  "name" : "Rodriguez_Jorge",
  "imports" : [ ]
}, {
  "name" : "Sabate_Felix",
  "imports" : [ ]
}, {
  "name" : "Bouchoux_Horacio",
  "imports" : [ ]
}, {
  "name" : "Feldman_Fabian",
  "imports" : [ ]
}, {
  "name" : "Cartagenova_Veronica",
  "imports" : [ ]
}, {
  "name" : "Macchia_Elvio",
  "imports" : [ ]
}, {
  "name" : "Fernandez_Oscar",
  "imports" : [ ]
}, {
  "name" : "Orlowski_de_Amadeo_Beatriz",
  "imports" : [ ]
}, {
  "name" : "Perez_de_Bianchi_Stella",
  "imports" : [ ]
}, {
  "name" : "Barros_Gabriel",
  "imports" : [ ]
}, {
  "name" : "Torres_Ruben_Humberto",
  "imports" : [ "Ponce_Juan_Carlos", "Otero_Carlos_Arturo", "Scaro_Cesar", "Herman_Pablo", "Piccinini_Alberto", "Julio_Eduardo", "Lopez_Vladino_Marcela", "Torres_Alberto" ]
}, {
  "name" : "Ponce_Juan_Carlos",
  "imports" : [ ]
}, {
  "name" : "Otero_Carlos_Arturo",
  "imports" : [ ]
}, {
  "name" : "Scaro_Cesar",
  "imports" : [ ]
}, {
  "name" : "Herman_Pablo",
  "imports" : [ ]
}, {
  "name" : "Piccinini_Alberto",
  "imports" : [ ]
}, {
  "name" : "Julio_Eduardo",
  "imports" : [ ]
}, {
  "name" : "Lopez_Vladino_Marcela",
  "imports" : [ ]
}, {
  "name" : "Torres_Alberto",
  "imports" : [ ]
}, {
  "name" : "Pezoa_Juan_Carlos",
  "imports" : [ "Scaglione_Adolfo", "Gutelli_Antonio", "Garay_Juan" ]
}, {
  "name" : "Scaglione_Adolfo",
  "imports" : [ ]
}, {
  "name" : "Gutelli_Antonio",
  "imports" : [ ]
}, {
  "name" : "Garay_Juan",
  "imports" : [ ]
}, {
  "name" : "Rios_Gustavo",
  "imports" : [ "Barillaro_Guillermo_Victor", "Donecker_Nora", "Di_Benedetto_Claudio_Fernando", "Gofman_Maria_Cecilia", "Paz_Hilario_Cesar", "Fiocca_Santiago", "Ramirez_Alejandra_M", "Basilio_Guillermo_Augusto", "Cerezo_Claudia_Rita", "Roldan_Sergio_Isidoro", "Vales_Diego_Gerardo", "Paolo_Jose_Luis", "Imbrogno_Alejandro_Agustin" ]
}, {
  "name" : "Barillaro_Guillermo_Victor",
  "imports" : [ ]
}, {
  "name" : "Donecker_Nora",
  "imports" : [ ]
}, {
  "name" : "Di_Benedetto_Claudio_Fernando",
  "imports" : [ ]
}, {
  "name" : "Gofman_Maria_Cecilia",
  "imports" : [ ]
}, {
  "name" : "Paz_Hilario_Cesar",
  "imports" : [ ]
}, {
  "name" : "Fiocca_Santiago",
  "imports" : [ ]
}, {
  "name" : "Ramirez_Alejandra_M",
  "imports" : [ ]
}, {
  "name" : "Basilio_Guillermo_Augusto",
  "imports" : [ ]
}, {
  "name" : "Cerezo_Claudia_Rita",
  "imports" : [ ]
}, {
  "name" : "Roldan_Sergio_Isidoro",
  "imports" : [ ]
}, {
  "name" : "Vales_Diego_Gerardo",
  "imports" : [ ]
}, {
  "name" : "Paolo_Jose_Luis",
  "imports" : [ ]
}, {
  "name" : "Imbrogno_Alejandro_Agustin",
  "imports" : [ ]
}, {
  "name" : "Rial_Noemi",
  "imports" : [ "Maldonado_Carlos", "Ieraci_Julio", "Hidalgo_Jose_Maria", "Gonzalez_Bellini_Guido", "Izquierdo_Roberto", "Iribarne_Alba", "Lombardi_Daniel", "Iribarren_Nestor", "Vischi_Eduardo", "Castillo_Gerardo", "Bertolyotti_Delma", "Amichetti_Hector", "Mariani_Juan_Carlos", "Cholvis_Jorge", "Zanola_Juan_Jose", "Ruiz_Alvaro", "Palacios_Marco", "Marano_Enrique", "Cholvis_Jorge_Francisco", "Cardigonde_Hernan", "Renda_Pedro", "Kaire_Roberto" ]
}, {
  "name" : "Maldonado_Carlos",
  "imports" : [ ]
}, {
  "name" : "Ieraci_Julio",
  "imports" : [ ]
}, {
  "name" : "Hidalgo_Jose_Maria",
  "imports" : [ ]
}, {
  "name" : "Gonzalez_Bellini_Guido",
  "imports" : [ ]
}, {
  "name" : "Izquierdo_Roberto",
  "imports" : [ ]
}, {
  "name" : "Iribarne_Alba",
  "imports" : [ ]
}, {
  "name" : "Lombardi_Daniel",
  "imports" : [ ]
}, {
  "name" : "Iribarren_Nestor",
  "imports" : [ ]
}, {
  "name" : "Vischi_Eduardo",
  "imports" : [ ]
}, {
  "name" : "Castillo_Gerardo",
  "imports" : [ ]
}, {
  "name" : "Bertolyotti_Delma",
  "imports" : [ ]
}, {
  "name" : "Amichetti_Hector",
  "imports" : [ ]
}, {
  "name" : "Mariani_Juan_Carlos",
  "imports" : [ ]
}, {
  "name" : "Cholvis_Jorge",
  "imports" : [ ]
}, {
  "name" : "Zanola_Juan_Jose",
  "imports" : [ ]
}, {
  "name" : "Ruiz_Alvaro",
  "imports" : [ ]
}, {
  "name" : "Palacios_Marco",
  "imports" : [ ]
}, {
  "name" : "Marano_Enrique",
  "imports" : [ ]
}, {
  "name" : "Cholvis_Jorge_Francisco",
  "imports" : [ ]
}, {
  "name" : "Cardigonde_Hernan",
  "imports" : [ ]
}, {
  "name" : "Renda_Pedro",
  "imports" : [ ]
}, {
  "name" : "Kaire_Roberto",
  "imports" : [ ]
}, {
  "name" : "Spano_Francisco",
  "imports" : [ "Romero_Juan_Carlos" ]
}, {
  "name" : "Lico_Oscar",
  "imports" : [ "Fenoglio_Jorge", "Barbaro_Nestor_Omar", "Spano_Francisco", "Marcolini_Jorge" ]
}, {
  "name" : "Fenoglio_Jorge",
  "imports" : [ ]
}, {
  "name" : "Barbaro_Nestor_Omar",
  "imports" : [ ]
}, {
  "name" : "Marcolini_Jorge",
  "imports" : [ ]
}, {
  "name" : "Prina_Eduardo_Daniel",
  "imports" : [ "Benitez_Manuel_Cesar", "Ayub_Roberto" ]
}, {
  "name" : "Benitez_Manuel_Cesar",
  "imports" : [ ]
}, {
  "name" : "Ayub_Roberto",
  "imports" : [ ]
}, {
  "name" : "Vizzotti_Carlos_Alberto",
  "imports" : [ "Vizzotti_Carlos", "Pages_Jose_Antonio", "Deschutter_Enrique_Jorge" ]
}, {
  "name" : "Vizzotti_Carlos",
  "imports" : [ ]
}, {
  "name" : "Pages_Jose_Antonio",
  "imports" : [ ]
}, {
  "name" : "Deschutter_Enrique_Jorge",
  "imports" : [ ]
}, {
  "name" : "Donikian_Oscsar",
  "imports" : [ "Gomes_Dos_Santos_Julia_Leal", "Bruno_Agollia_Manfredo" ]
}, {
  "name" : "Gomes_Dos_Santos_Julia_Leal",
  "imports" : [ ]
}, {
  "name" : "Bruno_Agollia_Manfredo",
  "imports" : [ ]
}, {
  "name" : "Albistur_Alberto_Alejandro",
  "imports" : [ "Ezquiaga_Ricardo_J", "Combale_Jose", "Vinelli_Guillermo" ]
}, {
  "name" : "Ezquiaga_Ricardo_J",
  "imports" : [ ]
}, {
  "name" : "Combale_Jose",
  "imports" : [ ]
}, {
  "name" : "Vinelli_Guillermo",
  "imports" : [ ]
}, {
  "name" : "Pizarro_Roberto",
  "imports" : [ "Cajzdik_Irene" ]
}, {
  "name" : "Cajzdik_Irene",
  "imports" : [ ]
}, {
  "name" : "Moreno_Mario_Guillermo",
  "imports" : [ "Brotto_Carlos_Hector", "Rodriguez_German", "Pizarro_Gustavo", "Jurdanas_Claudio", "Sutil_Jorge" ]
}, {
  "name" : "Brotto_Carlos_Hector",
  "imports" : [ ]
}, {
  "name" : "Rodriguez_German",
  "imports" : [ ]
}, {
  "name" : "Pizarro_Gustavo",
  "imports" : [ ]
}, {
  "name" : "Jurdanas_Claudio",
  "imports" : [ ]
}, {
  "name" : "Sutil_Jorge",
  "imports" : [ ]
}, {
  "name" : "Villella_Marcos_Leonel",
  "imports" : [ "Lucero_Schmidt_Juan", "Roman_Fabian", "Ramos_Irma", "Singerman_Pablo" ]
}, {
  "name" : "Lucero_Schmidt_Juan",
  "imports" : [ ]
}, {
  "name" : "Roman_Fabian",
  "imports" : [ ]
}, {
  "name" : "Ramos_Irma",
  "imports" : [ ]
}, {
  "name" : "Singerman_Pablo",
  "imports" : [ ]
}, {
  "name" : "Granada_Rolando",
  "imports" : [ "Curtis_Jorge", "Ishida_Viviana" ]
}, {
  "name" : "Curtis_Jorge",
  "imports" : [ ]
}, {
  "name" : "Ishida_Viviana",
  "imports" : [ ]
}, {
  "name" : "Limeres_Manuel",
  "imports" : [ "Mazzia_Leonardo", "Bonafiglio_Osvaldo", "Aguilar_Veronica", "Marinaro_Bautista", "Beraza_Fernando", "Lopez_Juan_Carlos", "Maito_Miguel" ]
}, {
  "name" : "Mazzia_Leonardo",
  "imports" : [ ]
}, {
  "name" : "Bonafiglio_Osvaldo",
  "imports" : [ ]
}, {
  "name" : "Aguilar_Veronica",
  "imports" : [ ]
}, {
  "name" : "Marinaro_Bautista",
  "imports" : [ ]
}, {
  "name" : "Beraza_Fernando",
  "imports" : [ ]
}, {
  "name" : "Lopez_Juan_Carlos",
  "imports" : [ ]
}, {
  "name" : "Maito_Miguel",
  "imports" : [ ]
}, {
  "name" : "Kirschenbaum_Juan_Manuel",
  "imports" : [ "Zaccagnini_Jorge", "Rubio_Gonzalo", "Demasi_Daniel", "Valerio_Hector", "Sobek_Gabriel", "Perez_Marcelo" ]
}, {
  "name" : "Zaccagnini_Jorge",
  "imports" : [ ]
}, {
  "name" : "Rubio_Gonzalo",
  "imports" : [ ]
}, {
  "name" : "Demasi_Daniel",
  "imports" : [ ]
}, {
  "name" : "Valerio_Hector",
  "imports" : [ ]
}, {
  "name" : "Sobek_Gabriel",
  "imports" : [ ]
}, {
  "name" : "Perez_Marcelo",
  "imports" : [ ]
}, {
  "name" : "Poggi_Margarita",
  "imports" : [ "Sverdlick_Ingrid" ]
}, {
  "name" : "Sverdlick_Ingrid",
  "imports" : [ ]
}, {
  "name" : "Conte_Grand_Alfredo_Horacio",
  "imports" : [ "Balea_Reino_Manuel", "Ratner_Mario", "Aguero_Juliana", "Cigliutti_Cesar", "Veschi_Elido", "Retamar_Miguel_A" ]
}, {
  "name" : "Balea_Reino_Manuel",
  "imports" : [ ]
}, {
  "name" : "Ratner_Mario",
  "imports" : [ ]
}, {
  "name" : "Aguero_Juliana",
  "imports" : [ ]
}, {
  "name" : "Cigliutti_Cesar",
  "imports" : [ ]
}, {
  "name" : "Veschi_Elido",
  "imports" : [ ]
}, {
  "name" : "Retamar_Miguel_A",
  "imports" : [ ]
}, {
  "name" : "Calzoni_Jorge_Fabian",
  "imports" : [ "Tonkonoff_Jorge" ]
}, {
  "name" : "Tonkonoff_Jorge",
  "imports" : [ ]
}, {
  "name" : "Diez_Luis_Angel",
  "imports" : [ "Constanzo_Escobar_Pablo_Alejandro" ]
}, {
  "name" : "Constanzo_Escobar_Pablo_Alejandro",
  "imports" : [ ]
}, {
  "name" : "Gregori_Alejandro",
  "imports" : [ "Escalante_Jose_Maria" ]
}, {
  "name" : "Escalante_Jose_Maria",
  "imports" : [ ]
}, {
  "name" : "Herrero_Anzorena_Julio",
  "imports" : [ "Gazola_Elisabeth", "Morello_Rodolfo", "Baigorria_Francisco", "Ortega_Lopez_Antonio" ]
}, {
  "name" : "Gazola_Elisabeth",
  "imports" : [ ]
}, {
  "name" : "Morello_Rodolfo",
  "imports" : [ ]
}, {
  "name" : "Baigorria_Francisco",
  "imports" : [ ]
}, {
  "name" : "Ortega_Lopez_Antonio",
  "imports" : [ ]
}, {
  "name" : "Ciaravino_Norberto_Jose",
  "imports" : [ "Tomada_Carlos", "Hammar_Olga", "Diaz_Gustavo", "Suarez_Eduardo_Valentin", "Quiroga_Miguel", "Praino_Raul" ]
}, {
  "name" : "Tomada_Carlos",
  "imports" : [ ]
}, {
  "name" : "Hammar_Olga",
  "imports" : [ ]
}, {
  "name" : "Diaz_Gustavo",
  "imports" : [ ]
}, {
  "name" : "Suarez_Eduardo_Valentin",
  "imports" : [ ]
}, {
  "name" : "Quiroga_Miguel",
  "imports" : [ ]
}, {
  "name" : "Praino_Raul",
  "imports" : [ ]
}, {
  "name" : "Rosso_Graciela_Zulema",
  "imports" : [ "Liwski_Norberto", "Gorla_Marcela", "Hoff_Robert", "Fernandez_Rodolfo", "Frondizi_Marcelo", "Minguez_Miguel", "Diaz_Eduardo", "Toledano_Roberto_Emilio" ]
}, {
  "name" : "Liwski_Norberto",
  "imports" : [ ]
}, {
  "name" : "Gorla_Marcela",
  "imports" : [ ]
}, {
  "name" : "Hoff_Robert",
  "imports" : [ ]
}, {
  "name" : "Fernandez_Rodolfo",
  "imports" : [ ]
}, {
  "name" : "Frondizi_Marcelo",
  "imports" : [ ]
}, {
  "name" : "Minguez_Miguel",
  "imports" : [ ]
}, {
  "name" : "Diaz_Eduardo",
  "imports" : [ ]
}, {
  "name" : "Toledano_Roberto_Emilio",
  "imports" : [ ]
}, {
  "name" : "Baratta_Roberto",
  "imports" : [ "Dr_Malesani_A", "Smid_Juan_Carlos", "Rollano_Francisco", "Schmidt_Juan_Carlos", "Pescarmona_Enrique", "Saenz_Eduardo", "Guiscardo_Marcelo", "Llamazares_Juan" ]
}, {
  "name" : "Dr_Malesani_A",
  "imports" : [ ]
}, {
  "name" : "Smid_Juan_Carlos",
  "imports" : [ ]
}, {
  "name" : "Rollano_Francisco",
  "imports" : [ ]
}, {
  "name" : "Schmidt_Juan_Carlos",
  "imports" : [ ]
}, {
  "name" : "Pescarmona_Enrique",
  "imports" : [ ]
}, {
  "name" : "Saenz_Eduardo",
  "imports" : [ ]
}, {
  "name" : "Llamazares_Juan",
  "imports" : [ ]
}, {
  "name" : "Cedola_Ofelia_Mabel",
  "imports" : [ "Egea_Daniel", "Fernandez_Angeles", "Feldman_Gustavo_Esteban" ]
}, {
  "name" : "Egea_Daniel",
  "imports" : [ ]
}, {
  "name" : "Fernandez_Angeles",
  "imports" : [ ]
}, {
  "name" : "Feldman_Gustavo_Esteban",
  "imports" : [ ]
}, {
  "name" : "Gadano_Julian",
  "imports" : [ "Ramirez_Jorge", "Kosteki_Mara", "Nacinovich_Cecilia", "Cardozo_Fernando", "Ramirez_Victor", "Lezcano_Lucas", "La_Via_Monica", "Delgado_Gisella", "Miceli_Pablo", "Rodriguez_Eduardo", "Urcullo_Gaston", "Rojas_Rosana_Lorena", "Lazota_Luis", "Comino_Carlos_Angel", "Nykiel_Ana_Irene", "Soraire_Nestor_Carlos", "Vellido_Sandra" ]
}, {
  "name" : "Ramirez_Jorge",
  "imports" : [ ]
}, {
  "name" : "Kosteki_Mara",
  "imports" : [ ]
}, {
  "name" : "Nacinovich_Cecilia",
  "imports" : [ ]
}, {
  "name" : "Cardozo_Fernando",
  "imports" : [ ]
}, {
  "name" : "Ramirez_Victor",
  "imports" : [ ]
}, {
  "name" : "Lezcano_Lucas",
  "imports" : [ ]
}, {
  "name" : "La_Via_Monica",
  "imports" : [ ]
}, {
  "name" : "Delgado_Gisella",
  "imports" : [ ]
}, {
  "name" : "Miceli_Pablo",
  "imports" : [ ]
}, {
  "name" : "Rodriguez_Eduardo",
  "imports" : [ ]
}, {
  "name" : "Urcullo_Gaston",
  "imports" : [ ]
}, {
  "name" : "Rojas_Rosana_Lorena",
  "imports" : [ ]
}, {
  "name" : "Lazota_Luis",
  "imports" : [ ]
}, {
  "name" : "Comino_Carlos_Angel",
  "imports" : [ ]
}, {
  "name" : "Nykiel_Ana_Irene",
  "imports" : [ ]
}, {
  "name" : "Soraire_Nestor_Carlos",
  "imports" : [ ]
}, {
  "name" : "Vellido_Sandra",
  "imports" : [ ]
}, {
  "name" : "Vitobello_Julio_Fernando",
  "imports" : [ "Urdapilleta_Ines", "Coullier_Pablo", "Arguello_Jorge" ]
}, {
  "name" : "Urdapilleta_Ines",
  "imports" : [ ]
}, {
  "name" : "Coullier_Pablo",
  "imports" : [ ]
}, {
  "name" : "Arguello_Jorge",
  "imports" : [ ]
}, {
  "name" : "Periotti_Nelson",
  "imports" : [ "Trivino_Jose", "Icare_Alberto", "Vulijscher_Osvaldo", "Mongelo_Jose", "Molina_Juan_Carlos", "Palazzio_Victor", "Fernandez_Alfredo_Cesar", "Ordonez_Jorge", "Pensotti_Jorge_Angel" ]
}, {
  "name" : "Trivino_Jose",
  "imports" : [ ]
}, {
  "name" : "Icare_Alberto",
  "imports" : [ ]
}, {
  "name" : "Vulijscher_Osvaldo",
  "imports" : [ ]
}, {
  "name" : "Mongelo_Jose",
  "imports" : [ ]
}, {
  "name" : "Molina_Juan_Carlos",
  "imports" : [ ]
}, {
  "name" : "Palazzio_Victor",
  "imports" : [ ]
}, {
  "name" : "Fernandez_Alfredo_Cesar",
  "imports" : [ ]
}, {
  "name" : "Ordonez_Jorge",
  "imports" : [ ]
}, {
  "name" : "Pensotti_Jorge_Angel",
  "imports" : [ ]
}, {
  "name" : "Savino_Atilio",
  "imports" : [ "Ferreira_Anibal_Jorge", "Damonte_Guillermo", "Buzzurro_Ernesto_H", "Rass_Fernando_Luis", "Galan_Ricardo_Osvaldo" ]
}, {
  "name" : "Ferreira_Anibal_Jorge",
  "imports" : [ ]
}, {
  "name" : "Damonte_Guillermo",
  "imports" : [ ]
}, {
  "name" : "Buzzurro_Ernesto_H",
  "imports" : [ ]
}, {
  "name" : "Rass_Fernando_Luis",
  "imports" : [ ]
}, {
  "name" : "Galan_Ricardo_Osvaldo",
  "imports" : [ ]
}, {
  "name" : "Rodriguez_Maria_Jose",
  "imports" : [ "Ibanez_Lucio", "Davila_Clara_Rita", "Falbo_Maria_del_Carmen" ]
}, {
  "name" : "Ibanez_Lucio",
  "imports" : [ ]
}, {
  "name" : "Davila_Clara_Rita",
  "imports" : [ ]
}, {
  "name" : "Falbo_Maria_del_Carmen",
  "imports" : [ ]
}, {
  "name" : "Almandoz_Maria_Rosa",
  "imports" : [ "De_la_Arena_Gustavo", "Hans_Christiaan", "Lukez_Ana_Maria", "Gruber_Rebeca", "Sobrevila_Marcelo_Antonio" ]
}, {
  "name" : "De_la_Arena_Gustavo",
  "imports" : [ ]
}, {
  "name" : "Hans_Christiaan",
  "imports" : [ ]
}, {
  "name" : "Lukez_Ana_Maria",
  "imports" : [ ]
}, {
  "name" : "Gruber_Rebeca",
  "imports" : [ ]
}, {
  "name" : "Sobrevila_Marcelo_Antonio",
  "imports" : [ ]
}, {
  "name" : "Abriata_Jose_Pablo",
  "imports" : [ "Smith_Ian", "Jaque_Celso", "Gregui_Jose", "Granados_Alejandro_Santiago" ]
}, {
  "name" : "Smith_Ian",
  "imports" : [ ]
}, {
  "name" : "Jaque_Celso",
  "imports" : [ ]
}, {
  "name" : "Gregui_Jose",
  "imports" : [ ]
}, {
  "name" : "Granados_Alejandro_Santiago",
  "imports" : [ ]
}, {
  "name" : "Lapsenson_Jorge_Teodoro",
  "imports" : [ "Akbar_Abid_Javed", "Caracotche_Edgardo", "Gonzalez_Abella_Miguel_Angel", "Garre_Nilda", "Wagner_Tomas", "Castellan_Norberto", "Gomez_Jose_Alberto", "Khan_Rafiq_Ahmed", "Barturen_Carmelo_Angulo" ]
}, {
  "name" : "Akbar_Abid_Javed",
  "imports" : [ ]
}, {
  "name" : "Caracotche_Edgardo",
  "imports" : [ ]
}, {
  "name" : "Gonzalez_Abella_Miguel_Angel",
  "imports" : [ ]
}, {
  "name" : "Garre_Nilda",
  "imports" : [ ]
}, {
  "name" : "Wagner_Tomas",
  "imports" : [ ]
}, {
  "name" : "Castellan_Norberto",
  "imports" : [ ]
}, {
  "name" : "Gomez_Jose_Alberto",
  "imports" : [ ]
}, {
  "name" : "Khan_Rafiq_Ahmed",
  "imports" : [ ]
}, {
  "name" : "Barturen_Carmelo_Angulo",
  "imports" : [ ]
}, {
  "name" : "Kulikowski_Carlos_Esteban",
  "imports" : [ "Frederic_Ruiz-Ramon_Ramon", "Otero_Eduardo", "Calleja_Roberto_Ismael" ]
}, {
  "name" : "Frederic_Ruiz-Ramon_Ramon",
  "imports" : [ ]
}, {
  "name" : "Otero_Eduardo",
  "imports" : [ ]
}, {
  "name" : "Calleja_Roberto_Ismael",
  "imports" : [ ]
}, {
  "name" : "Cingolani_Ignacio_Martin",
  "imports" : [ "Franco_Hetor", "Martinez_Heber", "Verdaguer_Hernan", "Gambarini_Jorge", "Gattas_Orlando", "Vignola_Martin", "Jantus_Patricia", "Cozzi_Angel", "Zuccoli_Juan_Antonio" ]
}, {
  "name" : "Franco_Hetor",
  "imports" : [ ]
}, {
  "name" : "Martinez_Heber",
  "imports" : [ ]
}, {
  "name" : "Verdaguer_Hernan",
  "imports" : [ ]
}, {
  "name" : "Gambarini_Jorge",
  "imports" : [ ]
}, {
  "name" : "Gattas_Orlando",
  "imports" : [ ]
}, {
  "name" : "Vignola_Martin",
  "imports" : [ ]
}, {
  "name" : "Jantus_Patricia",
  "imports" : [ ]
}, {
  "name" : "Cozzi_Angel",
  "imports" : [ ]
}, {
  "name" : "Zuccoli_Juan_Antonio",
  "imports" : [ ]
}, {
  "name" : "Leibovich_Andres_Joaquin",
  "imports" : [ "Lago_Adriana_Nora" ]
}, {
  "name" : "Lago_Adriana_Nora",
  "imports" : [ ]
}, {
  "name" : "Vilas_Graciela_Marta",
  "imports" : [ "Vera_Victor" ]
}, {
  "name" : "Vera_Victor",
  "imports" : [ ]
}, {
  "name" : "Bibiloni_Homero_Maximo",
  "imports" : [ "Sanguinetti_Juan_Carlos", "Bondanza_Maria_Esther", "Cabeza_Edgardo" ]
}, {
  "name" : "Sanguinetti_Juan_Carlos",
  "imports" : [ ]
}, {
  "name" : "Bondanza_Maria_Esther",
  "imports" : [ ]
}, {
  "name" : "Cabeza_Edgardo",
  "imports" : [ ]
}, {
  "name" : "Martinez_Leone_Ricardo",
  "imports" : [ "Rodriguez_Messina_Pablo", "Bulacio_Claudio", "Pujals_Fernando", "Harmatiuk_Oreste", "Neme_Alejandro" ]
}, {
  "name" : "Rodriguez_Messina_Pablo",
  "imports" : [ ]
}, {
  "name" : "Bulacio_Claudio",
  "imports" : [ ]
}, {
  "name" : "Pujals_Fernando",
  "imports" : [ ]
}, {
  "name" : "Harmatiuk_Oreste",
  "imports" : [ ]
}, {
  "name" : "Neme_Alejandro",
  "imports" : [ ]
}, {
  "name" : "Palacio_Ricardo",
  "imports" : [ "Lopez_Jose", "Martinez_Monica", "Canda_Alcira", "Zurlo_Marcelo", "Cherquis_Bialo_Ernesto", "Fergola_Sandro", "Knesevich_Juan_Daniel" ]
}, {
  "name" : "Lopez_Jose",
  "imports" : [ ]
}, {
  "name" : "Martinez_Monica",
  "imports" : [ ]
}, {
  "name" : "Canda_Alcira",
  "imports" : [ ]
}, {
  "name" : "Zurlo_Marcelo",
  "imports" : [ ]
}, {
  "name" : "Cherquis_Bialo_Ernesto",
  "imports" : [ ]
}, {
  "name" : "Fergola_Sandro",
  "imports" : [ ]
}, {
  "name" : "Knesevich_Juan_Daniel",
  "imports" : [ ]
}, {
  "name" : "Jaime_Raul_Ricardo",
  "imports" : [ "Morales_Luis", "Pedraza_Jose", "Acuna_Joaquin", "Calderon_Marcelo", "Otero_Nestor", "Diez_Luis_Angel", "Romero_Benjamin_Gabriel", "D<U+00A8>Angelo_A", "Canegallo_Norberto", "Crespo_Alberto", "Vazquez_Manuel", "Pino_Carlos", "Cirigliano_Claudio", "Ramirez_Ernesto", "Cimo_Hector" ]
}, {
  "name" : "Morales_Luis",
  "imports" : [ ]
}, {
  "name" : "Pedraza_Jose",
  "imports" : [ ]
}, {
  "name" : "Acuna_Joaquin",
  "imports" : [ ]
}, {
  "name" : "Calderon_Marcelo",
  "imports" : [ ]
}, {
  "name" : "Otero_Nestor",
  "imports" : [ ]
}, {
  "name" : "Romero_Benjamin_Gabriel",
  "imports" : [ ]
}, {
  "name" : "D<U+00A8>Angelo_A",
  "imports" : [ ]
}, {
  "name" : "Canegallo_Norberto",
  "imports" : [ ]
}, {
  "name" : "Crespo_Alberto",
  "imports" : [ ]
}, {
  "name" : "Vazquez_Manuel",
  "imports" : [ ]
}, {
  "name" : "Pino_Carlos",
  "imports" : [ ]
}, {
  "name" : "Cirigliano_Claudio",
  "imports" : [ ]
}, {
  "name" : "Ramirez_Ernesto",
  "imports" : [ ]
}, {
  "name" : "Cimo_Hector",
  "imports" : [ ]
}, {
  "name" : "Auge_Osvaldo",
  "imports" : [ "Rossi_Felipe", "Castro_Alfonso_Eduardo" ]
}, {
  "name" : "Rossi_Felipe",
  "imports" : [ ]
}, {
  "name" : "Castro_Alfonso_Eduardo",
  "imports" : [ ]
}, {
  "name" : "Del_Bono_Tulio_Abel",
  "imports" : [ "Gaggioli_Nestor", "Cafiero_Ana", "Garcia_Augusto", "Neffa_Julio", "Ceccatto_Alejandro", "Rosales_Blanca", "Caivano_Garcia_Mario", "Tiramonti_Guillermina", "Puig_de_Stubrin_Lilia", "Savino_Atilio", "Perez_Lindo_Augusto", "Posse_Daniel_Oscar", "Marengo_Segundo", "Cantarelli_Luis_Maria", "Torres_Hector_Roberto", "Di_Pietro_Luis" ]
}, {
  "name" : "Gaggioli_Nestor",
  "imports" : [ ]
}, {
  "name" : "Garcia_Augusto",
  "imports" : [ ]
}, {
  "name" : "Neffa_Julio",
  "imports" : [ ]
}, {
  "name" : "Ceccatto_Alejandro",
  "imports" : [ ]
}, {
  "name" : "Rosales_Blanca",
  "imports" : [ ]
}, {
  "name" : "Caivano_Garcia_Mario",
  "imports" : [ ]
}, {
  "name" : "Tiramonti_Guillermina",
  "imports" : [ ]
}, {
  "name" : "Puig_de_Stubrin_Lilia",
  "imports" : [ ]
}, {
  "name" : "Perez_Lindo_Augusto",
  "imports" : [ ]
}, {
  "name" : "Posse_Daniel_Oscar",
  "imports" : [ ]
}, {
  "name" : "Marengo_Segundo",
  "imports" : [ ]
}, {
  "name" : "Cantarelli_Luis_Maria",
  "imports" : [ ]
}, {
  "name" : "Torres_Hector_Roberto",
  "imports" : [ ]
}, {
  "name" : "Di_Pietro_Luis",
  "imports" : [ ]
}, {
  "name" : "Guerrero_Miguel_Angel",
  "imports" : [ "Fillol_Casas_Jorge" ]
}, {
  "name" : "Fillol_Casas_Jorge",
  "imports" : [ ]
}, {
  "name" : "Bortolozzi_Edgardo_Atilio",
  "imports" : [ "Mel_Agustin" ]
}, {
  "name" : "Mel_Agustin",
  "imports" : [ ]
}, {
  "name" : "Ivancich_Norberto",
  "imports" : [ "Spairani_Hugo" ]
}, {
  "name" : "Spairani_Hugo",
  "imports" : [ ]
}, {
  "name" : "Albistur_Enrique_Raul",
  "imports" : [ "Feito_Oscar", "Mignona_Eduardo", "Cornide_Osvaldo", "Gaitia_Miguel_Angel", "Rojas_Diego", "Vaca_Narvaja_Patricia", "Federico_Leopoldo", "Rotemberg_Carlos", "Bauer_Tristan", "Lopez_Matheu_Pedro", "Valle_Hector", "Berghmans_German", "Palacio_Ricardo", "Lazzaro_Luis", "Aharonian_Aram" ]
}, {
  "name" : "Feito_Oscar",
  "imports" : [ ]
}, {
  "name" : "Mignona_Eduardo",
  "imports" : [ ]
}, {
  "name" : "Cornide_Osvaldo",
  "imports" : [ ]
}, {
  "name" : "Gaitia_Miguel_Angel",
  "imports" : [ ]
}, {
  "name" : "Rojas_Diego",
  "imports" : [ ]
}, {
  "name" : "Vaca_Narvaja_Patricia",
  "imports" : [ ]
}, {
  "name" : "Federico_Leopoldo",
  "imports" : [ ]
}, {
  "name" : "Rotemberg_Carlos",
  "imports" : [ ]
}, {
  "name" : "Bauer_Tristan",
  "imports" : [ ]
}, {
  "name" : "Lopez_Matheu_Pedro",
  "imports" : [ ]
}, {
  "name" : "Valle_Hector",
  "imports" : [ ]
}, {
  "name" : "Berghmans_German",
  "imports" : [ ]
}, {
  "name" : "Lazzaro_Luis",
  "imports" : [ ]
}, {
  "name" : "Aharonian_Aram",
  "imports" : [ ]
}, {
  "name" : "Garreta_Jaime",
  "imports" : [ "Wesner_Donald", "Fernandez_Julio", "Bossa_Mauricio", "Hang_Julio", "Serrat_Francisco_R", "Vieras_Nora", "Matiak_Carlos", "Aguilera_Eduardo" ]
}, {
  "name" : "Wesner_Donald",
  "imports" : [ ]
}, {
  "name" : "Fernandez_Julio",
  "imports" : [ ]
}, {
  "name" : "Bossa_Mauricio",
  "imports" : [ ]
}, {
  "name" : "Hang_Julio",
  "imports" : [ ]
}, {
  "name" : "Serrat_Francisco_R",
  "imports" : [ ]
}, {
  "name" : "Vieras_Nora",
  "imports" : [ ]
}, {
  "name" : "Matiak_Carlos",
  "imports" : [ ]
}, {
  "name" : "Aguilera_Eduardo",
  "imports" : [ ]
}, {
  "name" : "Arq_Salas_Lisandro",
  "imports" : [ "Alvarez_Jorge", "Santi_Esteban_Diego", "Cassina_Juan_Carlos", "Aadgaard_Anibal", "Gomez_Javier_F" ]
}, {
  "name" : "Alvarez_Jorge",
  "imports" : [ ]
}, {
  "name" : "Santi_Esteban_Diego",
  "imports" : [ ]
}, {
  "name" : "Cassina_Juan_Carlos",
  "imports" : [ ]
}, {
  "name" : "Aadgaard_Anibal",
  "imports" : [ ]
}, {
  "name" : "Gomez_Javier_F",
  "imports" : [ ]
}, {
  "name" : "Zaghini_Marta_Elsa",
  "imports" : [ "Machuca_Jorge" ]
}, {
  "name" : "Machuca_Jorge",
  "imports" : [ ]
}, {
  "name" : "Ramirez_Raul",
  "imports" : [ "Ferrari_Luis_Maria" ]
}, {
  "name" : "Ferrari_Luis_Maria",
  "imports" : [ ]
}, {
  "name" : "Segui_Luz",
  "imports" : [ "Monroy_Augusto", "Urdapilleta_Ines", "Rodriguez_Maria" ]
}, {
  "name" : "Monroy_Augusto",
  "imports" : [ ]
}, {
  "name" : "Rodriguez_Maria",
  "imports" : [ ]
}, {
  "name" : "Martin_Carlos_A",
  "imports" : [ "Crosetto_Carlos_Oscar" ]
}, {
  "name" : "Crosetto_Carlos_Oscar",
  "imports" : [ ]
}, {
  "name" : "Sevilla_Guillermo_Alberto",
  "imports" : [ "Sem_Horaldo" ]
}, {
  "name" : "Sem_Horaldo",
  "imports" : [ ]
}, {
  "name" : "Mariotto_Juan_G",
  "imports" : [ "Binstok_Eduardo", "Lavieri_Omar", "Rossi_Elio", "Gonzalez_Miguel_Angel", "Barral_Patricia", "Rivero_Julio", "Chames_Marcelo", "Alem_Lorena", "Moncalvillo_Adelina", "Flematti_Cecilio", "Souto_Gustavo", "Hapanowicz_Jorge", "Carlino_Alfredo", "Cherquis_Vialo_Ernesto", "Peloso_Rogelio", "Garcia_Luis", "Suppli_Edgardo", "Miro_Rodrigo", "Pinto_Mario", "Boveda_Fernando", "Egiman_Julio", "Perie_Hugo", "Dominguez_Loly", "Nacer_Jorge", "Nazar_Marcelo", "Di_Salvo_Virginia", "Tedeschi_Melisa", "Gaita_Miguel", "Pugliese_Juan_Carlos", "Fiotti_Gabriela", "Juarez_Andres", "Facultad_de_Periodismo_de_la_Plata_Roxana", "Gambaccini_Ana", "Rojas_Diego", "Alvarez_Eliseo", "Gimenez_Luis", "Gonzalez_Juan_Manuel", "Cantarinos_Nestor", "Morel_Claudio", "Amodio_Adrian", "Moratto_Ricardo", "Dorio_Julieta", "Mazzitelli_Luis", "Peluso_Ana_Maria", "Aragon_Santiago", "Vainstub_Gustavo", "Vera_Daniel", "Varela_Roca_Horacio", "Kaunitz_Ignacaio", "Lupo_Tom", "Canelas_Ruben", "Calmus_Leopoldo", "Balcedo_Miriam", "Moro_Jose", "Cunto_Adriana", "Massatti_Marcelo", "Cyngiel_Elena", "Ventos_Hugo", "Tancredi_Patricia", "Sivit_Jorge", "Gomez_Oscar", "Palacio_Ricardo", "Rossi_Carlos", "Soria_Jorge_Dioniisio", "Iribarne_Ines", "Omill_Carlos" ]
}, {
  "name" : "Binstok_Eduardo",
  "imports" : [ ]
}, {
  "name" : "Lavieri_Omar",
  "imports" : [ ]
}, {
  "name" : "Rossi_Elio",
  "imports" : [ ]
}, {
  "name" : "Gonzalez_Miguel_Angel",
  "imports" : [ ]
}, {
  "name" : "Barral_Patricia",
  "imports" : [ ]
}, {
  "name" : "Rivero_Julio",
  "imports" : [ ]
}, {
  "name" : "Chames_Marcelo",
  "imports" : [ ]
}, {
  "name" : "Alem_Lorena",
  "imports" : [ ]
}, {
  "name" : "Flematti_Cecilio",
  "imports" : [ ]
}, {
  "name" : "Souto_Gustavo",
  "imports" : [ ]
}, {
  "name" : "Hapanowicz_Jorge",
  "imports" : [ ]
}, {
  "name" : "Carlino_Alfredo",
  "imports" : [ ]
}, {
  "name" : "Cherquis_Vialo_Ernesto",
  "imports" : [ ]
}, {
  "name" : "Peloso_Rogelio",
  "imports" : [ ]
}, {
  "name" : "Garcia_Luis",
  "imports" : [ ]
}, {
  "name" : "Suppli_Edgardo",
  "imports" : [ ]
}, {
  "name" : "Pinto_Mario",
  "imports" : [ ]
}, {
  "name" : "Boveda_Fernando",
  "imports" : [ ]
}, {
  "name" : "Egiman_Julio",
  "imports" : [ ]
}, {
  "name" : "Perie_Hugo",
  "imports" : [ ]
}, {
  "name" : "Dominguez_Loly",
  "imports" : [ ]
}, {
  "name" : "Nacer_Jorge",
  "imports" : [ ]
}, {
  "name" : "Nazar_Marcelo",
  "imports" : [ ]
}, {
  "name" : "Di_Salvo_Virginia",
  "imports" : [ ]
}, {
  "name" : "Tedeschi_Melisa",
  "imports" : [ ]
}, {
  "name" : "Gaita_Miguel",
  "imports" : [ ]
}, {
  "name" : "Pugliese_Juan_Carlos",
  "imports" : [ ]
}, {
  "name" : "Fiotti_Gabriela",
  "imports" : [ ]
}, {
  "name" : "Juarez_Andres",
  "imports" : [ ]
}, {
  "name" : "Facultad_de_Periodismo_de_la_Plata_Roxana",
  "imports" : [ ]
}, {
  "name" : "Gambaccini_Ana",
  "imports" : [ ]
}, {
  "name" : "Alvarez_Eliseo",
  "imports" : [ ]
}, {
  "name" : "Gimenez_Luis",
  "imports" : [ ]
}, {
  "name" : "Gonzalez_Juan_Manuel",
  "imports" : [ ]
}, {
  "name" : "Cantarinos_Nestor",
  "imports" : [ ]
}, {
  "name" : "Morel_Claudio",
  "imports" : [ ]
}, {
  "name" : "Amodio_Adrian",
  "imports" : [ ]
}, {
  "name" : "Moratto_Ricardo",
  "imports" : [ ]
}, {
  "name" : "Dorio_Julieta",
  "imports" : [ ]
}, {
  "name" : "Mazzitelli_Luis",
  "imports" : [ ]
}, {
  "name" : "Peluso_Ana_Maria",
  "imports" : [ ]
}, {
  "name" : "Aragon_Santiago",
  "imports" : [ ]
}, {
  "name" : "Vainstub_Gustavo",
  "imports" : [ ]
}, {
  "name" : "Vera_Daniel",
  "imports" : [ ]
}, {
  "name" : "Varela_Roca_Horacio",
  "imports" : [ ]
}, {
  "name" : "Kaunitz_Ignacaio",
  "imports" : [ ]
}, {
  "name" : "Canelas_Ruben",
  "imports" : [ ]
}, {
  "name" : "Calmus_Leopoldo",
  "imports" : [ ]
}, {
  "name" : "Balcedo_Miriam",
  "imports" : [ ]
}, {
  "name" : "Moro_Jose",
  "imports" : [ ]
}, {
  "name" : "Cunto_Adriana",
  "imports" : [ ]
}, {
  "name" : "Massatti_Marcelo",
  "imports" : [ ]
}, {
  "name" : "Cyngiel_Elena",
  "imports" : [ ]
}, {
  "name" : "Ventos_Hugo",
  "imports" : [ ]
}, {
  "name" : "Tancredi_Patricia",
  "imports" : [ ]
}, {
  "name" : "Sivit_Jorge",
  "imports" : [ ]
}, {
  "name" : "Gomez_Oscar",
  "imports" : [ ]
}, {
  "name" : "Rossi_Carlos",
  "imports" : [ ]
}, {
  "name" : "Soria_Jorge_Dioniisio",
  "imports" : [ ]
}, {
  "name" : "Iribarne_Ines",
  "imports" : [ ]
}, {
  "name" : "Omill_Carlos",
  "imports" : [ ]
}, {
  "name" : "Contissa_Nestor",
  "imports" : [ "Marini_Anselmo", "Cajzdik_Irene", "Kleinman_Hernan", "Camara_Juan" ]
}, {
  "name" : "Marini_Anselmo",
  "imports" : [ ]
}, {
  "name" : "Kleinman_Hernan",
  "imports" : [ ]
}, {
  "name" : "Camara_Juan",
  "imports" : [ ]
}, {
  "name" : "Slokar_Alejandro_Walter",
  "imports" : [ "Fuks_Gabriel_Marcelo", "Slokar_Alejandro", "Vassel_Pablo" ]
}, {
  "name" : "Fuks_Gabriel_Marcelo",
  "imports" : [ ]
}, {
  "name" : "Slokar_Alejandro",
  "imports" : [ ]
}, {
  "name" : "Vassel_Pablo",
  "imports" : [ ]
}, {
  "name" : "Verruno_Camilo",
  "imports" : [ "Ferrer_Claudio", "Rial_Roberto_Oscar", "Grana_Dante", "Rubinstein_Liliana" ]
}, {
  "name" : "Ferrer_Claudio",
  "imports" : [ ]
}, {
  "name" : "Rial_Roberto_Oscar",
  "imports" : [ ]
}, {
  "name" : "Grana_Dante",
  "imports" : [ ]
}, {
  "name" : "Rubinstein_Liliana",
  "imports" : [ ]
}, {
  "name" : "Bontempo_Luis_Alberto_Rafael",
  "imports" : [ "Lopez_Horacio_Luis", "Mosca_Sabrina", "Ulloa_Nestor_Alberto", "Bodlovic_Jose_Ramon", "Forster_Samuel", "Perotti_Omar_Angel", "Franetovich_Ariel", "Quiros_Julio", "Zarabozo_Felix_Luis", "Terranova_Juan_Cayetano", "Diaz_Mirta", "Corbacho_Eduardo", "Romero_Fernando_Adrian", "Selzer_Subsecretario_de_Vivienda_del_Gob_de_la_Ci_Ernesto", "Alvarez_Sergio", "Serantes_Eduardo" ]
}, {
  "name" : "Lopez_Horacio_Luis",
  "imports" : [ ]
}, {
  "name" : "Mosca_Sabrina",
  "imports" : [ ]
}, {
  "name" : "Ulloa_Nestor_Alberto",
  "imports" : [ ]
}, {
  "name" : "Bodlovic_Jose_Ramon",
  "imports" : [ ]
}, {
  "name" : "Forster_Samuel",
  "imports" : [ ]
}, {
  "name" : "Perotti_Omar_Angel",
  "imports" : [ ]
}, {
  "name" : "Franetovich_Ariel",
  "imports" : [ ]
}, {
  "name" : "Quiros_Julio",
  "imports" : [ ]
}, {
  "name" : "Zarabozo_Felix_Luis",
  "imports" : [ ]
}, {
  "name" : "Terranova_Juan_Cayetano",
  "imports" : [ ]
}, {
  "name" : "Diaz_Mirta",
  "imports" : [ ]
}, {
  "name" : "Corbacho_Eduardo",
  "imports" : [ ]
}, {
  "name" : "Romero_Fernando_Adrian",
  "imports" : [ ]
}, {
  "name" : "Selzer_Subsecretario_de_Vivienda_del_Gob_de_la_Ci_Ernesto",
  "imports" : [ ]
}, {
  "name" : "Alvarez_Sergio",
  "imports" : [ ]
}, {
  "name" : "Serantes_Eduardo",
  "imports" : [ ]
}, {
  "name" : "Suarez_Fernando",
  "imports" : [ "Gomez_Fabio", "De_Grandis_Carlos_Alberto", "Montana_Julio_Tito", "Arias_Uriburu_Gabriela", "Alvarez_de_Olivera_Baldomero", "Amaya_Domingo", "Calvo_Cristina", "Granados_Alejandro_Santiago", "Ivoskus_Ricardo", "Simoncini_Raul", "Varas_Alberto_Jaime", "De_Vido_Hugo_Eduardo", "Slezak_Enrique", "Bo_Eduardo", "Garcia_Juan_M", "Silber_Faden_Daniel", "Rosenfeld_Leon_Carlos", "Charriere_Margarita" ]
}, {
  "name" : "Gomez_Fabio",
  "imports" : [ ]
}, {
  "name" : "De_Grandis_Carlos_Alberto",
  "imports" : [ ]
}, {
  "name" : "Montana_Julio_Tito",
  "imports" : [ ]
}, {
  "name" : "Alvarez_de_Olivera_Baldomero",
  "imports" : [ ]
}, {
  "name" : "Amaya_Domingo",
  "imports" : [ ]
}, {
  "name" : "Calvo_Cristina",
  "imports" : [ ]
}, {
  "name" : "Ivoskus_Ricardo",
  "imports" : [ ]
}, {
  "name" : "Simoncini_Raul",
  "imports" : [ ]
}, {
  "name" : "Varas_Alberto_Jaime",
  "imports" : [ ]
}, {
  "name" : "De_Vido_Hugo_Eduardo",
  "imports" : [ ]
}, {
  "name" : "Slezak_Enrique",
  "imports" : [ ]
}, {
  "name" : "Bo_Eduardo",
  "imports" : [ ]
}, {
  "name" : "Garcia_Juan_M",
  "imports" : [ ]
}, {
  "name" : "Silber_Faden_Daniel",
  "imports" : [ ]
}, {
  "name" : "Rosenfeld_Leon_Carlos",
  "imports" : [ ]
}, {
  "name" : "Charriere_Margarita",
  "imports" : [ ]
}, {
  "name" : "Gonzalez_Garcia_Gines",
  "imports" : [ "Dumont_Alberto", "Bost_Eric", "Wilkens_Madeleine", "Aizcorbe_Ricardo", "Pages_Jose_Antonio", "Zuccaro_Humberto", "Clement_Manuel", "Oliveira_Daniel", "Falu_Ana", "Balliarda_Luis", "Rivera_Pizzarro_Jorge", "Calo_Antonio", "Videla_Gilberto" ]
}, {
  "name" : "Dumont_Alberto",
  "imports" : [ ]
}, {
  "name" : "Bost_Eric",
  "imports" : [ ]
}, {
  "name" : "Wilkens_Madeleine",
  "imports" : [ ]
}, {
  "name" : "Aizcorbe_Ricardo",
  "imports" : [ ]
}, {
  "name" : "Zuccaro_Humberto",
  "imports" : [ ]
}, {
  "name" : "Clement_Manuel",
  "imports" : [ ]
}, {
  "name" : "Oliveira_Daniel",
  "imports" : [ ]
}, {
  "name" : "Falu_Ana",
  "imports" : [ ]
}, {
  "name" : "Balliarda_Luis",
  "imports" : [ ]
}, {
  "name" : "Rivera_Pizzarro_Jorge",
  "imports" : [ ]
}, {
  "name" : "Calo_Antonio",
  "imports" : [ ]
}, {
  "name" : "Videla_Gilberto",
  "imports" : [ ]
}, {
  "name" : "Kiener_Marcelo_Baldomir",
  "imports" : [ "Pujals_Fernando", "Genta_Guillermo" ]
}, {
  "name" : "Genta_Guillermo",
  "imports" : [ ]
}, {
  "name" : "Lopez_Jose_Francisco",
  "imports" : [ "Diez_Alvarez_Osvaldo", "Camara_Juan", "Navarro_Jose", "Browser_de_Koning_Luis", "Massacesi_Aladino_Antonio_Luciano" ]
}, {
  "name" : "Diez_Alvarez_Osvaldo",
  "imports" : [ ]
}, {
  "name" : "Navarro_Jose",
  "imports" : [ ]
}, {
  "name" : "Browser_de_Koning_Luis",
  "imports" : [ ]
}, {
  "name" : "Massacesi_Aladino_Antonio_Luciano",
  "imports" : [ ]
}, {
  "name" : "Samek_Alejandro",
  "imports" : [ "Lopez_Fabian", "Aguero_Sandro", "Gociol_Judith", "Gonzalez_Poisson_Haydee" ]
}, {
  "name" : "Lopez_Fabian",
  "imports" : [ ]
}, {
  "name" : "Aguero_Sandro",
  "imports" : [ ]
}, {
  "name" : "Gociol_Judith",
  "imports" : [ ]
}, {
  "name" : "Gonzalez_Poisson_Haydee",
  "imports" : [ ]
}, {
  "name" : "Nicoletti_Victor_Rene",
  "imports" : [ "Caballero_Osvaldo" ]
}, {
  "name" : "Caballero_Osvaldo",
  "imports" : [ ]
}, {
  "name" : "Bechini_Leonardo",
  "imports" : [ "Portal_Lucia", "Peluffo_Mariano", "Reech_Reina", "Badia_Juan_Alberto", "Echave_Rolando", "Lafrati_Patricia", "Ferrada_Paula", "Zurlo_Miguel_Angel", "Bal_Julieta", "Santonoli_Ramiro" ]
}, {
  "name" : "Portal_Lucia",
  "imports" : [ ]
}, {
  "name" : "Peluffo_Mariano",
  "imports" : [ ]
}, {
  "name" : "Reech_Reina",
  "imports" : [ ]
}, {
  "name" : "Badia_Juan_Alberto",
  "imports" : [ ]
}, {
  "name" : "Echave_Rolando",
  "imports" : [ ]
}, {
  "name" : "Lafrati_Patricia",
  "imports" : [ ]
}, {
  "name" : "Ferrada_Paula",
  "imports" : [ ]
}, {
  "name" : "Zurlo_Miguel_Angel",
  "imports" : [ ]
}, {
  "name" : "Bal_Julieta",
  "imports" : [ ]
}, {
  "name" : "Santonoli_Ramiro",
  "imports" : [ ]
}, {
  "name" : "Oyhanarte_Marta",
  "imports" : [ "Lanza_Lucas", "Modesto_Zapata_Ruben", "Leoni_Claudio", "Koshoupetra_Jorge", "Mally_Rene" ]
}, {
  "name" : "Lanza_Lucas",
  "imports" : [ ]
}, {
  "name" : "Modesto_Zapata_Ruben",
  "imports" : [ ]
}, {
  "name" : "Leoni_Claudio",
  "imports" : [ ]
}, {
  "name" : "Koshoupetra_Jorge",
  "imports" : [ ]
}, {
  "name" : "Mally_Rene",
  "imports" : [ ]
}, {
  "name" : "Orefice_Horacio_A",
  "imports" : [ "Laplace_Ana", "Sain_Marcelo", "Rodriguez_Ricardo", "Borgonovo_Esteban", "Asensio_Carlos" ]
}, {
  "name" : "Laplace_Ana",
  "imports" : [ ]
}, {
  "name" : "Sain_Marcelo",
  "imports" : [ ]
}, {
  "name" : "Rodriguez_Ricardo",
  "imports" : [ ]
}, {
  "name" : "Borgonovo_Esteban",
  "imports" : [ ]
}, {
  "name" : "Asensio_Carlos",
  "imports" : [ ]
}, {
  "name" : "Dominguez_Elba_E",
  "imports" : [ "Carranza_Alberto" ]
}, {
  "name" : "Carranza_Alberto",
  "imports" : [ ]
}, {
  "name" : "Castruccio_Daniel",
  "imports" : [ "Cubero_Schiaffino_Jorge", "Castruccio_Daniel_Osvaldo" ]
}, {
  "name" : "Cubero_Schiaffino_Jorge",
  "imports" : [ ]
}, {
  "name" : "Castruccio_Daniel_Osvaldo",
  "imports" : [ ]
}, {
  "name" : "Piscitelli_Alejandro_Gustavo",
  "imports" : [ "Filmus_Daniel", "Huergo_Hernan", "Urbina_Marzoa" ]
}, {
  "name" : "Filmus_Daniel",
  "imports" : [ ]
}, {
  "name" : "Huergo_Hernan",
  "imports" : [ ]
}, {
  "name" : "Urbina_Marzoa",
  "imports" : [ ]
}, {
  "name" : "Sozio_Torcuato",
  "imports" : [ "Tomasov_Jorge", "Dominguez_Maria_Laura" ]
}, {
  "name" : "Tomasov_Jorge",
  "imports" : [ ]
}, {
  "name" : "Dominguez_Maria_Laura",
  "imports" : [ ]
}, {
  "name" : "Ochoa_Romero_Pedro",
  "imports" : [ "Minini_Juan", "Papicio_Jorge", "Palumbo_Mauricio" ]
}, {
  "name" : "Minini_Juan",
  "imports" : [ ]
}, {
  "name" : "Papicio_Jorge",
  "imports" : [ ]
}, {
  "name" : "Palumbo_Mauricio",
  "imports" : [ ]
}, {
  "name" : "Lucero_Marcos",
  "imports" : [ "Lucero_Marcos_Obdulio" ]
}, {
  "name" : "Lucero_Marcos_Obdulio",
  "imports" : [ ]
}, {
  "name" : "Bartolucci_Maria_Cristina",
  "imports" : [ "Giannetto_Maximiliano", "Bianchi_Maria_del_Carmen", "Jacovkis_Pablo_Miguel", "Perez_Gollan_Jose_Antonio", "Barcena_Roberto", "Etcheverry_Ricardo_Oscar" ]
}, {
  "name" : "Giannetto_Maximiliano",
  "imports" : [ ]
}, {
  "name" : "Bianchi_Maria_del_Carmen",
  "imports" : [ ]
}, {
  "name" : "Jacovkis_Pablo_Miguel",
  "imports" : [ ]
}, {
  "name" : "Perez_Gollan_Jose_Antonio",
  "imports" : [ ]
}, {
  "name" : "Barcena_Roberto",
  "imports" : [ ]
}, {
  "name" : "Etcheverry_Ricardo_Oscar",
  "imports" : [ ]
}, {
  "name" : "Sardella_Rafael",
  "imports" : [ "Ferraro_Ricardo" ]
}, {
  "name" : "Ferraro_Ricardo",
  "imports" : [ ]
}, {
  "name" : "Radic_Adrian",
  "imports" : [ "Hidalgo_Jose_Amador" ]
}, {
  "name" : "Hidalgo_Jose_Amador",
  "imports" : [ ]
}, {
  "name" : "Fuks_Gabriel_Marcelo",
  "imports" : [ "Vazquez_Licenciado", "Vicente_Silvia", "Damiani_Jorge", "Fappiano_Omar", "Carcamo_Juan_Carlos", "Azcurra_Jose", "Amura_Alejandro", "De_Paoli_Carlos", "Vennera_Horacio", "Munoz_Carlos" ]
}, {
  "name" : "Vazquez_Licenciado",
  "imports" : [ ]
}, {
  "name" : "Vicente_Silvia",
  "imports" : [ ]
}, {
  "name" : "Damiani_Jorge",
  "imports" : [ ]
}, {
  "name" : "Fappiano_Omar",
  "imports" : [ ]
}, {
  "name" : "Carcamo_Juan_Carlos",
  "imports" : [ ]
}, {
  "name" : "Azcurra_Jose",
  "imports" : [ ]
}, {
  "name" : "Amura_Alejandro",
  "imports" : [ ]
}, {
  "name" : "De_Paoli_Carlos",
  "imports" : [ ]
}, {
  "name" : "Vennera_Horacio",
  "imports" : [ ]
}, {
  "name" : "Munoz_Carlos",
  "imports" : [ ]
}, {
  "name" : "Namuncura_Ceferino",
  "imports" : [ "Virasoro_Blanca", "Oriente_Mario", "Di_Pasquo_Alejandro_Maria" ]
}, {
  "name" : "Virasoro_Blanca",
  "imports" : [ ]
}, {
  "name" : "Oriente_Mario",
  "imports" : [ ]
}, {
  "name" : "Di_Pasquo_Alejandro_Maria",
  "imports" : [ ]
}, {
  "name" : "Filmus_Daniel_Fernando",
  "imports" : [ "Romero_Sergio", "Bordoni_Ingrid_Beatriz", "Piscitelli_Alejandro", "Isturiz_Martin_A", "Hughes_John", "Blanco_Mercedes", "Grunblatt_Tzvi", "Spairani_Anibal", "Benyacard_-" ]
}, {
  "name" : "Romero_Sergio",
  "imports" : [ ]
}, {
  "name" : "Bordoni_Ingrid_Beatriz",
  "imports" : [ ]
}, {
  "name" : "Piscitelli_Alejandro",
  "imports" : [ ]
}, {
  "name" : "Isturiz_Martin_A",
  "imports" : [ ]
}, {
  "name" : "Hughes_John",
  "imports" : [ ]
}, {
  "name" : "Blanco_Mercedes",
  "imports" : [ ]
}, {
  "name" : "Grunblatt_Tzvi",
  "imports" : [ ]
}, {
  "name" : "Spairani_Anibal",
  "imports" : [ ]
}, {
  "name" : "Benyacard_-",
  "imports" : [ ]
}, {
  "name" : "Nun_Jose",
  "imports" : [ "Moujan_Carlos_Cesar", "Yi_Zhang", "Diaz_Anibal", "De_Lajonquiere_Nelson", "Bauer_Tristan", "Sanchez_Pena_Miguel", "Isella_Cesar" ]
}, {
  "name" : "Moujan_Carlos_Cesar",
  "imports" : [ ]
}, {
  "name" : "Yi_Zhang",
  "imports" : [ ]
}, {
  "name" : "Diaz_Anibal",
  "imports" : [ ]
}, {
  "name" : "De_Lajonquiere_Nelson",
  "imports" : [ ]
}, {
  "name" : "Sanchez_Pena_Miguel",
  "imports" : [ ]
}, {
  "name" : "Isella_Cesar",
  "imports" : [ ]
}, {
  "name" : "Frydman_Felipe",
  "imports" : [ "Martinez_Estela_Maris" ]
}, {
  "name" : "Martinez_Estela_Maris",
  "imports" : [ ]
}, {
  "name" : "Vessvessian_Marcela_Paola",
  "imports" : [ "Pareja_Enrique", "Gilitchensky_Eugenia", "Vargas_Duran_Facundo", "Suarez_Raquel_Adriana" ]
}, {
  "name" : "Pareja_Enrique",
  "imports" : [ ]
}, {
  "name" : "Gilitchensky_Eugenia",
  "imports" : [ ]
}, {
  "name" : "Vargas_Duran_Facundo",
  "imports" : [ ]
}, {
  "name" : "Suarez_Raquel_Adriana",
  "imports" : [ ]
}, {
  "name" : "Franco_Leonardo",
  "imports" : [ "Listre_Arnoldo", "Lopez_Ernesto", "Serrano_Jose_Rafael", "Viaje_en_Mision_Oficial", "Reunion_Directores", "Zanutigh_Adriana" ]
}, {
  "name" : "Listre_Arnoldo",
  "imports" : [ ]
}, {
  "name" : "Lopez_Ernesto",
  "imports" : [ ]
}, {
  "name" : "Serrano_Jose_Rafael",
  "imports" : [ ]
}, {
  "name" : "Viaje_en_Mision_Oficial",
  "imports" : [ ]
}, {
  "name" : "Reunion_Directores",
  "imports" : [ ]
}, {
  "name" : "Zanutigh_Adriana",
  "imports" : [ ]
}, {
  "name" : "Roncero_Jessica",
  "imports" : [ "Maldonado_Stella_Maris", "Pigna_Felipe" ]
}, {
  "name" : "Maldonado_Stella_Maris",
  "imports" : [ ]
}, {
  "name" : "Pigna_Felipe",
  "imports" : [ ]
}, {
  "name" : "Haczek_Gustavo_Gerardo",
  "imports" : [ "Alonso_Diego" ]
}, {
  "name" : "Alonso_Diego",
  "imports" : [ ]
}, {
  "name" : "De_Vido_Julio_M",
  "imports" : [ "Presidencia_De_la_Nacion", "Joubert_Philippe", "Lopez_Jose", "Posse_Gustavo", "Cameron_Daniel", "Schiaretti_Juan", "Madaro_Fulvio", "Muguerza_Daniel", "Peris_Antoni", "Namuncura_Ceferino", "Pena_Nestor", "Abriata_Pablo", "Porras_Alfredo", "Jaime_Ricardo", "Capitanich_Jorge", "De_la_Sota_Jose_Manuel", "Picheto_Miguel_Angel", "Busti_Jorge", "Folgar_Cristian" ]
}, {
  "name" : "Presidencia_De_la_Nacion",
  "imports" : [ ]
}, {
  "name" : "Joubert_Philippe",
  "imports" : [ ]
}, {
  "name" : "Posse_Gustavo",
  "imports" : [ ]
}, {
  "name" : "Cameron_Daniel",
  "imports" : [ ]
}, {
  "name" : "Schiaretti_Juan",
  "imports" : [ ]
}, {
  "name" : "Madaro_Fulvio",
  "imports" : [ ]
}, {
  "name" : "Muguerza_Daniel",
  "imports" : [ ]
}, {
  "name" : "Peris_Antoni",
  "imports" : [ ]
}, {
  "name" : "Pena_Nestor",
  "imports" : [ ]
}, {
  "name" : "Abriata_Pablo",
  "imports" : [ ]
}, {
  "name" : "Porras_Alfredo",
  "imports" : [ ]
}, {
  "name" : "Capitanich_Jorge",
  "imports" : [ ]
}, {
  "name" : "De_la_Sota_Jose_Manuel",
  "imports" : [ ]
}, {
  "name" : "Picheto_Miguel_Angel",
  "imports" : [ ]
}, {
  "name" : "Busti_Jorge",
  "imports" : [ ]
}, {
  "name" : "Folgar_Cristian",
  "imports" : [ ]
}, {
  "name" : "Fleitas_Ortiz_de_Rozas_Abel",
  "imports" : [ "Curia_Eugenio", "Pappalardo_Juan", "Pena_Federico", "Abiad_Pablo", "Mallea_Eduardo", "Sietecase_Reynaldo", "Plaza_Martin_Ignacio", "Pedretti_Ruben_Alfredo", "Quassolo_Luis_Antonio", "Fidel_Gabriel" ]
}, {
  "name" : "Curia_Eugenio",
  "imports" : [ ]
}, {
  "name" : "Pappalardo_Juan",
  "imports" : [ ]
}, {
  "name" : "Pena_Federico",
  "imports" : [ ]
}, {
  "name" : "Abiad_Pablo",
  "imports" : [ ]
}, {
  "name" : "Mallea_Eduardo",
  "imports" : [ ]
}, {
  "name" : "Sietecase_Reynaldo",
  "imports" : [ ]
}, {
  "name" : "Plaza_Martin_Ignacio",
  "imports" : [ ]
}, {
  "name" : "Pedretti_Ruben_Alfredo",
  "imports" : [ ]
}, {
  "name" : "Quassolo_Luis_Antonio",
  "imports" : [ ]
}, {
  "name" : "Fidel_Gabriel",
  "imports" : [ ]
}, {
  "name" : "Gutierrez_Anibal_Gabriel",
  "imports" : [ "Stok_Capella_Jorge", "Estrella_Miguel_Angel_Embajador", "Mallea_Eduardo__Ministro", "Duhalde_Eduardo", "Reunion_Coordinacion_Cumbre_de_las_Americas", "Firma_de_Acuerdo_Constitucion_Comite_Auditoria_de_Cancilleria", "Recepcion_En_Embajada_de_Grecia", "Firma_de_Convenio_Fundacion_Alemana", "Viaje_en_Mision_Oficial_Al_Reino_de_Marruecos", "Viaje_en_Mision_Oficial" ]
}, {
  "name" : "Stok_Capella_Jorge",
  "imports" : [ ]
}, {
  "name" : "Estrella_Miguel_Angel_Embajador",
  "imports" : [ ]
}, {
  "name" : "Mallea_Eduardo__Ministro",
  "imports" : [ ]
}, {
  "name" : "Duhalde_Eduardo",
  "imports" : [ ]
}, {
  "name" : "Reunion_Coordinacion_Cumbre_de_las_Americas",
  "imports" : [ ]
}, {
  "name" : "Firma_de_Acuerdo_Constitucion_Comite_Auditoria_de_Cancilleria",
  "imports" : [ ]
}, {
  "name" : "Recepcion_En_Embajada_de_Grecia",
  "imports" : [ ]
}, {
  "name" : "Firma_de_Convenio_Fundacion_Alemana",
  "imports" : [ ]
}, {
  "name" : "Viaje_en_Mision_Oficial_Al_Reino_de_Marruecos",
  "imports" : [ ]
}, {
  "name" : "Deibe_Adolfo_Enrique",
  "imports" : [ "Tangelson_Pablo", "Pineyrua_Ana_Lia", "Muller_Lucia", "Motessi_Ricardo_Alberto" ]
}, {
  "name" : "Tangelson_Pablo",
  "imports" : [ ]
}, {
  "name" : "Pineyrua_Ana_Lia",
  "imports" : [ ]
}, {
  "name" : "Muller_Lucia",
  "imports" : [ ]
}, {
  "name" : "Motessi_Ricardo_Alberto",
  "imports" : [ ]
}, {
  "name" : "Elordi_Susana",
  "imports" : [ "Schwiter_Mario", "Alvarez_Jose_Maria", "Abib_Emiliano" ]
}, {
  "name" : "Schwiter_Mario",
  "imports" : [ ]
}, {
  "name" : "Alvarez_Jose_Maria",
  "imports" : [ ]
}, {
  "name" : "Abib_Emiliano",
  "imports" : [ ]
}, {
  "name" : "Bender_Gloria_Raquel",
  "imports" : [ "Rachess_Cesar_Osvaldo", "Baglietto_Mireya", "Arrieta_de_Blaquier_Nelly", "Rosemberg_Adriana", "Banegas_Cristina", "Ons_Melina", "Espel_Guillermo", "Feldman_Norberto" ]
}, {
  "name" : "Rachess_Cesar_Osvaldo",
  "imports" : [ ]
}, {
  "name" : "Baglietto_Mireya",
  "imports" : [ ]
}, {
  "name" : "Arrieta_de_Blaquier_Nelly",
  "imports" : [ ]
}, {
  "name" : "Rosemberg_Adriana",
  "imports" : [ ]
}, {
  "name" : "Banegas_Cristina",
  "imports" : [ ]
}, {
  "name" : "Ons_Melina",
  "imports" : [ ]
}, {
  "name" : "Espel_Guillermo",
  "imports" : [ ]
}, {
  "name" : "Feldman_Norberto",
  "imports" : [ ]
}, {
  "name" : "Di_Cola_Eduardo_Roman",
  "imports" : [ "Saavedra_Ignacio", "Caride_Horacio", "De_Miguel_Benito" ]
}, {
  "name" : "Saavedra_Ignacio",
  "imports" : [ ]
}, {
  "name" : "Caride_Horacio",
  "imports" : [ ]
}, {
  "name" : "De_Miguel_Benito",
  "imports" : [ ]
}, {
  "name" : "Verta_Gustavo",
  "imports" : [ "Martinez_Oscar" ]
}, {
  "name" : "Martinez_Oscar",
  "imports" : [ ]
}, {
  "name" : "Martinez_de_Jimenez_Lidia_Mabel",
  "imports" : [ "Meisegeier_Jose_M", "Gonzalez_Roxana", "Samper_Alicia", "De_Felippe_Oscar" ]
}, {
  "name" : "Meisegeier_Jose_M",
  "imports" : [ ]
}, {
  "name" : "Gonzalez_Roxana",
  "imports" : [ ]
}, {
  "name" : "Samper_Alicia",
  "imports" : [ ]
}, {
  "name" : "De_Felippe_Oscar",
  "imports" : [ ]
}, {
  "name" : "Pugliese_Juan_Carlos",
  "imports" : [ "Tiramonti_Guillermina", "Dulevich_Uzal_Ariel", "Lobo_Pedro_W", "Fernandez_Carlos", "Damonte_Ricardo", "Pechen_D<U+00B4>Angelo_Ana_Maria", "Maiztegui_Alberto", "Barrachina_Raul", "Cormons_Alejandra", "Rueda_Susana", "Seiler_Roberto", "Rubini_Mirta", "Abad_Maximiliano", "Masco_Alejandro", "Bibiloni_Anibal", "Porras_Jose", "Perez_Lindo_Augusto" ]
}, {
  "name" : "Dulevich_Uzal_Ariel",
  "imports" : [ ]
}, {
  "name" : "Lobo_Pedro_W",
  "imports" : [ ]
}, {
  "name" : "Fernandez_Carlos",
  "imports" : [ ]
}, {
  "name" : "Damonte_Ricardo",
  "imports" : [ ]
}, {
  "name" : "Pechen_D<U+00B4>Angelo_Ana_Maria",
  "imports" : [ ]
}, {
  "name" : "Maiztegui_Alberto",
  "imports" : [ ]
}, {
  "name" : "Barrachina_Raul",
  "imports" : [ ]
}, {
  "name" : "Cormons_Alejandra",
  "imports" : [ ]
}, {
  "name" : "Rueda_Susana",
  "imports" : [ ]
}, {
  "name" : "Seiler_Roberto",
  "imports" : [ ]
}, {
  "name" : "Rubini_Mirta",
  "imports" : [ ]
}, {
  "name" : "Abad_Maximiliano",
  "imports" : [ ]
}, {
  "name" : "Masco_Alejandro",
  "imports" : [ ]
}, {
  "name" : "Bibiloni_Anibal",
  "imports" : [ ]
}, {
  "name" : "Porras_Jose",
  "imports" : [ ]
}, {
  "name" : "Dorrego_Sergio",
  "imports" : [ "Farinari_Horacio_Alberto", "Salas_Lisando", "Contessi_Federico", "Suarez_Enrique_Omar" ]
}, {
  "name" : "Farinari_Horacio_Alberto",
  "imports" : [ ]
}, {
  "name" : "Salas_Lisando",
  "imports" : [ ]
}, {
  "name" : "Contessi_Federico",
  "imports" : [ ]
}, {
  "name" : "Suarez_Enrique_Omar",
  "imports" : [ ]
}, {
  "name" : "DCastilla_Americo",
  "imports" : [ "Severi_Aldo", "Rocha_Dde_Einaudi_Maria", "Kutzcher_Slvia" ]
}, {
  "name" : "Severi_Aldo",
  "imports" : [ ]
}, {
  "name" : "Rocha_Dde_Einaudi_Maria",
  "imports" : [ ]
}, {
  "name" : "Kutzcher_Slvia",
  "imports" : [ ]
}, {
  "name" : "Garcia_Moritan_Roberto",
  "imports" : [ "Viaje_en_Mision_Oficial_-" ]
}, {
  "name" : "Viaje_en_Mision_Oficial_-",
  "imports" : [ ]
}, {
  "name" : "Sereno_Juan_Carlos",
  "imports" : [ "Ordonez_Lopez_Emilio", "Lovato_Alfredo", "Marin_Enrique", "Suazo_Sergio", "Padoan_Alberto", "Villian_Jose", "Clerici_Estela", "Carrizo_Jose", "Boasso_Jose_Ernesto", "Gonzalez_Roberto", "Rassol_Alberto", "Carnevale_Piedrabuena_Gustavo_Mario", "Gilbert_Armando", "Ibarlin_Andres", "Portillo_Mario_Luciano", "Rios_Dora" ]
}, {
  "name" : "Ordonez_Lopez_Emilio",
  "imports" : [ ]
}, {
  "name" : "Lovato_Alfredo",
  "imports" : [ ]
}, {
  "name" : "Marin_Enrique",
  "imports" : [ ]
}, {
  "name" : "Suazo_Sergio",
  "imports" : [ ]
}, {
  "name" : "Padoan_Alberto",
  "imports" : [ ]
}, {
  "name" : "Villian_Jose",
  "imports" : [ ]
}, {
  "name" : "Clerici_Estela",
  "imports" : [ ]
}, {
  "name" : "Carrizo_Jose",
  "imports" : [ ]
}, {
  "name" : "Boasso_Jose_Ernesto",
  "imports" : [ ]
}, {
  "name" : "Gonzalez_Roberto",
  "imports" : [ ]
}, {
  "name" : "Rassol_Alberto",
  "imports" : [ ]
}, {
  "name" : "Carnevale_Piedrabuena_Gustavo_Mario",
  "imports" : [ ]
}, {
  "name" : "Gilbert_Armando",
  "imports" : [ ]
}, {
  "name" : "Ibarlin_Andres",
  "imports" : [ ]
}, {
  "name" : "Portillo_Mario_Luciano",
  "imports" : [ ]
}, {
  "name" : "Rios_Dora",
  "imports" : [ ]
}, {
  "name" : "Martin_Daniel_Eduardo",
  "imports" : [ "Squivo_Oscar_Ruben", "Cabullo_Mirtha_A", "Chevez_Hugo_A", "De_Franco_Osvaldo_Mariano" ]
}, {
  "name" : "Squivo_Oscar_Ruben",
  "imports" : [ ]
}, {
  "name" : "Cabullo_Mirtha_A",
  "imports" : [ ]
}, {
  "name" : "Chevez_Hugo_A",
  "imports" : [ ]
}, {
  "name" : "De_Franco_Osvaldo_Mariano",
  "imports" : [ ]
}, {
  "name" : "Kirchner_Alicia_Margarita",
  "imports" : [ "Pinheiro_Guimaraes_Samuel", "Mazza_Jorge", "Weretilneck_Alberto" ]
}, {
  "name" : "Pinheiro_Guimaraes_Samuel",
  "imports" : [ ]
}, {
  "name" : "Mazza_Jorge",
  "imports" : [ ]
}, {
  "name" : "Weretilneck_Alberto",
  "imports" : [ ]
}, {
  "name" : "Aguilera_Daniel_Pablo",
  "imports" : [ "Palacios_Marco", "Rodriguez_Alejandrdo", "Sierra_Manuel", "Estevez_Guillermo", "De_Salterain_Maria_Cecilia", "Stur_Adrian", "Agura_Silvia" ]
}, {
  "name" : "Rodriguez_Alejandrdo",
  "imports" : [ ]
}, {
  "name" : "Sierra_Manuel",
  "imports" : [ ]
}, {
  "name" : "Estevez_Guillermo",
  "imports" : [ ]
}, {
  "name" : "De_Salterain_Maria_Cecilia",
  "imports" : [ ]
}, {
  "name" : "Stur_Adrian",
  "imports" : [ ]
}, {
  "name" : "Agura_Silvia",
  "imports" : [ ]
}, {
  "name" : "Levati_Gustavo",
  "imports" : [ "Garcia_Caffi_Pedro", "Franco_Marcelo", "Berta_Gustavo", "Moreira_Eduardo", "Llano_Edgardo", "Giancarlos_Marta", "Saa_Gustavo", "Merlo_Susana", "Gentilli_Saul" ]
}, {
  "name" : "Garcia_Caffi_Pedro",
  "imports" : [ ]
}, {
  "name" : "Franco_Marcelo",
  "imports" : [ ]
}, {
  "name" : "Berta_Gustavo",
  "imports" : [ ]
}, {
  "name" : "Moreira_Eduardo",
  "imports" : [ ]
}, {
  "name" : "Llano_Edgardo",
  "imports" : [ ]
}, {
  "name" : "Giancarlos_Marta",
  "imports" : [ ]
}, {
  "name" : "Saa_Gustavo",
  "imports" : [ ]
}, {
  "name" : "Merlo_Susana",
  "imports" : [ ]
}, {
  "name" : "Gentilli_Saul",
  "imports" : [ ]
}, {
  "name" : "Orchansky_Alejandro",
  "imports" : [ "Romero_Oscar" ]
}, {
  "name" : "Romero_Oscar",
  "imports" : [ ]
}, {
  "name" : "Godoy_Jorge_Omar",
  "imports" : [ "Garcia_Enrique", "Graf_Helmut_Cristian", "Frers_Jose", "Bertone_Roxana", "Podetti_Raul", "Memoli_Mariano_Arnaldo", "Micheli_Pablo" ]
}, {
  "name" : "Garcia_Enrique",
  "imports" : [ ]
}, {
  "name" : "Graf_Helmut_Cristian",
  "imports" : [ ]
}, {
  "name" : "Frers_Jose",
  "imports" : [ ]
}, {
  "name" : "Podetti_Raul",
  "imports" : [ ]
}, {
  "name" : "Memoli_Mariano_Arnaldo",
  "imports" : [ ]
}, {
  "name" : "Micheli_Pablo",
  "imports" : [ ]
}, {
  "name" : "Cardoso_Jose_Camilo",
  "imports" : [ "Razetti_Horacio" ]
}, {
  "name" : "Razetti_Horacio",
  "imports" : [ ]
}, {
  "name" : "Paredes_de_Periotti_Liliana",
  "imports" : [ "Bost_Eric", "Giovanini_Sergio", "Martin_Maria_Isabel", "Leiva_Ma_Laura" ]
}, {
  "name" : "Giovanini_Sergio",
  "imports" : [ ]
}, {
  "name" : "Martin_Maria_Isabel",
  "imports" : [ ]
}, {
  "name" : "Leiva_Ma_Laura",
  "imports" : [ ]
}, {
  "name" : "Soratti_Carlos_Alberto",
  "imports" : [ "Sanchez_Marisa_Noemi" ]
}, {
  "name" : "Sanchez_Marisa_Noemi",
  "imports" : [ ]
}, {
  "name" : "Piccone_Nestor",
  "imports" : [ "Segura_Martin" ]
}, {
  "name" : "Segura_Martin",
  "imports" : [ ]
}, {
  "name" : "Alonso_Navone_Guillermo_Esteban_Jesus",
  "imports" : [ "Guerchi_Pablo", "Caligari_Mario_Eduardo", "Federico_Vicente", "Paz_Posse_Lucio", "Pro_Jorge_Horacio" ]
}, {
  "name" : "Guerchi_Pablo",
  "imports" : [ ]
}, {
  "name" : "Caligari_Mario_Eduardo",
  "imports" : [ ]
}, {
  "name" : "Federico_Vicente",
  "imports" : [ ]
}, {
  "name" : "Paz_Posse_Lucio",
  "imports" : [ ]
}, {
  "name" : "Pro_Jorge_Horacio",
  "imports" : [ ]
}, {
  "name" : "Berraondo_Ruben",
  "imports" : [ "Catardi_Carlos_Alberto" ]
}, {
  "name" : "Catardi_Carlos_Alberto",
  "imports" : [ ]
}, {
  "name" : "Lagana_Salvador",
  "imports" : [ "Martinez_Oscar", "Martinez_Monica", "Curuchet_Gabriel", "Raymond_Aldunate_Nelly", "Maiello_Mario" ]
}, {
  "name" : "Curuchet_Gabriel",
  "imports" : [ ]
}, {
  "name" : "Raymond_Aldunate_Nelly",
  "imports" : [ ]
}, {
  "name" : "Maiello_Mario",
  "imports" : [ ]
}, {
  "name" : "Nieto_Hector",
  "imports" : [ "Neffa_Julio" ]
}, {
  "name" : "Scioli_Daniel_Osvaldo",
  "imports" : [ "Oliveri_Guillermo_Rodolfo", "Stok_Capella_Jorge" ]
}, {
  "name" : "Navarro_Mariana",
  "imports" : [ "Yayoi_Sato" ]
}, {
  "name" : "Yayoi_Sato",
  "imports" : [ ]
}, {
  "name" : "Meyer_Carlos_Enrique",
  "imports" : [ "Pagano_Gustavo", "De_Salterain_Maria_Cecilia", "Fernandez_Dotzel_Marcelo", "Vander_Heyden_Miguel", "Sanguinetti_Roberto", "Serantes_Carlos", "Lavallen_Guillermo", "Galiser_Jose_Alberto", "Morresi_Claudio", "Icare_Alberto", "Persson_Ake", "Toha_Jaime", "Hammar_Klas", "Cederberg_Helena", "Forastieri_Franco", "Baldini_Ricardo", "Scaglione_Adolfo", "Boldovich_Jose", "Biondi_Esteban", "Paats_Willy", "Ryan_Tomas", "Lichter_Alfredo", "Llavallol_Arturo", "Beheran_Monica", "Gutierrez_Carlos", "Abolsky_Carlos", "Garramuno_Jorge", "Alkaddour_Omar", "Gabrielli_Daniel", "Vulletich_Jorge", "Susacasa_Ernesto", "Mendez_Nestor", "Sokolowicz_Fernando", "Guinsburg_Jorge", "Boente_Ricardo", "Dejean_Raul", "Kahlke_Eric" ]
}, {
  "name" : "Pagano_Gustavo",
  "imports" : [ ]
}, {
  "name" : "Fernandez_Dotzel_Marcelo",
  "imports" : [ ]
}, {
  "name" : "Vander_Heyden_Miguel",
  "imports" : [ ]
}, {
  "name" : "Sanguinetti_Roberto",
  "imports" : [ ]
}, {
  "name" : "Serantes_Carlos",
  "imports" : [ ]
}, {
  "name" : "Lavallen_Guillermo",
  "imports" : [ ]
}, {
  "name" : "Galiser_Jose_Alberto",
  "imports" : [ ]
}, {
  "name" : "Morresi_Claudio",
  "imports" : [ ]
}, {
  "name" : "Persson_Ake",
  "imports" : [ ]
}, {
  "name" : "Toha_Jaime",
  "imports" : [ ]
}, {
  "name" : "Hammar_Klas",
  "imports" : [ ]
}, {
  "name" : "Cederberg_Helena",
  "imports" : [ ]
}, {
  "name" : "Forastieri_Franco",
  "imports" : [ ]
}, {
  "name" : "Baldini_Ricardo",
  "imports" : [ ]
}, {
  "name" : "Boldovich_Jose",
  "imports" : [ ]
}, {
  "name" : "Biondi_Esteban",
  "imports" : [ ]
}, {
  "name" : "Paats_Willy",
  "imports" : [ ]
}, {
  "name" : "Ryan_Tomas",
  "imports" : [ ]
}, {
  "name" : "Lichter_Alfredo",
  "imports" : [ ]
}, {
  "name" : "Llavallol_Arturo",
  "imports" : [ ]
}, {
  "name" : "Beheran_Monica",
  "imports" : [ ]
}, {
  "name" : "Gutierrez_Carlos",
  "imports" : [ ]
}, {
  "name" : "Abolsky_Carlos",
  "imports" : [ ]
}, {
  "name" : "Garramuno_Jorge",
  "imports" : [ ]
}, {
  "name" : "Alkaddour_Omar",
  "imports" : [ ]
}, {
  "name" : "Gabrielli_Daniel",
  "imports" : [ ]
}, {
  "name" : "Vulletich_Jorge",
  "imports" : [ ]
}, {
  "name" : "Susacasa_Ernesto",
  "imports" : [ ]
}, {
  "name" : "Mendez_Nestor",
  "imports" : [ ]
}, {
  "name" : "Sokolowicz_Fernando",
  "imports" : [ ]
}, {
  "name" : "Guinsburg_Jorge",
  "imports" : [ ]
}, {
  "name" : "Boente_Ricardo",
  "imports" : [ ]
}, {
  "name" : "Dejean_Raul",
  "imports" : [ ]
}, {
  "name" : "Kahlke_Eric",
  "imports" : [ ]
}, {
  "name" : "Garcia_Cuerva_Mariano",
  "imports" : [ "Severi_Alfredo" ]
}, {
  "name" : "Severi_Alfredo",
  "imports" : [ ]
}, {
  "name" : "Nogues_Lascano_Gaston",
  "imports" : [ "Garay_Graciela", "Cartabbia_Vicente" ]
}, {
  "name" : "Garay_Graciela",
  "imports" : [ ]
}, {
  "name" : "Cartabbia_Vicente",
  "imports" : [ ]
}, {
  "name" : "Pampuro_Jose_Juan_Bautista",
  "imports" : [ "Gutierrez_Lino", "Schiaffino_Eduardo_Augusto", "Hughes_John", "Nisar_Mohammad" ]
}, {
  "name" : "Gutierrez_Lino",
  "imports" : [ ]
}, {
  "name" : "Nisar_Mohammad",
  "imports" : [ ]
}, {
  "name" : "Dr_Gelly_Cantilo_Alberto",
  "imports" : [ "Torres_Juan_Lucio", "Alfonsin_Jorge_Juan", "Schavelzon_Daniel", "Rios_Ernesto_Adolfo", "Castex_Cesar_Maria", "Cerolini_Fernando", "Perri_Serafina" ]
}, {
  "name" : "Torres_Juan_Lucio",
  "imports" : [ ]
}, {
  "name" : "Alfonsin_Jorge_Juan",
  "imports" : [ ]
}, {
  "name" : "Schavelzon_Daniel",
  "imports" : [ ]
}, {
  "name" : "Rios_Ernesto_Adolfo",
  "imports" : [ ]
}, {
  "name" : "Castex_Cesar_Maria",
  "imports" : [ ]
}, {
  "name" : "Cerolini_Fernando",
  "imports" : [ ]
}, {
  "name" : "Perri_Serafina",
  "imports" : [ ]
}, {
  "name" : "Lenzberg_Alejandro_Cesar",
  "imports" : [ "Scoltore_Fabian", "Barreiro_Horacio", "Faerstein_Adhemar", "Lerner_Eduardo", "Garcia_Ziella_Daniel", "Pont_Lezica_Santiago", "Martinez_Raquel", "Ezcurra_Federico", "Federovisky_Sergio", "Ferragut_Nara" ]
}, {
  "name" : "Scoltore_Fabian",
  "imports" : [ ]
}, {
  "name" : "Barreiro_Horacio",
  "imports" : [ ]
}, {
  "name" : "Faerstein_Adhemar",
  "imports" : [ ]
}, {
  "name" : "Lerner_Eduardo",
  "imports" : [ ]
}, {
  "name" : "Garcia_Ziella_Daniel",
  "imports" : [ ]
}, {
  "name" : "Pont_Lezica_Santiago",
  "imports" : [ ]
}, {
  "name" : "Martinez_Raquel",
  "imports" : [ ]
}, {
  "name" : "Ezcurra_Federico",
  "imports" : [ ]
}, {
  "name" : "Federovisky_Sergio",
  "imports" : [ ]
}, {
  "name" : "Ferragut_Nara",
  "imports" : [ ]
}, {
  "name" : "Villareal_Norma_Beatriz",
  "imports" : [ "Perez_Pablo" ]
}, {
  "name" : "Perez_Pablo",
  "imports" : [ ]
}, {
  "name" : "Kunkel_Carlos_Miguel",
  "imports" : [ "Pereira_Analia_Haydee", "Zanoli_Oscar", "Huarte_Ricardo_Hector", "Vazzano_Hector", "Fernandez_Victor" ]
}, {
  "name" : "Pereira_Analia_Haydee",
  "imports" : [ ]
}, {
  "name" : "Zanoli_Oscar",
  "imports" : [ ]
}, {
  "name" : "Huarte_Ricardo_Hector",
  "imports" : [ ]
}, {
  "name" : "Vazzano_Hector",
  "imports" : [ ]
}, {
  "name" : "Fernandez_Victor",
  "imports" : [ ]
}, {
  "name" : "Odasso_Carmen",
  "imports" : [ "Granovsky_Marta", "Lagana_Salvador" ]
}, {
  "name" : "Granovsky_Marta",
  "imports" : [ ]
}, {
  "name" : "Raigorodsky_Nicolas",
  "imports" : [ "Asselin_Lynnette", "Quaglio_Carlos", "Penalillo_Miguel", "Fidel_Gabriel", "Pena_Federico" ]
}, {
  "name" : "Asselin_Lynnette",
  "imports" : [ ]
}, {
  "name" : "Quaglio_Carlos",
  "imports" : [ ]
}, {
  "name" : "Penalillo_Miguel",
  "imports" : [ ]
}, {
  "name" : "Fernandez_Novoa_Sergio",
  "imports" : [ "Rodriguez_Villafane_Miguel_Julio", "Pellitero_Ramilo_Laudelino", "Matus_Javier", "Alvis_Omar", "Cattaneo_Javier", "Iglesias_Martin", "Pachecoy_Susana", "Cozzi_Angel", "Brennan_Roberto", "Vivero_Carlos_Alberto", "Schenone_Luis" ]
}, {
  "name" : "Rodriguez_Villafane_Miguel_Julio",
  "imports" : [ ]
}, {
  "name" : "Pellitero_Ramilo_Laudelino",
  "imports" : [ ]
}, {
  "name" : "Matus_Javier",
  "imports" : [ ]
}, {
  "name" : "Alvis_Omar",
  "imports" : [ ]
}, {
  "name" : "Cattaneo_Javier",
  "imports" : [ ]
}, {
  "name" : "Iglesias_Martin",
  "imports" : [ ]
}, {
  "name" : "Pachecoy_Susana",
  "imports" : [ ]
}, {
  "name" : "Vivero_Carlos_Alberto",
  "imports" : [ ]
}, {
  "name" : "Schenone_Luis",
  "imports" : [ ]
}, {
  "name" : "Rodriguez_Carlos_Anibal",
  "imports" : [ "Duarte_Victor", "Saucedo_Jose", "Geneiro_Americo", "Micheli_Pablo", "Cantarinos_Nestor", "Guerra_Nestor", "Izquierdo_Jorge_Alberto", "Martinez_Deolidia", "Cruzate_Jorge", "Quiroga_Alberto", "Hoyos_Angel_Alfredo" ]
}, {
  "name" : "Duarte_Victor",
  "imports" : [ ]
}, {
  "name" : "Saucedo_Jose",
  "imports" : [ ]
}, {
  "name" : "Geneiro_Americo",
  "imports" : [ ]
}, {
  "name" : "Guerra_Nestor",
  "imports" : [ ]
}, {
  "name" : "Izquierdo_Jorge_Alberto",
  "imports" : [ ]
}, {
  "name" : "Martinez_Deolidia",
  "imports" : [ ]
}, {
  "name" : "Cruzate_Jorge",
  "imports" : [ ]
}, {
  "name" : "Quiroga_Alberto",
  "imports" : [ ]
}, {
  "name" : "Hoyos_Angel_Alfredo",
  "imports" : [ ]
}, {
  "name" : "Tomada_Carlos_Alfonso",
  "imports" : [ "Moreyra_Domingo", "Duarte_Rosalia", "Fabre_Maximiliano", "Camano_Hugo", "Renda_Pedro", "Vazquez_Juan_Carlos", "Cortes_Cecilia", "Altuve_Ada", "Centofante_Mariana_Carolina", "Arias_Graciela", "Alcaraz_Alicia_Amanda", "Morales_Luis", "Videla_Luis_Felipe", "Escudero_Sonia", "Burgos_Mario", "Pedraza_Jose", "Garcia_Rodolfo_Alcides", "Aiello_Ana_Ines", "Basteiro_Ariel", "Espinoza_Nestor_Miguel", "Samayoa_Juan_Adrian", "Suarez_Claudio", "Corvalan_Juan_Pedro", "Amichetti_Hector", "Mussano_Maria_Cristina", "Kusema_Liliana", "Pappalardo_Juan", "Quiroga_Miguel", "Fernandez_Luis_Alberto", "Villaverde_Eduardo", "Cuello_Juan_Carlos", "Cigliutti_Cesar", "Rojas_Oscar", "Apicella_Rafael", "Hammar_Olga", "Tangelson_Pablo", "Bielsa_Rafael", "Vicente_Oscar", "Abascal_Carlos", "Kirchner_Nestor", "Censi_Luis", "Cornide_Osvaldo", "Bonomi_Eduardo", "Amstutuz_Guillermo", "Masi_Nicolas_Alberto", "Al_Sineh_Riad", "Diaz_Victor", "Carranza_Pedro_Pablo", "Bengolea_Jorge_Domingo", "Nicolini_Daniel", "Mosquera_Maria_Jesus", "Nicolini_Daniel_Oscar", "Mrabet_de_Labidi_Hamila", "Motessi_Ricardo_Alberto", "Pistoia_Gabino", "Cabrera_Raul_Hernan" ]
}, {
  "name" : "Moreyra_Domingo",
  "imports" : [ ]
}, {
  "name" : "Duarte_Rosalia",
  "imports" : [ ]
}, {
  "name" : "Fabre_Maximiliano",
  "imports" : [ ]
}, {
  "name" : "Camano_Hugo",
  "imports" : [ ]
}, {
  "name" : "Vazquez_Juan_Carlos",
  "imports" : [ ]
}, {
  "name" : "Cortes_Cecilia",
  "imports" : [ ]
}, {
  "name" : "Altuve_Ada",
  "imports" : [ ]
}, {
  "name" : "Centofante_Mariana_Carolina",
  "imports" : [ ]
}, {
  "name" : "Arias_Graciela",
  "imports" : [ ]
}, {
  "name" : "Alcaraz_Alicia_Amanda",
  "imports" : [ ]
}, {
  "name" : "Videla_Luis_Felipe",
  "imports" : [ ]
}, {
  "name" : "Escudero_Sonia",
  "imports" : [ ]
}, {
  "name" : "Burgos_Mario",
  "imports" : [ ]
}, {
  "name" : "Garcia_Rodolfo_Alcides",
  "imports" : [ ]
}, {
  "name" : "Aiello_Ana_Ines",
  "imports" : [ ]
}, {
  "name" : "Basteiro_Ariel",
  "imports" : [ ]
}, {
  "name" : "Espinoza_Nestor_Miguel",
  "imports" : [ ]
}, {
  "name" : "Samayoa_Juan_Adrian",
  "imports" : [ ]
}, {
  "name" : "Suarez_Claudio",
  "imports" : [ ]
}, {
  "name" : "Corvalan_Juan_Pedro",
  "imports" : [ ]
}, {
  "name" : "Mussano_Maria_Cristina",
  "imports" : [ ]
}, {
  "name" : "Kusema_Liliana",
  "imports" : [ ]
}, {
  "name" : "Fernandez_Luis_Alberto",
  "imports" : [ ]
}, {
  "name" : "Villaverde_Eduardo",
  "imports" : [ ]
}, {
  "name" : "Cuello_Juan_Carlos",
  "imports" : [ ]
}, {
  "name" : "Rojas_Oscar",
  "imports" : [ ]
}, {
  "name" : "Apicella_Rafael",
  "imports" : [ ]
}, {
  "name" : "Bielsa_Rafael",
  "imports" : [ ]
}, {
  "name" : "Vicente_Oscar",
  "imports" : [ ]
}, {
  "name" : "Abascal_Carlos",
  "imports" : [ ]
}, {
  "name" : "Censi_Luis",
  "imports" : [ ]
}, {
  "name" : "Bonomi_Eduardo",
  "imports" : [ ]
}, {
  "name" : "Amstutuz_Guillermo",
  "imports" : [ ]
}, {
  "name" : "Masi_Nicolas_Alberto",
  "imports" : [ ]
}, {
  "name" : "Al_Sineh_Riad",
  "imports" : [ ]
}, {
  "name" : "Diaz_Victor",
  "imports" : [ ]
}, {
  "name" : "Carranza_Pedro_Pablo",
  "imports" : [ ]
}, {
  "name" : "Bengolea_Jorge_Domingo",
  "imports" : [ ]
}, {
  "name" : "Nicolini_Daniel",
  "imports" : [ ]
}, {
  "name" : "Mosquera_Maria_Jesus",
  "imports" : [ ]
}, {
  "name" : "Nicolini_Daniel_Oscar",
  "imports" : [ ]
}, {
  "name" : "Mrabet_de_Labidi_Hamila",
  "imports" : [ ]
}, {
  "name" : "Pistoia_Gabino",
  "imports" : [ ]
}, {
  "name" : "Cabrera_Raul_Hernan",
  "imports" : [ ]
}, {
  "name" : "Parrilli_Oscar",
  "imports" : [ "Fernandez_Jorge", "Gbione_Luis", "Chafi_Omar", "Bordon_Luis", "Galvan_Osmar_Eduardo", "Feldhein_Ricardo", "Schonfeld_de_Bru_Rosa", "Galera_Bernabe_Julian", "Irigoyen_Jose_Daniel", "Zandona_Juan_Alberto", "Delfino_Juan_Antonio", "Weretineck_Alberto" ]
}, {
  "name" : "Fernandez_Jorge",
  "imports" : [ ]
}, {
  "name" : "Gbione_Luis",
  "imports" : [ ]
}, {
  "name" : "Chafi_Omar",
  "imports" : [ ]
}, {
  "name" : "Bordon_Luis",
  "imports" : [ ]
}, {
  "name" : "Galvan_Osmar_Eduardo",
  "imports" : [ ]
}, {
  "name" : "Feldhein_Ricardo",
  "imports" : [ ]
}, {
  "name" : "Schonfeld_de_Bru_Rosa",
  "imports" : [ ]
}, {
  "name" : "Galera_Bernabe_Julian",
  "imports" : [ ]
}, {
  "name" : "Irigoyen_Jose_Daniel",
  "imports" : [ ]
}, {
  "name" : "Zandona_Juan_Alberto",
  "imports" : [ ]
}, {
  "name" : "Delfino_Juan_Antonio",
  "imports" : [ ]
}, {
  "name" : "Weretineck_Alberto",
  "imports" : [ ]
}, {
  "name" : "Rohde_Carlos_Alberto",
  "imports" : [ "Krymov_I", "Duhalde_Luis", "Caceres_Angel_Dario_Benetiz", "Deluchi_Marta", "Lic_Ottegui", "Comite_Franco-Arg_-" ]
}, {
  "name" : "Krymov_I",
  "imports" : [ ]
}, {
  "name" : "Duhalde_Luis",
  "imports" : [ ]
}, {
  "name" : "Caceres_Angel_Dario_Benetiz",
  "imports" : [ ]
}, {
  "name" : "Lic_Ottegui",
  "imports" : [ ]
}, {
  "name" : "Comite_Franco-Arg_-",
  "imports" : [ ]
} ]